Workbook
Name IQ_CH: 110000
Name IQ_CQ: 5000
Name IQ_CY: 10000
Name IQ_DAILY: 500000
Name IQ_FH: 100000
Name IQ_FQ: 500
Name IQ_FY: 1000
Name IQ_LTM: 2000
Name IQ_MONTH: 15000
Name IQ_NTM: 6000
Name IQ_WEEK: 50000
Name IQ_YTD: 3000

Sheet Input Sheet
B4: Please provide the below inputs
B6: Name of the Company | C6: Bluestar Ltd
B8: WACC Inputs
B9: Country | C9: India
B10: Local Currency 10Y Government Bond Yield | C10: 0.0686
B11: =C9&"'s"&" Moody's Sovereign Rating" -> India's Moody's Sovereign Rating | C11: =VLOOKUP(C9,'Damodaran Data'!B3:D159,3,FALSE) -> Baa3
B12: Credit Default Spread as per Damodaran | C12: =VLOOKUP(C9,'Damodaran Data'!B3:E159,4,FALSE) -> 0.0209
B13: Implied US Equity Risk Premium | C13: 0.0418
B14: Asset Beta | C14: 0.4
B15: Asset Beta Variation (+/-) | C15: 0.05
B16: Debt to Equity Ratio | C16: ='Assumptions Working'!M945 -> 0.18266543
B17: Debt to Capital (Gearing) | C17: ='Assumptions Working'!M946 -> 0.15445233
B18: Marginal Tax Rate | C18: 0.2512
B19: Company Credit Rating Available | C19: Yes
B20: Company is large or small firm? | C20: L | E20: L | F20: Yes
B21: Provide Credit Rating | C21: Aaa/AAA | E21: S | F21: No
B22: Interest Coverage Ratio | C22: ='Ratio Analysis'!G87 -> 10.418769
B23: ICR Based Corporate Default Spread | C23: =IF(C20="L",VLOOKUP(C22,'Damodaran Data'!G4:J19,4,TRUE),VLOOKUP('Input Sheet'!C22,'Damodaran Data'!L4:O19,4,TRUE)) -> 0.004
B24: Small Size Premium | C24: ='WACC Analysis'!D13 -> 0.076
B25: Asset Specific Risk Premium | C25: 0

Sheet Damodaran Data
B1: Country Data | G1: Company Data
B2: Country | C2: Africa | D2: Moody's rating | E2: Rating-based Default Spread | G2: For large non-financial service firms | M2: For smaller and riskier firms
B3: India | C3: Asia | D3: Baa3 | E3: 0.0209 | H3: If interest coverage ratio is | M3: If interest coverage ratio is
B4: United Kingdom | C4: Western Europe | D4: Aa3 | E4: 0.0057 | G4: > | H4: ≤ to | I4: Rating is | J4: Spread is | L4: greater than | M4: ≤ to | N4: Rating is | O4: Spread is
B5: United States | C5: North America | D5: Aa1 | E5: 0.0026 | G5: -100000 | H5: 0.199999 | I5: D2/D | J5: 0.19 | L5: -100000 | M5: 0.499999 | N5: D2/D | O5: 0.19
B6: Abu Dhabi | C6: Middle East | D6: Aa2 | E6: 0.0047 | G6: 0.2 | H6: 0.649999 | I6: C2/C | J6: 0.16 | L6: 0.5 | M6: 0.799999 | N6: C2/C | O6: 0.16
B7: Albania | C7: Eastern Europe & Russia | D7: Ba3 | E7: 0.0342 | G7: 0.65 | H7: 0.799999 | I7: Ca2/CC | J7: 0.1261 | L7: 0.8 | M7: 1.249999 | N7: Ca2/CC | O7: 0.1261
B8: Andorra (Principality of) | C8: Western Europe | D8: Baa1 | E8: 0.0152 | G8: 0.8 | H8: 1.249999 | I8: Caa/CCC | J8: 0.0885 | L8: 1.25 | M8: 1.499999 | N8: Caa/CCC | O8: 0.0885
B9: Angola | C9: Africa | D9: B3 | E9: 0.0618 | G9: 1.25 | H9: 1.499999 | I9: B3/B- | J9: 0.0509 | L9: 1.5 | M9: 1.999999 | N9: B3/B- | O9: 0.0509
B10: Argentina | C10: Central and South America | D10: Caa1 | E10: 0.0714 | G10: 1.5 | H10: 1.749999 | I10: B2/B | J10: 0.0321 | L10: 2 | M10: 2.499999 | N10: B2/B | O10: 0.0321
B11: Armenia | C11: Eastern Europe & Russia | D11: Ba3 | E11: 0.0342 | G11: 1.75 | H11: 1.999999 | I11: B1/B+ | J11: 0.0275 | L11: 2.5 | M11: 2.999999 | N11: B1/B+ | O11: 0.0275
B12: Aruba | C12: Caribbean | D12: Baa3 | E12: 0.0209 | G12: 2 | H12: 2.2499999 | I12: Ba2/BB | J12: 0.0184 | L12: 3 | M12: 3.499999 | N12: Ba2/BB | O12: 0.0184
B13: Australia | C13: Australia & New Zealand | D13: Aaa | E13: 0 | G13: 2.25 | H13: 2.49999 | I13: Ba1/BB+ | J13: 0.0138 | L13: 3.5 | M13: 3.9999999 | N13: Ba1/BB+ | O13: 0.0138
B14: Austria | C14: Western Europe | D14: Aa1 | E14: 0.0026 | G14: 2.5 | H14: 2.999999 | I14: Baa2/BBB | J14: 0.0111 | L14: 4 | M14: 4.499999 | N14: Baa2/BBB | O14: 0.0111
B15: Azerbaijan | C15: Eastern Europe & Russia | D15: Baa3 | E15: 0.0209 | G15: 3 | H15: 4.249999 | I15: A3/A- | J15: 0.0089 | L15: 4.5 | M15: 5.999999 | N15: A3/A- | O15: 0.0089
B16: Bahamas | C16: Caribbean | D16: B1 | E16: 0.0428 | G16: 4.25 | H16: 5.499999 | I16: A2/A | J16: 0.0078 | L16: 6 | M16: 7.499999 | N16: A2/A | O16: 0.0078
... B19: Barbados | C19: Caribbean | D19: B2 | E19: 0.0523 | G19: 8.5 | H19: 100000 | I19: Aaa/AAA | J19: 0.004 | L19: 12.5 | M19: 100000 | N19: Aaa/AAA | O19: 0.004
B20: Belarus | C20: Eastern Europe & Russia | D20: C | E20: 0.175
B21: Belgium | C21: Western Europe | D21: Aa3 | E21: 0.0057
B22: Belize | C22: Central and South America | D22: Caa1 | E22: 0.0714
B23: Benin | C23: Africa | D23: B1 | E23: 0.0428
B24: Bermuda | C24: Caribbean | D24: A2 | E24: 0.0081
B25: Bolivia | C25: Central and South America | D25: Caa3 | E25: 0.0952
B26: Bosnia and Herzegovina | C26: Eastern Europe & Russia | D26: B3 | E26: 0.0618
B27: Botswana | C27: Africa | D27: Baa1 | E27: 0.0152
B28: Brazil | C28: Central and South America | D28: Ba1 | E28: 0.0238
B29: Bulgaria | C29: Eastern Europe & Russia | D29: Baa1 | E29: 0.0152
B30: Burkina Faso | C30: Africa | D30: Caa1 | E30: 0.0714
B31: Cambodia | C31: Asia | D31: B2 | E31: 0.0523
... B159: Zambia | C159: Africa | D159: Caa2 | E159: 0.0857

Sheet Historical Data
B2: HISTORICAL FINANCIAL DATA
B3: All figures in INR Crores.
B5: Fiscal Year Ending | C5: 2017 | D5: =C5+1 -> 2018 | E5: =D5+1 -> 2019 | F5: =E5+1 -> 2020 | G5: =F5+1 -> 2021 | H5: =G5+1 -> 2022 | I5: =H5+1 -> 2023 | J5: =I5+1 -> 2024 | K5: =J5+1 -> 2025 | L5: =K5+1 -> 2026
B7: INCOME STATEMENT
B8: Revenue From Operations | C8: 4385.24 | D8: 4638.95 | E8: 5234.84 | F8: 5360.19 | G8: 4263.59 | H8: 6045.58 | I8: 7977.32 | J8: 9685.36 | K8: 11967.65 | L8: 12401.99
B9: Revenue Growth % | C9: - | D9: =D8/C8-1 -> 0.057855442 | E9: =E8/D8-1 -> 0.12845364 | F9: =F8/E8-1 -> 0.023945335 | G9: =G8/F8-1 -> -0.2045823 | H9: =H8/G8-1 -> 0.41795529 | I9: =I8/H8-1 -> 0.31952931 | J9: =J8/I8-1 -> 0.21411201 | K9: =K8/J8-1 -> 0.23564328 | L9: =L8/K8-1 -> 0.036292839
B10: Less: Cost of Goods Sold/ Services | C10: 3112.25 | D10: 3454.95 | E10: 3931.18 | F10: 4018.11 | G10: 3271.35 | H10: 4714.68 | I10: 6181.67 | J10: 7391.97 | K10: 9074.34 | L10: 9542.09
B11: Gross Profit | C11: =C8-C10 -> 1272.99 | D11: =D8-D10 -> 1184 | E11: =E8-E10 -> 1303.66 | F11: =F8-F10 -> 1342.08 | G11: =G8-G10 -> 992.24 | H11: =H8-H10 -> 1330.9 | I11: =I8-I10 -> 1795.65 | J11: =J8-J10 -> 2293.39 | ... L11: =L8-L10 -> 2859.9
B12: Gross Margin (%) | C12: =C11/C8 -> 0.2902897 | D12: =D11/D8 -> 0.25523017 | E12: =E11/E8 -> 0.24903531 | F12: =F11/F8 -> 0.25037918 | G12: =G11/G8 -> 0.23272407 | H12: =H11/H8 -> 0.2201443 | I12: =I11/I8 -> 0.22509439 | J12: =J11/J8 -> 0.23678934 | ... L12: =L11/L8 -> 0.23060009
B14: Less: SG&A Expenses | C14: 1050.58 | D14: 918.1 | E14: 957.12 | F14: 1059.3 | G14: 752.43 | H14: 984.43 | I14: 1302.87 | J14: 1628.45 | K14: 2017.39 | L14: 1929.5
B15: SG&A % Revenue | C15: =C14/C8 -> 0.23957184 | D15: =D14/D8 -> 0.19791117 | E15: =E14/E8 -> 0.18283653 | F15: =F14/F8 -> 0.19762359 | G15: =G14/G8 -> 0.17647804 | H15: =H14/H8 -> 0.16283467 | I15: =I14/I8 -> 0.16332177 | J15: =J14/J8 -> 0.16813521 | ... L15: =L14/L8 -> 0.15557987
B16: Earning before Interest Taxes Depreciation & Amortization (EBITDA) | C16: =C11-C14 -> 222.41 | D16: =D11-D14 -> 265.9 | E16: =E11-E14 -> 346.54 | F16: =F11-F14 -> 282.78 | G16: =G11-G14 -> 239.81 | H16: =H11-H14 -> 346.47 | I16: =I11-I14 -> 492.78 | J16: =J11-J14 -> 664.94 | ... L16: =L11-L14 -> 930.4
B17: EBITDA Margin (%) | C17: =C16/C8 -> 0.050717863 | D17: =D16/D8 -> 0.057319005 | E17: =E16/E8 -> 0.066198776 | F17: =F16/F8 -> 0.052755593 | G17: =G16/G8 -> 0.056246027 | H17: =H16/H8 -> 0.057309638 | I17: =I16/I8 -> 0.061772625 | J17: =J16/J8 -> 0.068654134 | ... L17: =L16/L8 -> 0.075020219
B19: Less: Depreciation and Amortization | C19: 60.58 | D19: 63.81 | E19: 74.9 | F19: 87.99 | G19: 92.29 | H19: 85.98 | I19: 84.78 | J19: 97.61 | K19: 128.37 | L19: 178.79
B20: Earning before Interest & Taxes (EBIT) | C20: =C16-C19 -> 161.83 | D20: =D16-D19 -> 202.09 | E20: =E16-E19 -> 271.64 | F20: =F16-F19 -> 194.79 | G20: =G16-G19 -> 147.52 | H20: =H16-H19 -> 260.49 | I20: =I16-I19 -> 408 | J20: =J16-J19 -> 567.33 | ... L20: =L16-L19 -> 751.61
B21: EBIT Margin (%) | C21: =C20/C8 -> 0.036903339 | D21: =D20/D8 -> 0.043563737 | E21: =E20/E8 -> 0.051890793 | F21: =F20/F8 -> 0.03634013 | G21: =G20/G8 -> 0.03459995 | H21: =H20/H8 -> 0.043087677 | I21: =I20/I8 -> 0.051144996 | J21: =J20/J8 -> 0.058576036 | ... L21: =L20/L8 -> 0.060603984
B23: Other Income | C23: 13.07 | D23: 16.95 | E23: 24.69 | F23: 44.7 | G23: 62.35 | H23: 35.72 | I23: 30.87 | J23: 47.42 | K23: 75 | L23: 61.91
B24: Less: Interest Expenses | C24: 16.27 | D24: 28.74 | E24: 47.87 | F24: 29.47 | G24: 64.72 | H24: 46.4 | I24: 54.7 | J24: 58.08 | K24: 48.8 | L24: 72.14
B25: Less: Other Expense | C25: 0 | D25: -5.27 | E25: -2.68 | F25: 4.03 | G25: 0 | H25: 0 | I25: -170.81 | J25: 0 | K25: -12.51 | L25: 38.83
B26: Earnings Before Tax (PBT) | C26: =C20+C23-C24-C25 -> 158.63 | D26: =D20+D23-D24-D25 -> 195.57 | E26: =E20+E23-E24-E25 -> 251.14 | F26: =F20+F23-F24-F25 -> 205.99 | G26: =G20+G23-G24-G25 -> 145.15 | H26: =H20+H23-H24-H25 -> 249.81 | I26: =I20+I23-I24-I25 -> 554.98 | J26: =J20+J23-J24-J25 -> 556.67 | ... L26: =L20+L23-L24-L25 -> 702.55
B27: EBT Margins | C27: =C26/C8 -> 0.036173619 | D27: =D26/D8 -> 0.042158247 | E27: =E26/E8 -> 0.047974723 | F27: =F26/F8 -> 0.038429608 | G27: =G26/G8 -> 0.03404408 | H27: =H26/H8 -> 0.041321097 | I27: =I26/I8 -> 0.06956973 | J27: =J26/J8 -> 0.057475406 | ... L27: =L26/L8 -> 0.056648167
B29: Less: Tax Expense | C29: 36.67 | D29: 49.42 | E29: 41.99 | F29: 65.32 | G29: 47.09 | H29: 82.9 | I29: 154.69 | J29: 142.85 | K29: 193.65 | L29: 175.78
B30: Net Income | C30: =C26-C29 -> 121.96 | D30: =D26-D29 -> 146.15 | E30: =E26-E29 -> 209.15 | F30: =F26-F29 -> 140.67 | G30: =G26-G29 -> 98.06 | H30: =H26-H29 -> 166.91 | I30: =I26-I29 -> 400.29 | J30: =J26-J29 -> 413.82 | ... L30: =L26-L29 -> 526.77
B31: Net Income Margin (%) | C31: =C30/C8 -> 0.027811477 | D31: =D30/D8 -> 0.031504974 | E31: =E30/E8 -> 0.039953466 | F31: =F30/F8 -> 0.026243473 | G31: =G30/G8 -> 0.022999397 | H31: =H30/H8 -> 0.0276086 | I31: =I30/I8 -> 0.050178506 | J31: =J30/J8 -> 0.042726342 | ... L31: =L30/L8 -> 0.042474635
B32: Add:Profit from Discontinued Operations | C32: 0 | D32: 0 | E32: 0 | F32: 0 | G32: 0 | H32: 0 | I32: 0 | J32: 0 | K32: 0 | L32: 0
B33: Less: Loss from Discontinued Operations | C33: 0 | D33: 0 | E33: 0 | F33: 0 | G33: 0 | H33: 0 | I33: 0 | J33: 0 | K33: 0 | L33: 0
B34: Net Income of the Year | C34: =C30+C32-C33 -> 121.96 | D34: =D30+D32-D33 -> 146.15 | E34: =E30+E32-E33 -> 209.15 | F34: =F30+F32-F33 -> 140.67 | G34: =G30+G32-G33 -> 98.06 | H34: =H30+H32-H33 -> 166.91 | I34: =I30+I32-I33 -> 400.29 | J34: =J30+J32-J33 -> 413.82 | ... L34: =L30+L32-L33 -> 526.77
B39: BALANCE SHEET
B40: Equity and Liablities
B41: Shareholder's Funds
B42: Equity Share Capital | C42: 19.11 | D42: 19.2 | E42: 19.26 | F42: 19.26 | G42: 19.26 | H42: 19.26 | I42: 19.26 | J42: 41.12 | K42: 41.12 | L42: 41.12
B43: Reserves & Surplus | C43: 738.02 | D43: 773.53 | E43: 853.8 | F43: 763.11 | G43: 865.92 | H43: 998.32 | I43: 1311.39 | J43: 2568.95 | K43: 3023.9 | L43: 3390.29
B44: Total Shareholder's Funds | C44: =SUM(C42:C43) -> 757.13 | D44: =SUM(D42:D43) -> 792.73 | E44: =SUM(E42:E43) -> 873.06 | F44: =SUM(F42:F43) -> 782.37 | G44: =SUM(G42:G43) -> 885.18 | H44: =SUM(H42:H43) -> 1017.58 | I44: =SUM(I42:I43) -> 1330.65 | J44: =SUM(J42:J43) -> 2610.07 | ... L44: =SUM(L42:L43) -> 3431.41
B45: Minority Interest | C45: 1.22 | D45: 1.52 | E45: 1.83 | F45: 2.31 | G45: 2.68 | H45: 2.96 | I45: 3.19 | J45: 2.55 | K45: 2.6 | L45: 2.45
B47: Non Current Liablities
B48: Long Term Borrowings | C48: 20.2 | D48: 25.9 | E48: 8.65 | F48: 47.71 | G48: 349.26 | H48: 241.57 | I48: 161.74 | J48: 0 | K48: 0 | L48: 0
B49: Deferred Tax Liabilities | C49: 0 | D49: 0 | E49: 0 | F49: 0 | G49: 0 | H49: 0 | I49: 0 | J49: 6.98 | K49: 13.45 | L49: 31.6
B50: Other Long Term Liabilities | C50: 4.08 | D50: 6.27 | E50: 6.45 | F50: 47.92 | G50: 40.06 | H50: 71.27 | I50: 108.32 | J50: 103.1 | K50: 206.73 | L50: 191.49
B51: Long Term Provisions | C51: 11.17 | D51: 12.54 | E51: 12.06 | F51: 13.26 | G51: 10.82 | H51: 10.06 | I51: 11.41 | J51: 15.93 | K51: 25.31 | L51: 52.77
B52: Total Non-Current Liabilities | C52: =SUM(C48:C51) -> 35.45 | D52: =SUM(D48:D51) -> 44.71 | E52: =SUM(E48:E51) -> 27.16 | F52: =SUM(F48:F51) -> 108.89 | G52: =SUM(G48:G51) -> 400.14 | H52: =SUM(H48:H51) -> 322.9 | I52: =SUM(I48:I51) -> 281.47 | J52: =SUM(J48:J51) -> 126.01 | ... L52: =SUM(L48:L51) -> 275.86
B54: Current Liablities
B55: Short Term Borrowings | C55: 195.92 | D55: 344.02 | E55: 335.89 | F55: 401.23 | G55: 102.34 | H55: 236.26 | I55: 415.9 | J55: 166.62 | K55: 199.36 | L55: 626.8
B56: Trade Payables | C56: 1177.23 | D56: 1532.69 | E56: 1534.62 | F56: 1582.36 | G56: 1604.89 | H56: 2041.67 | I56: 2511.16 | J56: 2616.6 | K56: 3427.62 | L56: 2942.86
B57: Other Current Liabilities | C57: 443.38 | D57: 461.55 | E57: 491.4 | F57: 497.12 | G57: 505.85 | H57: 630.45 | I57: 791.69 | J57: 1019.54 | K57: 1206.33 | L57: 1160.11
B58: Short Term Provisions | C58: 39.85 | D58: 59 | E58: 87 | F58: 64.98 | G58: 48.37 | H58: 60.82 | I58: 65 | J58: 76.86 | K58: 111.08 | L58: 136.49
B59: Total Current Liabilities | C59: =SUM(C55:C58) -> 1856.38 | D59: =SUM(D55:D58) -> 2397.26 | E59: =SUM(E55:E58) -> 2448.91 | F59: =SUM(F55:F58) -> 2545.69 | G59: =SUM(G55:G58) -> 2261.45 | H59: =SUM(H55:H58) -> 2969.2 | I59: =SUM(I55:I58) -> 3783.75 | J59: =SUM(J55:J58) -> 3879.62 | ... L59: =SUM(L55:L58) -> 4866.26
B61: Total Equity and Liablities | C61: =SUM(C44,C45,C52,C59) -> 2650.18 | D61: =SUM(D44,D45,D52,D59) -> 3236.22 | E61: =SUM(E44,E45,E52,E59) -> 3350.96 | F61: =SUM(F44,F45,F52,F59) -> 3439.26 | G61: =SUM(G44,G45,G52,G59) -> 3549.45 | H61: =SUM(H44,H45,H52,H59) -> 4312.64 | I61: =SUM(I44,I45,I52,I59) -> 5399.06 | J61: =SUM(J44,J45,J52,J59) -> 6618.25 | ... L61: =SUM(L44,L45,L52,L59) -> 8575.98
B63: Assets
B64: Non Current Assets
B65: Tangible Assets | C65: 312.38 | D65: 335.87 | E65: 349.88 | F65: 392.4 | G65: 331.25 | H65: 391.13 | I65: 799.93 | J65: 1071.32 | K65: 1422.38 | L65: 1439.17
B66: Intangible Assets | C66: 43.73 | D66: 56.13 | E66: 50.32 | F66: 51.39 | G66: 52.31 | H66: 41.67 | I66: 58.96 | J66: 93.22 | K66: 113.33 | L66: 155.56
B67: Capital Work-In-Progress | C67: 21.51 | D67: 18.38 | E67: 30.77 | F67: 56.35 | G67: 68.11 | H67: 145.09 | I67: 60.93 | J67: 108.06 | K67: 73.36 | L67: 65.47
B68: Intangible Assets Under Development | C68: 12.09 | D68: 6.97 | E68: 10.45 | F68: 11.01 | G68: 3.42 | H68: 7.2 | I68: 22.39 | J68: 19 | K68: 49.81 | L68: 0
B69: Non-Current Investments | C69: 10.97 | D69: 13.24 | E69: 14.63 | F69: 16.87 | G69: 15.91 | H69: 17.31 | I69: 18.22 | J69: 17.88 | K69: 17.94 | L69: 21.94
B70: Deferred Tax Assets [Net] | C70: 107.66 | D70: 113.57 | E70: 107.55 | F70: 81.75 | G70: 47.49 | H70: 27.57 | I70: 7.94 | J70: 7.28 | K70: 8.9 | L70: 9.26
B71: Long Term Loans And Advances | C71: 17.31 | D71: 18.17 | E71: 19.82 | F71: 19.28 | G71: 22.42 | H71: 3.34 | I71: 4.69 | J71: 5.86 | K71: 20.05 | L71: 23.31
B72: Other Non-Current Assets | C72: 103.08 | D72: 95.38 | E72: 106.96 | F72: 159 | G72: 148.98 | H72: 195.9 | I72: 175.39 | J72: 255.6 | K72: 238.96 | L72: 473
B73: Total Non-Current Assets | C73: =SUM(C65:C72) -> 628.73 | D73: =SUM(D65:D72) -> 657.71 | E73: =SUM(E65:E72) -> 690.38 | F73: =SUM(F65:F72) -> 788.05 | G73: =SUM(G65:G72) -> 689.89 | H73: =SUM(H65:H72) -> 829.21 | I73: =SUM(I65:I72) -> 1148.45 | J73: =SUM(J65:J72) -> 1578.22 | ... L73: =SUM(L65:L72) -> 2187.71
B75: Current Assets
B76: Current Investments | C76: 0 | D76: 0 | E76: 0 | F76: 0 | G76: 279.06 | H76: 145.03 | I76: 129.88 | J76: 248.92 | K76: 414.12 | L76: 435.26
B77: Inventories | C77: 595.58 | D77: 1017.08 | E77: 869.32 | F77: 869.82 | G77: 882.42 | H77: 1144.24 | I77: 1433.39 | J77: 1407.18 | K77: 2149.15 | L77: 2166.2
B78: Trade Receivables | C78: 938.98 | D78: 950.42 | E78: 1112.05 | F78: 837.67 | G78: 810.98 | H78: 1189.74 | I78: 1548.82 | J78: 1952.56 | K78: 1959.37 | L78: 2139.7
B79: Cash And Cash Equivalents | C79: 96.57 | D79: 80.88 | E79: 100.94 | F79: 293.94 | G79: 332.16 | H79: 269.66 | I79: 247.27 | J79: 377.37 | K79: 431.92 | L79: 402.07
B80: Short Term Loans And Advances | C80: 4.01 | D80: 14.22 | E80: 11.34 | F80: 14.63 | G80: 20.13 | H80: 3.18 | I80: 1.92 | J80: 2.62 | K80: 4.6 | L80: 4.81
B81: OtherCurrentAssets | C81: 386.31 | D81: 515.91 | E81: 566.93 | F81: 635.15 | G81: 534.81 | H81: 731.58 | I81: 889.33 | J81: 1051.38 | K81: 1353.61 | L81: 1240.23
B82: Total Current Assets | C82: =SUM(C76:C81) -> 2021.45 | D82: =SUM(D76:D81) -> 2578.51 | E82: =SUM(E76:E81) -> 2660.58 | F82: =SUM(F76:F81) -> 2651.21 | G82: =SUM(G76:G81) -> 2859.56 | H82: =SUM(H76:H81) -> 3483.43 | I82: =SUM(I76:I81) -> 4250.61 | J82: =SUM(J76:J81) -> 5040.03 | ... L82: =SUM(L76:L81) -> 6388.27
B84: Total Assets | C84: =C73+C82 -> 2650.18 | D84: =D73+D82 -> 3236.22 | E84: =E73+E82 -> 3350.96 | F84: =F73+F82 -> 3439.26 | G84: =G73+G82 -> 3549.45 | H84: =H73+H82 -> 4312.64 | I84: =I73+I82 -> 5399.06 | J84: =J73+J82 -> 6618.25 | ... L84: =L73+L82 -> 8575.98
B87: CASHFLOW STATEMENT
B95: Net Cash From Operating Activities | C95: 128.97 | D95: -29.01 | E95: 152.22 | F95: 398.34 | G95: 308.35 | H95: 57.33 | I95: 308.1 | J95: 246.83 | K95: 662.2 | L95: 41.44
B102: Net Cash Used In Investing Activities | C102: 72.78 | D102: -65.63 | E102: -77.92 | F102: -64.41 | G102: -245.69 | H102: -2.36 | I102: -86.12 | J102: -698.64 | K102: -494.91 | L102: -175.93
B109: Net Cash Used From Financing Activities | C109: -215.43 | D109: 72.78 | E109: -104.65 | F109: -137.54 | G109: 15.35 | H109: -150.1 | I109: -247.77 | J109: 539.09 | K109: -126.1 | L109: 127.22

Sheet Growth Drivers
B2: Blue Star Ltd - Growth Drivers
A4: 1 | B4: Rapid housing sector expansion
A5: 2 | B5: accelerated adoption of renewable energy
A6: 3 | B6: vibrant rural economic growth
A7: 4 | B7: Robust demand in Overall Air Conditioning products
A8: 5 | B8: Strong execution in ElectroMechanical Projects
A9: 6 | B9: Demand for Commercial Refrigeration products due to rising healthcare and Food & Beverages sector
A10: 7 | B10: Rapid urbanisation and rising disposable income
A11: 8 | B11: India's becoming manufacturing hub to build domestic supply chains and export growth
A12: 9 | B12: Rising Disposable Income and Consumption
B16: Year | C16: Housing Units Sold
B17: 2022 | C17: 420554
B18: 2023 | C18: 484330
B19: 2024 | C19: 513811
B20: 2025 | C20: 494154
B24: https://www.credaincr.org/iismgmt/all-images/policypdf/pdf_1753099631.pdf
B27: Year | C27: Energy Capacity (MW)
B28: 2015 | C28: 4100.5
B29: 2016 | C29: 7141.3
B30: 2017 | C30: 11466.81
B31: 2018 | C31: 12093.24
B32: 2019 | C32: 8760.56
B33: 2020 | C33: 8843.31
B34: 2021 | C34: 7548.11
B35: 2022 | C35: 14081.97
B36: 2023 | C36: 15274.43
B37: 2024 | C37: 18484.68
B38: 2025 | C38: 28723.65
B42: https://mnre.gov.in/en/year-wise-achievement
B45: Year | C45: Acs unit sold (mn)
B46: 2023 | C46: 10.2
B47: 2024 | C47: 13.3
B48: 2025 | C48: 15.4
B49: 2026 | C49: 14.75

Sheet Assumptions Working
A2: # | B2: Revenue Growth
B4: Segment Mix | E4: FY26 Contribution | G4: Segment Revenue FY26
B6: Electro-Mechanical Projects and Commercial Air Conditioning Systems | E6: =G6/$G$9 -> 0.54529915 | G6: 6762.8
B7: Unitary Products | E7: =G7/$G$9 -> 0.42996291 | G7: 5332.4
B8: Professional Electronics and Industrial Systems | E8: =G8/$G$9 -> 0.024737945 | G8: 306.8
G9: =SUM(G6:G8) -> 12402
A13: # | B13: Company Historical Growth
O14: CAGR
B15: Particulars | D15: 2017 | E15: =D15+1 -> 2018 | F15: =E15+1 -> 2019 | G15: =F15+1 -> 2020 | H15: =G15+1 -> 2021 | I15: =H15+1 -> 2022 | J15: =I15+1 -> 2023 | K15: =J15+1 -> 2024 | L15: =K15+1 -> 2025 | M15: =L15+1 -> 2026 | O15: 3 Years | P15: 5 Years | Q15: 7 Years
B16: Revenue From Operations | D16: ='Historical Data'!C8 -> 4385.24 | E16: ='Historical Data'!D8 -> 4638.95 | F16: ='Historical Data'!E8 -> 5234.84 | G16: ='Historical Data'!F8 -> 5360.19 | H16: ='Historical Data'!G8 -> 4263.59 | I16: ='Historical Data'!H8 -> 6045.58 | J16: ='Historical Data'!I8 -> 7977.32 | K16: ='Historical Data'!J8 -> 9685.36 | ... M16: ='Historical Data'!L8 -> 12401.99 | O16: =_xlfn.RRI(3,J16,M16) -> 0.15845221 | P16: =_xlfn.RRI(5,H16,M16) -> 0.23806426 | Q16: =_xlfn.RRI(7,F16,M16) -> 0.13113012
B17: Growth YoY % | E17: ='Historical Data'!D9 -> 0.057855442 | F17: ='Historical Data'!E9 -> 0.12845364 | G17: ='Historical Data'!F9 -> 0.023945335 | H17: ='Historical Data'!G9 -> -0.2045823 | I17: ='Historical Data'!H9 -> 0.41795529 | J17: ='Historical Data'!I9 -> 0.31952931 | K17: ='Historical Data'!J9 -> 0.21411201 | L17: ='Historical Data'!K9 -> 0.23564328 | M17: ='Historical Data'!L9 -> 0.036292839
B20: Statista | D20: https://www.statista.com/outlook/cmo/household-appliances/major-appliances/air-conditioners/india/?srsltid=AfmBOop31nu0pkk5kCV8MoPgmKk2VtWrxiPHXx6y8TaZqeB64e0d7tMk#revenue
B22: 2023 Revenue | D22: US$9.01bn
B23: CAGR Growth 2026-2031 | D23: 0.1462
B24: Volume Growth in 2027 | D24: 0.1436
M29: REVENUE CHART AND VOLUME CHART
B30: Global Data | D30: https://www.globaldata.com/store/report/india-conditioner-market-analysis/#TabReport_2 | M30: price per unit chart
B32: Conditioner market in India registered a positive compound annual growth rate (CAGR) of 7.21% during the period 2018 to 2023..
B33: The market achieved its strongest performance in 2019, when it grew by 9.46% over its previous year and its weakest performance in 2020, when it increased by 3.76% over 2019.
B35: Imarc Group | D35: https://www.imarcgroup.com/india-air-conditioning-market
B37: The India air conditioning market size was valued at USD 6.15 Billion in 2025 and is projected to reach USD 21.59 Billion by 2034, growing at a CAGR of 14.98% during 2026-2034.
B39: IBEF | D39: https://www.ibef.org/news/indian-room-air-conditioner-market-to-reach-us-5-6-billion-rs-50-000-crore-by-fy29-voltas
B41: The India room air-conditioners (RAC) market is projected to grow at a robust CAGR of 12% and reach US$ 5.6 billion (Rs. 50,000 crore) by FY 2028-29,
B43: ICRA | D43: https://www.icra.in
B45: The long-term demand outlook for the RAC industry, however, remains healthy with a forecasted compounded annual growth rate (CAGR) of 10–15% in volumes between FY2026 and FY2030
B46: Reduction in the goods & services tax (GST) rate on RACs (under 2 tonne) to 18% with effect from September 22, 2025, against 28% earlier, is likely to reduce the prices of RACs by around 6-8%, or around Rs. 2000-3000 per unit, thus boosting demand | D46: PDF
B47: commodity exchange forward contracts | D47: 2
B48: ICRA projects the sales volume for the Indian RAC industry to contract to approximately11.0–11.5 million units in FY2026 from 12.5-13.0 million units in FY2025, primarily due tothe unseasonal rainfall during the summer, which impacted demand in Q1 FY2026
B49: The domestic RAC industry is estimated to have experienced a15-20% YoY decline in volumes during April–July 2025.
B50: This compressed RAC volumes in 4M FY2026 by around 15-20% in YoY terms, which will, however, be partly compensated by sales during the rest of the year due to favorable summer expectations in the Western and Sothern regions during H2 FY2026.
B51: India’s domestic RAC manufacturing capacity, currently at24–26 million units annually, is projected to grow to30–32 million units by CY2027and40–42 million units by CY2030, reflecting a40–50% increase,to meet rising demand.
B54: SOIC | D54: https://www.soic.in/blog-page/from-heatwaves-to-market-waves-decoding-indias-ac-industry
B56: Current penetration: Just 8% in India (vs 60–100% in developed markets).
B57: Market growth: Indian RAC (Room Air Conditioner) volumes grew at a 10% CAGR (FY13–19), and post-COVID, the momentum picked up with a projected 17% CAGR from FY23–28
B58: Global vs India gap: Global AC volumes ~150 mn units, China ~85 mn, India just ~7–8 mn (Exhibit 10). The runway is massive.
B59: India’s current penetration ~8% vs >100% in China and >90% in developed markets.
B60: Even doubling penetration to 15–20% by 2030 means tens of millions of new units sold.
B89: electromechanical projects and commercial air conditioning, that is Segment 1.
B90: Coming to Segment 2, that is Unitary Products
A93: # | B93: Company Concalls
B95: 46143
B97: Voume growth | C97: 0.1
B98: Overall RevenueAverage Growth (Commercial) | C98: 8%-10%
B99: We have already said that in the volume terms, we will be somewhere around some 11% of the market
B100: Within Segment 2, the room air conditioner business witnessed reasonable growth with primary demand picking up in March and channels across all regions stocking up for the summer. The dealer network expansion continues to progress as planned.
B101: I have always stated that the given there is price increase of I'm saying average you take at least 10% over last year, a good performance would mean anywhere between 25% to 30% over last year.
B141: 46054
B142: The company expects Q4FY26 to be a strong quarter for Room Air-Conditioners, Commercial Air-Conditioning, and Refrigeration products. In Electro-Mechanical Projects business, the demand from Factories and Data Center vertical continues to be healthy. In anticipation of a robust growth in FY2027, the Company is focused on expanding distribution reach and continues to invest in R&D, manufacturing, and digitalization, while persisting with cost optimization measures.
B143: Firstly, on the growth outlook, so, on Segment-I and Segment-II, and Segment-I, essentially on the projects and CSE, typically, we discussed 12% to 15% CAGRs is what the growth rate should be.
B144: The nine-month growth rate for Segment-I is almost 20%
B145: but you can take 12% to 15% CAGR as a good modeling assumption and Room Air-Conditioner, despite the failed summer, I would still model it anywhere between 18% to 20%.
B146: You don’t really have the breakup of that for me to disclose, but the category is supposed to grow at a CAGR of anywhere between 12% to 15%, given the processed food penetration, dairy, pharma—anything you take. FY26 was again a bad year.
B147: For segment 1 But when your pending order book is lower, your growth in the subsequent months will be impacted, that is why I said that one should look at a single-digit growth or just a 10% growth.
B148: Again, I am saying that it will be a growth at a CAGR of 8% to 10%.
B165: Keeping all this in mind, I think if you ask me at the moment, I will take it as CAGR of around 8% to 10%, and then revise it depending on how the first six months of the next fiscal goes.
B166: For segment 1 -. So, 8% to 10% range that we are talking about is for the entire EMP business, right?
B168: Capex : Yes, so with regards to capex, see, the annual capex can be anywhere in the region of around RS.250 Crore to RS.350 Crore. So that's the normal spend that we have. When I say this capex, it includes all type of capex that is the normal routine capex, maintenance capex, investments in R&D, product development as well as whatever IT investments that we'll be doing.
B170: For electro mechanical project segment 1 - Having said that, January has begun very well, and many inquiries are coming up for finalization. So, that should be happening. But when your pending order book is lower, your growth in the subsequent months will be impacted, that is why I said that one should look at a single-digit growth or just a 10% growth.
B197: 45870
B198: The growth story for the industry is strong. Even if you look at the CAGR from FY20 or you ignore the COVID years you take from FY22, the industry has grown, and Blue Star has grown in double digits. So, there is no doubt about the long-term prospects of this business. It is just that this particular financial year is tough
B210: It is also probable that the industry ends up with (-15%) over last year and Blue Star does better than that, because we are dependent on just two windows now.
B211: . So it can well be a growth which is minus 15%, it could be. So the range could be minus 15% to 0. But as of now, I am still hoping that one can attempt to deliver flat growth, if there is going to be a good summer outlook. That's the change. The festival season has not gone as one would have expected.
B213: And one can say that it will be somewhere around 7.5% to 8% growth at least should be possible for this business in this financial year as a whole.
B214: . In H1, our estimate is the industry would have shrunk by 15% and we have shrunk only by 10%. To that extent, we may have done better
B215: segment 3- So one can say that at a CAGR of 10% to 12%, it will grow.
B235: Yeah. So the Commercial Air-Conditioning, there is no caution at all, 12% to 15% kind of growth has been the story there
B236: The Commercial Air-Conditioning, by nature, it will be only 12% CAGR growt
B237: So there is absolutely no problem. Electro-Mechanical projects, we will maintain it only at around 10%
B238: That's not the way to do it. According to me, if you look at the FY20 to FY26, it is 16%. FY21 to FY26, it will be 24%. FY22 to FY26, 21%. FY23 to FY26, it will be 15%. By many estimates, FY25 to FY30, it will be 19%. So, do not worry about it.
B239: , I think the industry volumes, more or less the revenue, de-grew by 17% and Blue Star volumes would have de-grown by 12% in Q2.
A242: # | B242: Consensus Estimates
C244: 2025A | D244: 2026A | E244: 2027E | F244: 2028E
B245: Axis Direct (Crores) | C245: 11968 | D245: =M16 -> 12401.99 | E245: 15109 | F245: -
B246: Growth % | D246: =D245/C245-1 -> 0.036262533 | E246: =E245/D245-1 -> 0.21827223 | F246: -
B247: Motilal Oswal (Crores) | C247: =L16 -> 11967.65 | D247: 12401.99 | E247: 14370 | F247: 16690
B248: Growth % | D248: =D247/C247-1 -> 0.036292839 | E248: =E247/D247-1 -> 0.15868502 | F248: =F247/E247-1 -> 0.16144746
B249: BOB Capital Markets (Crores) | C249: 11968 | D249: 12401.99 | E249: 14628.5 | F249: 16854
B250: Growth % | D250: =D249/C249-1 -> 0.036262533 | E250: =E249/D249-1 -> 0.17952845 | F250: -
B251: Emkay (Crores) | C251: 11967.7 | D251: 12401.99 | E251: 14943.5 | F251: 17382.4
B252: Growth % | D252: =D251/C251-1 -> 0.03628851 | E252: =E251/D251-1 -> 0.2049276 | F252: =F251/E251-1 -> 0.16320808
B253: Average Revenue Estimate | C253: 11968 | D253: 12401.99 | E253: =AVERAGE(E245,E247,E249,E251) -> 14762.75 | F253: =AVERAGE(F247,F249,F251) -> 16975.467
B254: Growth % estimate | C254: - | D254: =D253/C253-1 -> 0.036262533 | E254: =E253/D253-1 -> 0.19035332 | F254: =F253/E253-1 -> 0.14988513
A271: # | B271: Gross Margin
B273: Company Historical Margin
B274: Particulars | D274: 2017 | E274: =D274+1 -> 2018 | F274: =E274+1 -> 2019 | G274: =F274+1 -> 2020 | H274: =G274+1 -> 2021 | I274: =H274+1 -> 2022 | J274: =I274+1 -> 2023 | K274: =J274+1 -> 2024 | L274: =K274+1 -> 2025 | M274: =L274+1 -> 2026 | O274: Median | P274: Average
B275: Gross Margins | D275: ='Historical Data'!C12 -> 0.2902897 | E275: ='Historical Data'!D12 -> 0.25523017 | F275: ='Historical Data'!E12 -> 0.24903531 | G275: ='Historical Data'!F12 -> 0.25037918 | H275: ='Historical Data'!G12 -> 0.23272407 | I275: ='Historical Data'!H12 -> 0.2201443 | J275: ='Historical Data'!I12 -> 0.22509439 | K275: ='Historical Data'!J12 -> 0.23678934 | ... M275: ='Historical Data'!L12 -> 0.23060009 | O275: =MEDIAN(D275:M275) -> 0.23927513 | P275: =AVERAGE(D275:M275) -> 0.24320475
B277: Sector Data
B278: India - Screener.in
B279: India's HVAC Industry | C279: 0.25
B281: All Emerging Markets - Damodaran Data
B282: Machinery | C282: 0.239
B284: Global
C285: 0.28
B286: Source : Oxmaint.com
B287: https://oxmaint.com/industries/hvac/hvac-market-size-growth-forecast-2026-global-analysis
B289: HVAC service and maintenance contracts typically deliver gross margins of 35–55%, compared to 18–28% for equipment manufacturing and 12–22% for installation contracting — making services the highest-margin segment of the HVAC value chain
B291: The Company is subject to fluctuations in prices for the purchase of copper, alluminium, and other raw material inputs.
B292: The Company is exposed to foreign exchange risk due to its international operations and sourcing of raw materials from multiple geographies.
B293: Blue Star has adopted a comprehensive Foreign Exchange Risk Management Policy with appropriate processes for regular monitoring and hedging of currency exposures.
B295: The Company’s profitability may be adversely affected by fluctuations in commodity prices, rising input and freight costs, or credit defaults by customers.
...

Sheet Control Sheet
B2: Blue Star Ltd
B3: Control Sheet
H4: Current case: | I4: 2
I6: Forecasting
B7: Fiscal Year Ending | C7: =#REF!+1 -> #REF! | D7: =2022 -> 2022 | E7: =D7+1 -> 2023 | F7: =E7+1 -> 2024 | G7: =F7+1 -> 2025 | H7: =G7+1 -> 2026 | I7: =H7+1 -> 2027 | J7: =I7+1 -> 2028 | K7: =J7+1 -> 2029 | L7: =K7+1 -> 2030 | ... R7: =Q7+1 -> 2036
B9: Assumptions
A11: # | B11: Revenue
B13: Revenue - YoY % Growth
B14: Management Case | D14: ='Historical Data'!H9 -> 0.41795529 | E14: ='Historical Data'!I9 -> 0.31952931 | F14: ='Historical Data'!J9 -> 0.21411201 | G14: ='Historical Data'!K9 -> 0.23564328 | H14: ='Historical Data'!L9 -> 0.036292839 | I14: 0.138 | J14: =I14-(($I$14-$R$14)/($R$7-$I$7)) -> 0.136 | K14: =J14-(($I$14-$R$14)/($R$7-$I$7)) -> 0.134 | L14: =K14-(($I$14-$R$14)/($R$7-$I$7)) -> 0.132 | M14: =L14-(($I$14-$R$14)/($R$7-$I$7)) -> 0.13 | N14: =M14-(($I$14-$R$14)/($R$7-$I$7)) -> 0.128 | O14: =N14-(($I$14-$R$14)/($R$7-$I$7)) -> 0.126 | P14: =O14-(($I$14-$R$14)/($R$7-$I$7)) -> 0.124 | Q14: =P14-(($I$14-$R$14)/($R$7-$I$7)) -> 0.122 | R14: 0.12
B15: Base Case | D15: =D14 -> 0.41795529 | E15: =E14 -> 0.31952931 | F15: =F14 -> 0.21411201 | G15: =G14 -> 0.23564328 | H15: =H14 -> 0.036292839 | I15: =13% -> 0.13 | J15: =I15-(($I$15-$R$15)/($R$7-$I$7)) -> 0.12888889 | K15: =J15-(($I$15-$R$15)/($R$7-$I$7)) -> 0.12777778 | L15: =K15-(($I$15-$R$15)/($R$7-$I$7)) -> 0.12666667 | M15: =L15-(($I$15-$R$15)/($R$7-$I$7)) -> 0.12555556 | N15: =M15-(($I$15-$R$15)/($R$7-$I$7)) -> 0.12444444 | O15: =N15-(($I$15-$R$15)/($R$7-$I$7)) -> 0.12333333 | P15: =O15-(($I$15-$R$15)/($R$7-$I$7)) -> 0.12222222 | Q15: =P15-(($I$15-$R$15)/($R$7-$I$7)) -> 0.12111111 | R15: =12% -> 0.12
B16: Down Case | D16: =D14 -> 0.41795529 | E16: =E14 -> 0.31952931 | F16: =F14 -> 0.21411201 | G16: =G14 -> 0.23564328 | H16: =H14 -> 0.036292839 | I16: =10% -> 0.1 | J16: =I16-(($I$16-$R$16)/($R$7-$I$7)) -> 0.097777778 | K16: =J16-(($I$16-$R$16)/($R$7-$I$7)) -> 0.095555556 | L16: =K16-(($I$16-$R$16)/($R$7-$I$7)) -> 0.093333333 | M16: =L16-(($I$16-$R$16)/($R$7-$I$7)) -> 0.091111111 | N16: =M16-(($I$16-$R$16)/($R$7-$I$7)) -> 0.088888889 | O16: =N16-(($I$16-$R$16)/($R$7-$I$7)) -> 0.086666667 | P16: =O16-(($I$16-$R$16)/($R$7-$I$7)) -> 0.084444444 | Q16: =P16-(($I$16-$R$16)/($R$7-$I$7)) -> 0.082222222 | R16: =8% -> 0.08
B17: ="Current Case: "&CHOOSE($I$4,$B$14,$B$15,$B$16) -> Current Case: Base Case | I17: =CHOOSE($I$4,I$14,I$15,I$16) -> 0.13 | J17: =CHOOSE($I$4,J$14,J$15,J$16) -> 0.12888889 | K17: =CHOOSE($I$4,K$14,K$15,K$16) -> 0.12777778 | L17: =CHOOSE($I$4,L$14,L$15,L$16) -> 0.12666667 | M17: =CHOOSE($I$4,M$14,M$15,M$16) -> 0.12555556 | N17: =CHOOSE($I$4,N$14,N$15,N$16) -> 0.12444444 | O17: =CHOOSE($I$4,O$14,O$15,O$16) -> 0.12333333 | P17: =CHOOSE($I$4,P$14,P$15,P$16) -> 0.12222222 | ... R17: =CHOOSE($I$4,R$14,R$15,R$16) -> 0.12
A19: # | B19: COGS
B21: Goss Margin - YoY % Growth
B22: Management Case | D22: ='Historical Data'!H12 -> 0.2201443 | E22: ='Historical Data'!I12 -> 0.22509439 | F22: ='Historical Data'!J12 -> 0.23678934 | G22: ='Historical Data'!K12 -> 0.24176091 | H22: ='Historical Data'!L12 -> 0.23060009 | I22: 0.239 | J22: =I22 -> 0.239 | K22: =J22 -> 0.239 | L22: =K22 -> 0.239 | M22: =L22 -> 0.239 | N22: =M22 -> 0.239 | O22: =N22 -> 0.239 | P22: =O22 -> 0.239 | Q22: =P22 -> 0.239 | R22: =Q22 -> 0.239
B23: Base Case | D23: =D22 -> 0.2201443 | E23: =E22 -> 0.22509439 | F23: =F22 -> 0.23678934 | G23: =G22 -> 0.24176091 | H23: =H22 -> 0.23060009 | I23: =24% -> 0.24 | J23: =24% -> 0.24 | K23: =24% -> 0.24 | L23: =24% -> 0.24 | M23: =24% -> 0.24 | N23: =24% -> 0.24 | O23: =24% -> 0.24 | P23: =24% -> 0.24 | ... R23: =24% -> 0.24
B24: Down Case | D24: =D22 -> 0.2201443 | E24: =E22 -> 0.22509439 | F24: =F22 -> 0.23678934 | G24: =G22 -> 0.24176091 | H24: =H22 -> 0.23060009 | I24: =22% -> 0.22 | J24: =22% -> 0.22 | K24: =22% -> 0.22 | L24: =22% -> 0.22 | M24: =22% -> 0.22 | N24: =22% -> 0.22 | O24: =22% -> 0.22 | P24: =22% -> 0.22 | ... R24: =22% -> 0.22
B25: ="Current Case: "&CHOOSE($I$4,$B$14,$B$15,$B$16) -> Current Case: Base Case | I25: =CHOOSE($I$4,I$22,I$23,I$24) -> 0.24 | J25: =CHOOSE($I$4,J$22,J$23,J$24) -> 0.24 | K25: =CHOOSE($I$4,K$22,K$23,K$24) -> 0.24 | L25: =CHOOSE($I$4,L$22,L$23,L$24) -> 0.24 | M25: =CHOOSE($I$4,M$22,M$23,M$24) -> 0.24 | N25: =CHOOSE($I$4,N$22,N$23,N$24) -> 0.24 | O25: =CHOOSE($I$4,O$22,O$23,O$24) -> 0.24 | P25: =CHOOSE($I$4,P$22,P$23,P$24) -> 0.24 | ... R25: =CHOOSE($I$4,R$22,R$23,R$24) -> 0.24
B27: Current case: C0GS % Revenue | I27: =1-I25 -> 0.76 | J27: =1-J25 -> 0.76 | K27: =1-K25 -> 0.76 | L27: =1-L25 -> 0.76 | M27: =1-M25 -> 0.76 | N27: =1-N25 -> 0.76 | O27: =1-O25 -> 0.76 | P27: =1-P25 -> 0.76 | ... R27: =1-R25 -> 0.76
A29: # | B29: SG&A Expenses
B31: SG&A % Revenue
B32: Management Case | D32: ='Historical Data'!H15 -> 0.16283467 | E32: ='Historical Data'!I15 -> 0.16332177 | F32: ='Historical Data'!J15 -> 0.16813521 | G32: ='Historical Data'!K15 -> 0.16857027 | H32: ='Historical Data'!L15 -> 0.15557987 | I32: 0.16 | J32: =I32 -> 0.16 | K32: =J32 -> 0.16 | L32: =K32 -> 0.16 | M32: =L32 -> 0.16 | N32: =M32 -> 0.16 | O32: =N32 -> 0.16 | P32: =O32 -> 0.16 | Q32: =P32 -> 0.16 | R32: =Q32 -> 0.16
B33: Base Case | D33: =D32 -> 0.16283467 | E33: =E32 -> 0.16332177 | F33: =F32 -> 0.16813521 | G33: =G32 -> 0.16857027 | H33: =H32 -> 0.15557987 | I33: 0.16 | J33: =I33 -> 0.16 | K33: =J33 -> 0.16 | L33: =K33 -> 0.16 | M33: =L33 -> 0.16 | N33: =M33 -> 0.16 | O33: =N33 -> 0.16 | P33: =O33 -> 0.16 | Q33: =P33 -> 0.16 | R33: =Q33 -> 0.16
B34: Down Case | D34: =D32 -> 0.16283467 | E34: =E32 -> 0.16332177 | F34: =F32 -> 0.16813521 | G34: =G32 -> 0.16857027 | H34: =H32 -> 0.15557987 | I34: 0.16 | J34: =I34 -> 0.16 | K34: =J34 -> 0.16 | L34: =K34 -> 0.16 | M34: =L34 -> 0.16 | N34: =M34 -> 0.16 | O34: =N34 -> 0.16 | P34: =O34 -> 0.16 | Q34: =P34 -> 0.16 | R34: =Q34 -> 0.16
B35: ="Current Case: "&CHOOSE($I$4,$B$14,$B$15,$B$16) -> Current Case: Base Case | I35: =CHOOSE($I$4,I32,I$33,I$34) -> 0.16 | J35: =CHOOSE($I$4,J32,J$33,J$34) -> 0.16 | K35: =CHOOSE($I$4,K32,K$33,K$34) -> 0.16 | L35: =CHOOSE($I$4,L32,L$33,L$34) -> 0.16 | M35: =CHOOSE($I$4,M32,M$33,M$34) -> 0.16 | N35: =CHOOSE($I$4,N32,N$33,N$34) -> 0.16 | O35: =CHOOSE($I$4,O32,O$33,O$34) -> 0.16 | P35: =CHOOSE($I$4,P32,P$33,P$34) -> 0.16 | ... R35: =CHOOSE($I$4,R32,R$33,R$34) -> 0.16
A37: # | B37: Non Current Assets
B39: Intangible Assets % Revenue | I39: 0.01 | J39: =I39 -> 0.01 | K39: =J39 -> 0.01 | L39: =K39 -> 0.01 | M39: =L39 -> 0.01 | N39: =M39 -> 0.01 | O39: =N39 -> 0.01 | P39: =O39 -> 0.01 | Q39: =P39 -> 0.01 | R39: =Q39 -> 0.01
B41: Capital WIP
B42: Management Case | D42: - | E42: - | F42: - | G42: - | H42: - | I42: 0 | J42: =I42 -> 0 | K42: =J42 -> 0 | L42: =K42 -> 0 | M42: =L42 -> 0 | N42: =M42 -> 0 | O42: =N42 -> 0 | P42: =O42 -> 0 | Q42: =P42 -> 0 | R42: =Q42 -> 0
B43: Base Case | D43: - | E43: - | F43: - | G43: - | H43: - | I43: 0 | J43: =I43 -> 0 | K43: =J43 -> 0 | L43: =K43 -> 0 | M43: =L43 -> 0 | N43: =M43 -> 0 | O43: =N43 -> 0 | P43: =O43 -> 0 | Q43: =P43 -> 0 | R43: =Q43 -> 0
B44: Down Case | D44: - | E44: - | F44: - | G44: - | H44: - | I44: 0 | J44: =I44 -> 0 | K44: =J44 -> 0 | L44: =K44 -> 0 | M44: =L44 -> 0 | N44: =M44 -> 0 | O44: =N44 -> 0 | P44: =O44 -> 0 | Q44: =P44 -> 0 | R44: =Q44 -> 0
B45: ="Current Case: "&CHOOSE($I$4,$B$14,$B$15,$B$16) -> Current Case: Base Case | I45: =CHOOSE($I$4,I$42,I$43,I$44) -> 0 | J45: =CHOOSE($I$4,J$42,J$43,J$44) -> 0 | K45: =CHOOSE($I$4,K$42,K$43,K$44) -> 0 | L45: =CHOOSE($I$4,L$42,L$43,L$44) -> 0 | M45: =CHOOSE($I$4,M$42,M$43,M$44) -> 0 | N45: =CHOOSE($I$4,N$42,N$43,N$44) -> 0 | O45: =CHOOSE($I$4,O$42,O$43,O$44) -> 0 | P45: =CHOOSE($I$4,P$42,P$43,P$44) -> 0 | ... R45: =CHOOSE($I$4,R$42,R$43,R$44) -> 0
B47: Intangible Assets Under Development Growth %
B48: Management Case | D48: - | E48: - | F48: - | G48: - | H48: - | I48: 0 | J48: =I48 -> 0 | K48: =J48 -> 0 | L48: =K48 -> 0 | M48: =L48 -> 0 | N48: =M48 -> 0 | O48: =N48 -> 0 | P48: =O48 -> 0 | Q48: =P48 -> 0 | R48: =Q48 -> 0
B49: Base Case | D49: - | E49: - | F49: - | G49: - | H49: - | I49: 0 | J49: =I49 -> 0 | K49: =J49 -> 0 | L49: =K49 -> 0 | M49: =L49 -> 0 | N49: =M49 -> 0 | O49: =N49 -> 0 | P49: =O49 -> 0 | Q49: =P49 -> 0 | R49: =Q49 -> 0
B50: Down Case | D50: - | E50: - | F50: - | G50: - | H50: - | I50: 0 | J50: =I50 -> 0 | K50: =J50 -> 0 | L50: =K50 -> 0 | M50: =L50 -> 0 | N50: =M50 -> 0 | O50: =N50 -> 0 | P50: =O50 -> 0 | Q50: =P50 -> 0 | R50: =Q50 -> 0
B51: ="Current Case: "&CHOOSE($I$4,$B$14,$B$15,$B$16) -> Current Case: Base Case | I51: =CHOOSE($I$4,I$48,I$49,I$50) -> 0 | J51: =CHOOSE($I$4,J$48,J$49,J$50) -> 0 | K51: =CHOOSE($I$4,K$48,K$49,K$50) -> 0 | L51: =CHOOSE($I$4,L$48,L$49,L$50) -> 0 | M51: =CHOOSE($I$4,M$48,M$49,M$50) -> 0 | N51: =CHOOSE($I$4,N$48,N$49,N$50) -> 0 | O51: =CHOOSE($I$4,O$48,O$49,O$50) -> 0 | P51: =CHOOSE($I$4,P$48,P$49,P$50) -> 0 | ... R51: =CHOOSE($I$4,R$48,R$49,R$50) -> 0
B53: Non Current Investments
B54: Management Case | D54: - | E54: - | F54: - | G54: - | H54: - | I54: 0 | J54: =I54 -> 0 | K54: =J54 -> 0 | L54: =K54 -> 0 | M54: =L54 -> 0 | N54: =M54 -> 0 | O54: =N54 -> 0 | P54: =O54 -> 0 | Q54: =P54 -> 0 | R54: =Q54 -> 0
B55: Base Case | D55: - | E55: - | F55: - | G55: - | H55: - | I55: 0 | J55: =I55 -> 0 | K55: =J55 -> 0 | L55: =K55 -> 0 | M55: =L55 -> 0 | N55: =M55 -> 0 | O55: =N55 -> 0 | P55: =O55 -> 0 | Q55: =P55 -> 0 | R55: =Q55 -> 0
B56: Down Case | D56: - | E56: - | F56: - | G56: - | H56: - | I56: 0 | J56: =I56 -> 0 | K56: =J56 -> 0 | L56: =K56 -> 0 | M56: =L56 -> 0 | N56: =M56 -> 0 | O56: =N56 -> 0 | P56: =O56 -> 0 | Q56: =P56 -> 0 | R56: =Q56 -> 0
B57: ="Current Case: "&CHOOSE($I$4,$B$14,$B$15,$B$16) -> Current Case: Base Case | I57: =CHOOSE($I$4,I$54,I$55,I$56) -> 0 | J57: =CHOOSE($I$4,J$54,J$55,J$56) -> 0 | K57: =CHOOSE($I$4,K$54,K$55,K$56) -> 0 | L57: =CHOOSE($I$4,L$54,L$55,L$56) -> 0 | M57: =CHOOSE($I$4,M$54,M$55,M$56) -> 0 | N57: =CHOOSE($I$4,N$54,N$55,N$56) -> 0 | O57: =CHOOSE($I$4,O$54,O$55,O$56) -> 0 | P57: =CHOOSE($I$4,P$54,P$55,P$56) -> 0 | ... R57: =CHOOSE($I$4,R$54,R$55,R$56) -> 0
B59: Deferred Tax Assets
B60: Management Case | D60: - | E60: - | F60: - | G60: - | H60: - | I60: 0 | J60: =I60 -> 0 | K60: =J60 -> 0 | L60: =K60 -> 0 | M60: =L60 -> 0 | N60: =M60 -> 0 | O60: =N60 -> 0 | P60: =O60 -> 0 | Q60: =P60 -> 0 | R60: =Q60 -> 0
B61: Base Case | D61: - | E61: - | F61: - | G61: - | H61: - | I61: 0 | J61: =I61 -> 0 | K61: =J61 -> 0 | L61: =K61 -> 0 | M61: =L61 -> 0 | N61: =M61 -> 0 | O61: =N61 -> 0 | P61: =O61 -> 0 | Q61: =P61 -> 0 | R61: =Q61 -> 0
B62: Down Case | D62: - | E62: - | F62: - | G62: - | H62: - | I62: 0 | J62: =I62 -> 0 | K62: =J62 -> 0 | L62: =K62 -> 0 | M62: =L62 -> 0 | N62: =M62 -> 0 | O62: =N62 -> 0 | P62: =O62 -> 0 | Q62: =P62 -> 0 | R62: =Q62 -> 0
B63: ="Current Case: "&CHOOSE($I$4,$B$14,$B$15,$B$16) -> Current Case: Base Case | I63: =CHOOSE($I$4,I$60,I$61,I$62) -> 0 | J63: =CHOOSE($I$4,J$60,J$61,J$62) -> 0 | K63: =CHOOSE($I$4,K$60,K$61,K$62) -> 0 | L63: =CHOOSE($I$4,L$60,L$61,L$62) -> 0 | M63: =CHOOSE($I$4,M$60,M$61,M$62) -> 0 | N63: =CHOOSE($I$4,N$60,N$61,N$62) -> 0 | O63: =CHOOSE($I$4,O$60,O$61,O$62) -> 0 | P63: =CHOOSE($I$4,P$60,P$61,P$62) -> 0 | ... R63: =CHOOSE($I$4,R$60,R$61,R$62) -> 0
B65: Long term Loan and Advances
B66: Management Case | D66: - | E66: - | F66: - | G66: - | H66: - | I66: 0 | J66: =I66 -> 0 | K66: =J66 -> 0 | L66: =K66 -> 0 | M66: =L66 -> 0 | N66: =M66 -> 0 | O66: =N66 -> 0 | P66: =O66 -> 0 | Q66: =P66 -> 0 | R66: =Q66 -> 0
B67: Base Case | D67: - | E67: - | F67: - | G67: - | H67: - | I67: 0 | J67: =I67 -> 0 | K67: =J67 -> 0 | L67: =K67 -> 0 | M67: =L67 -> 0 | N67: =M67 -> 0 | O67: =N67 -> 0 | P67: =O67 -> 0 | Q67: =P67 -> 0 | R67: =Q67 -> 0
B68: Down Case | D68: - | E68: - | F68: - | G68: - | H68: - | I68: 0 | J68: =I68 -> 0 | K68: =J68 -> 0 | L68: =K68 -> 0 | M68: =L68 -> 0 | N68: =M68 -> 0 | O68: =N68 -> 0 | P68: =O68 -> 0 | Q68: =P68 -> 0 | R68: =Q68 -> 0
B69: ="Current Case: "&CHOOSE($I$4,$B$14,$B$15,$B$16) -> Current Case: Base Case | I69: =CHOOSE($I$4,I$66,I$67,I$68) -> 0 | J69: =CHOOSE($I$4,J$66,J$67,J$68) -> 0 | K69: =CHOOSE($I$4,K$66,K$67,K$68) -> 0 | L69: =CHOOSE($I$4,L$66,L$67,L$68) -> 0 | M69: =CHOOSE($I$4,M$66,M$67,M$68) -> 0 | N69: =CHOOSE($I$4,N$66,N$67,N$68) -> 0 | O69: =CHOOSE($I$4,O$66,O$67,O$68) -> 0 | P69: =CHOOSE($I$4,P$66,P$67,P$68) -> 0 | ... R69: =CHOOSE($I$4,R$66,R$67,R$68) -> 0
B71: Other Non Current Assets
B72: Management Case | D72: - | E72: - | F72: - | G72: - | H72: - | I72: 0 | J72: =I72 -> 0 | K72: =J72 -> 0 | L72: =K72 -> 0 | M72: =L72 -> 0 | N72: =M72 -> 0 | O72: =N72 -> 0 | P72: =O72 -> 0 | Q72: =P72 -> 0 | R72: =Q72 -> 0
B73: Base Case | D73: - | E73: - | F73: - | G73: - | H73: - | I73: 0 | J73: =I73 -> 0 | K73: =J73 -> 0 | L73: =K73 -> 0 | M73: =L73 -> 0 | N73: =M73 -> 0 | O73: =N73 -> 0 | P73: =O73 -> 0 | Q73: =P73 -> 0 | R73: =Q73 -> 0
B74: Down Case | D74: - | E74: - | F74: - | G74: - | H74: - | I74: 0 | J74: =I74 -> 0 | K74: =J74 -> 0 | L74: =K74 -> 0 | M74: =L74 -> 0 | N74: =M74 -> 0 | O74: =N74 -> 0 | P74: =O74 -> 0 | Q74: =P74 -> 0 | R74: =Q74 -> 0
B75: ="Current Case: "&CHOOSE($I$4,$B$14,$B$15,$B$16) -> Current Case: Base Case | I75: =CHOOSE($I$4,I$72,I$73,I$74) -> 0 | J75: =CHOOSE($I$4,J$72,J$73,J$74) -> 0 | K75: =CHOOSE($I$4,K$72,K$73,K$74) -> 0 | L75: =CHOOSE($I$4,L$72,L$73,L$74) -> 0 | M75: =CHOOSE($I$4,M$72,M$73,M$74) -> 0 | N75: =CHOOSE($I$4,N$72,N$73,N$74) -> 0 | O75: =CHOOSE($I$4,O$72,O$73,O$74) -> 0 | P75: =CHOOSE($I$4,P$72,P$73,P$74) -> 0 | ... R75: =CHOOSE($I$4,R$72,R$73,R$74) -> 0
A77: # | B77: Current Assets
B79: Current Investments
B80: Management Case | D80: - | E80: - | F80: - | G80: - | H80: - | I80: 0 | J80: =I80 -> 0 | K80: =J80 -> 0 | L80: =K80 -> 0 | M80: =L80 -> 0 | N80: =M80 -> 0 | O80: =N80 -> 0 | P80: =O80 -> 0 | Q80: =P80 -> 0 | R80: =Q80 -> 0
B81: Base Case | D81: - | E81: - | F81: - | G81: - | H81: - | I81: 0 | J81: =I81 -> 0 | K81: =J81 -> 0 | L81: =K81 -> 0 | M81: =L81 -> 0 | N81: =M81 -> 0 | O81: =N81 -> 0 | P81: =O81 -> 0 | Q81: =P81 -> 0 | R81: =Q81 -> 0
B82: Down Case | D82: - | E82: - | F82: - | G82: - | H82: - | I82: 0 | J82: =I82 -> 0 | K82: =J82 -> 0 | L82: =K82 -> 0 | M82: =L82 -> 0 | N82: =M82 -> 0 | O82: =N82 -> 0 | P82: =O82 -> 0 | Q82: =P82 -> 0 | R82: =Q82 -> 0
B83: ="Current Case: "&CHOOSE($I$4,$B$14,$B$15,$B$16) -> Current Case: Base Case | I83: =CHOOSE($I$4,I$80,I$81,I$82) -> 0 | J83: =CHOOSE($I$4,J$80,J$81,J$82) -> 0 | K83: =CHOOSE($I$4,K$80,K$81,K$82) -> 0 | L83: =CHOOSE($I$4,L$80,L$81,L$82) -> 0 | M83: =CHOOSE($I$4,M$80,M$81,M$82) -> 0 | N83: =CHOOSE($I$4,N$80,N$81,N$82) -> 0 | O83: =CHOOSE($I$4,O$80,O$81,O$82) -> 0 | P83: =CHOOSE($I$4,P$80,P$81,P$82) -> 0 | ... R83: =CHOOSE($I$4,R$80,R$81,R$82) -> 0
B85: Short Term Loans & Advances
B86: Management Case | D86: - | E86: - | F86: - | G86: - | H86: - | I86: 0 | J86: =I86 -> 0 | K86: =J86 -> 0 | L86: =K86 -> 0 | M86: =L86 -> 0 | N86: =M86 -> 0 | O86: =N86 -> 0 | P86: =O86 -> 0 | Q86: =P86 -> 0 | R86: =Q86 -> 0
B87: Base Case | D87: - | E87: - | F87: - | G87: - | H87: - | I87: 0 | J87: =I87 -> 0 | K87: =J87 -> 0 | L87: =K87 -> 0 | M87: =L87 -> 0 | N87: =M87 -> 0 | O87: =N87 -> 0 | P87: =O87 -> 0 | Q87: =P87 -> 0 | R87: =Q87 -> 0
B88: Down Case | D88: - | E88: - | F88: - | G88: - | H88: - | I88: 0 | J88: =I88 -> 0 | K88: =J88 -> 0 | L88: =K88 -> 0 | M88: =L88 -> 0 | N88: =M88 -> 0 | O88: =N88 -> 0 | P88: =O88 -> 0 | Q88: =P88 -> 0 | R88: =Q88 -> 0
B89: ="Current Case: "&CHOOSE($I$4,$B$14,$B$15,$B$16) -> Current Case: Base Case | I89: =CHOOSE($I$4,I$86,I$87,I$88) -> 0 | J89: =CHOOSE($I$4,J$86,J$87,J$88) -> 0 | K89: =CHOOSE($I$4,K$86,K$87,K$88) -> 0 | L89: =CHOOSE($I$4,L$86,L$87,L$88) -> 0 | M89: =CHOOSE($I$4,M$86,M$87,M$88) -> 0 | N89: =CHOOSE($I$4,N$86,N$87,N$88) -> 0 | O89: =CHOOSE($I$4,O$86,O$87,O$88) -> 0 | P89: =CHOOSE($I$4,P$86,P$87,P$88) -> 0 | ... R89: =CHOOSE($I$4,R$86,R$87,R$88) -> 0
B91: Other Current Assets
B92: Management Case | D92: - | E92: - | F92: - | G92: - | H92: - | I92: 0 | J92: =I92 -> 0 | K92: =J92 -> 0 | L92: =K92 -> 0 | M92: =L92 -> 0 | N92: =M92 -> 0 | O92: =N92 -> 0 | P92: =O92 -> 0 | Q92: =P92 -> 0 | R92: =Q92 -> 0
B93: Base Case | D93: - | E93: - | F93: - | G93: - | H93: - | I93: 0 | J93: =I93 -> 0 | K93: =J93 -> 0 | L93: =K93 -> 0 | M93: =L93 -> 0 | N93: =M93 -> 0 | O93: =N93 -> 0 | P93: =O93 -> 0 | Q93: =P93 -> 0 | R93: =Q93 -> 0
B94: Down Case | D94: - | E94: - | F94: - | G94: - | H94: - | I94: 0 | J94: =I94 -> 0 | K94: =J94 -> 0 | L94: =K94 -> 0 | M94: =L94 -> 0 | N94: =M94 -> 0 | O94: =N94 -> 0 | P94: =O94 -> 0 | Q94: =P94 -> 0 | R94: =Q94 -> 0
B95: ="Current Case: "&CHOOSE($I$4,$B$14,$B$15,$B$16) -> Current Case: Base Case | I95: =CHOOSE($I$4,I$92,I$93,I$94) -> 0 | J95: =CHOOSE($I$4,J$92,J$93,J$94) -> 0 | K95: =CHOOSE($I$4,K$92,K$93,K$94) -> 0 | L95: =CHOOSE($I$4,L$92,L$93,L$94) -> 0 | M95: =CHOOSE($I$4,M$92,M$93,M$94) -> 0 | N95: =CHOOSE($I$4,N$92,N$93,N$94) -> 0 | O95: =CHOOSE($I$4,O$92,O$93,O$94) -> 0 | P95: =CHOOSE($I$4,P$92,P$93,P$94) -> 0 | ... R95: =CHOOSE($I$4,R$92,R$93,R$94) -> 0
A97: # | B97: Non Current Liablities
B99: Deferred Tax Liablities
B100: Management Case | D100: - | E100: - | F100: - | G100: - | H100: - | I100: 0 | J100: =I100 -> 0 | K100: =J100 -> 0 | L100: =K100 -> 0 | M100: =L100 -> 0 | N100: =M100 -> 0 | O100: =N100 -> 0 | P100: =O100 -> 0 | Q100: =P100 -> 0 | R100: =Q100 -> 0
B101: Base Case | D101: - | E101: - | F101: - | G101: - | H101: - | I101: 0 | J101: =I101 -> 0 | K101: =J101 -> 0 | L101: =K101 -> 0 | M101: =L101 -> 0 | N101: =M101 -> 0 | O101: =N101 -> 0 | P101: =O101 -> 0 | Q101: =P101 -> 0 | R101: =Q101 -> 0
B102: Down Case | D102: - | E102: - | F102: - | G102: - | H102: - | I102: 0 | J102: =I102 -> 0 | K102: =J102 -> 0 | L102: =K102 -> 0 | M102: =L102 -> 0 | N102: =M102 -> 0 | O102: =N102 -> 0 | P102: =O102 -> 0 | Q102: =P102 -> 0 | R102: =Q102 -> 0
B103: ="Current Case: "&CHOOSE($I$4,$B$14,$B$15,$B$16) -> Current Case: Base Case | I103: =CHOOSE($I$4,I$60,I$61,I$62) -> 0 | J103: =CHOOSE($I$4,J$60,J$61,J$62) -> 0 | K103: =CHOOSE($I$4,K$60,K$61,K$62) -> 0 | L103: =CHOOSE($I$4,L$60,L$61,L$62) -> 0 | M103: =CHOOSE($I$4,M$60,M$61,M$62) -> 0 | N103: =CHOOSE($I$4,N$60,N$61,N$62) -> 0 | O103: =CHOOSE($I$4,O$60,O$61,O$62) -> 0 | P103: =CHOOSE($I$4,P$60,P$61,P$62) -> 0 | ... R103: =CHOOSE($I$4,R$60,R$61,R$62) -> 0
B105: Other Long Term Liablities
B106: Management Case | D106: - | E106: - | F106: - | G106: - | H106: - | I106: 0 | J106: =I106 -> 0 | K106: =J106 -> 0 | L106: =K106 -> 0 | M106: =L106 -> 0 | N106: =M106 -> 0 | O106: =N106 -> 0 | P106: =O106 -> 0 | Q106: =P106 -> 0 | R106: =Q106 -> 0
B107: Base Case | D107: - | E107: - | F107: - | G107: - | H107: - | I107: 0 | J107: =I107 -> 0 | K107: =J107 -> 0 | L107: =K107 -> 0 | M107: =L107 -> 0 | N107: =M107 -> 0 | O107: =N107 -> 0 | P107: =O107 -> 0 | Q107: =P107 -> 0 | R107: =Q107 -> 0
B108: Down Case | D108: - | E108: - | F108: - | G108: - | H108: - | I108: 0 | J108: =I108 -> 0 | K108: =J108 -> 0 | L108: =K108 -> 0 | M108: =L108 -> 0 | N108: =M108 -> 0 | O108: =N108 -> 0 | P108: =O108 -> 0 | Q108: =P108 -> 0 | R108: =Q108 -> 0
B109: ="Current Case: "&CHOOSE($I$4,$B$14,$B$15,$B$16) -> Current Case: Base Case | I109: =CHOOSE($I$4,I$66,I$67,I$68) -> 0 | J109: =CHOOSE($I$4,J$66,J$67,J$68) -> 0 | K109: =CHOOSE($I$4,K$66,K$67,K$68) -> 0 | L109: =CHOOSE($I$4,L$66,L$67,L$68) -> 0 | M109: =CHOOSE($I$4,M$66,M$67,M$68) -> 0 | N109: =CHOOSE($I$4,N$66,N$67,N$68) -> 0 | O109: =CHOOSE($I$4,O$66,O$67,O$68) -> 0 | P109: =CHOOSE($I$4,P$66,P$67,P$68) -> 0 | ... R109: =CHOOSE($I$4,R$66,R$67,R$68) -> 0
B111: Long Term Provisions
B112: Management Case | D112: - | E112: - | F112: - | G112: - | H112: - | I112: 0 | J112: =I112 -> 0 | K112: =J112 -> 0 | L112: =K112 -> 0 | M112: =L112 -> 0 | N112: =M112 -> 0 | O112: =N112 -> 0 | P112: =O112 -> 0 | Q112: =P112 -> 0 | R112: =Q112 -> 0
B113: Base Case | D113: - | E113: - | F113: - | G113: - | H113: - | I113: 0 | J113: =I113 -> 0 | K113: =J113 -> 0 | L113: =K113 -> 0 | M113: =L113 -> 0 | N113: =M113 -> 0 | O113: =N113 -> 0 | P113: =O113 -> 0 | Q113: =P113 -> 0 | R113: =Q113 -> 0
B114: Down Case | D114: - | E114: - | F114: - | G114: - | H114: - | I114: 0 | J114: =I114 -> 0 | K114: =J114 -> 0 | L114: =K114 -> 0 | M114: =L114 -> 0 | N114: =M114 -> 0 | O114: =N114 -> 0 | P114: =O114 -> 0 | Q114: =P114 -> 0 | R114: =Q114 -> 0
B115: ="Current Case: "&CHOOSE($I$4,$B$14,$B$15,$B$16) -> Current Case: Base Case | I115: =CHOOSE($I$4,I$72,I$73,I$74) -> 0 | J115: =CHOOSE($I$4,J$72,J$73,J$74) -> 0 | K115: =CHOOSE($I$4,K$72,K$73,K$74) -> 0 | L115: =CHOOSE($I$4,L$72,L$73,L$74) -> 0 | M115: =CHOOSE($I$4,M$72,M$73,M$74) -> 0 | N115: =CHOOSE($I$4,N$72,N$73,N$74) -> 0 | O115: =CHOOSE($I$4,O$72,O$73,O$74) -> 0 | P115: =CHOOSE($I$4,P$72,P$73,P$74) -> 0 | ... R115: =CHOOSE($I$4,R$72,R$73,R$74) -> 0
A117: # | B117: Current Liablities
B119: Other Current Liablities
B120: Management Case | D120: - | E120: - | F120: - | G120: - | H120: - | I120: 0 | J120: =I120 -> 0 | K120: =J120 -> 0 | L120: =K120 -> 0 | M120: =L120 -> 0 | N120: =M120 -> 0 | O120: =N120 -> 0 | P120: =O120 -> 0 | Q120: =P120 -> 0 | R120: =Q120 -> 0
B121: Base Case | D121: - | E121: - | F121: - | G121: - | H121: - | I121: 0 | J121: =I121 -> 0 | K121: =J121 -> 0 | L121: =K121 -> 0 | M121: =L121 -> 0 | N121: =M121 -> 0 | O121: =N121 -> 0 | P121: =O121 -> 0 | Q121: =P121 -> 0 | R121: =Q121 -> 0
B122: Down Case | D122: - | E122: - | F122: - | G122: - | H122: - | I122: 0 | J122: =I122 -> 0 | K122: =J122 -> 0 | L122: =K122 -> 0 | M122: =L122 -> 0 | N122: =M122 -> 0 | O122: =N122 -> 0 | P122: =O122 -> 0 | Q122: =P122 -> 0 | R122: =Q122 -> 0
B123: ="Current Case: "&CHOOSE($I$4,$B$14,$B$15,$B$16) -> Current Case: Base Case | I123: =CHOOSE($I$4,I$120,I$121,I$122) -> 0 | J123: =CHOOSE($I$4,J$120,J$121,J$122) -> 0 | K123: =CHOOSE($I$4,K$120,K$121,K$122) -> 0 | L123: =CHOOSE($I$4,L$120,L$121,L$122) -> 0 | M123: =CHOOSE($I$4,M$120,M$121,M$122) -> 0 | N123: =CHOOSE($I$4,N$120,N$121,N$122) -> 0 | O123: =CHOOSE($I$4,O$120,O$121,O$122) -> 0 | P123: =CHOOSE($I$4,P$120,P$121,P$122) -> 0 | ... R123: =CHOOSE($I$4,R$120,R$121,R$122) -> 0
B125: Short Term Provisions
B126: Management Case | D126: - | E126: - | F126: - | G126: - | H126: - | I126: 0 | J126: =I126 -> 0 | K126: =J126 -> 0 | L126: =K126 -> 0 | M126: =L126 -> 0 | N126: =M126 -> 0 | O126: =N126 -> 0 | P126: =O126 -> 0 | Q126: =P126 -> 0 | R126: =Q126 -> 0
B127: Base Case | D127: - | E127: - | F127: - | G127: - | H127: - | I127: 0 | J127: =I127 -> 0 | K127: =J127 -> 0 | L127: =K127 -> 0 | M127: =L127 -> 0 | N127: =M127 -> 0 | O127: =N127 -> 0 | P127: =O127 -> 0 | Q127: =P127 -> 0 | R127: =Q127 -> 0
B128: Down Case | D128: - | E128: - | F128: - | G128: - | H128: - | I128: 0 | J128: =I128 -> 0 | K128: =J128 -> 0 | L128: =K128 -> 0 | M128: =L128 -> 0 | N128: =M128 -> 0 | O128: =N128 -> 0 | P128: =O128 -> 0 | Q128: =P128 -> 0 | R128: =Q128 -> 0
B129: ="Current Case: "&CHOOSE($I$4,$B$14,$B$15,$B$16) -> Current Case: Base Case | I129: =CHOOSE($I$4,I$126,I$127,I$128) -> 0 | J129: =CHOOSE($I$4,J$126,J$127,J$128) -> 0 | K129: =CHOOSE($I$4,K$126,K$127,K$128) -> 0 | L129: =CHOOSE($I$4,L$126,L$127,L$128) -> 0 | M129: =CHOOSE($I$4,M$126,M$127,M$128) -> 0 | N129: =CHOOSE($I$4,N$126,N$127,N$128) -> 0 | O129: =CHOOSE($I$4,O$126,O$127,O$128) -> 0 | P129: =CHOOSE($I$4,P$126,P$127,P$128) -> 0 | ... R129: =CHOOSE($I$4,R$126,R$127,R$128) -> 0
...

Sheet Schedule
B2: Blue Star Ltd
B3: Schedules
E6: Forecasting
B7: Fiscal Year Ending | C7: =2025 -> 2025 | D7: =C7+1 -> 2026 | E7: =D7+1 -> 2027 | F7: =E7+1 -> 2028 | G7: =F7+1 -> 2029 | H7: =G7+1 -> 2030 | I7: =H7+1 -> 2031 | J7: =I7+1 -> 2032 | K7: =J7+1 -> 2033 | ... N7: =M7+1 -> 2036
B9: Assumptions
A11: # | B11: Revenue Schedule
B13: Revenue | C13: ='Historical Data'!K8 -> 11967.65 | D13: ='Historical Data'!L8 -> 12401.99 | E13: =D13*(1+E15) -> 14014.249 | F13: =E13*(1+F15) -> 15820.53 | G13: =F13*(1+G15) -> 17842.042 | H13: =G13*(1+H15) -> 20102.034 | I13: =H13*(1+I15) -> 22625.956 | J13: =I13*(1+J15) -> 25441.63 | K13: =J13*(1+K15) -> 28579.431 | L13: =K13*(1+L15) -> 32072.473 | ... N13: =M13*(1+N15) -> 40271.622
B15: Growth YoY % | C15: ='Control Sheet'!G14 -> 0.23564328 | D15: ='Control Sheet'!H14 -> 0.036292839 | E15: ='Control Sheet'!I17 -> 0.13 | F15: ='Control Sheet'!J17 -> 0.12888889 | G15: ='Control Sheet'!K17 -> 0.12777778 | H15: ='Control Sheet'!L17 -> 0.12666667 | I15: ='Control Sheet'!M17 -> 0.12555556 | J15: ='Control Sheet'!N17 -> 0.12444444 | K15: ='Control Sheet'!O17 -> 0.12333333 | L15: ='Control Sheet'!P17 -> 0.12222222 | ... N15: ='Control Sheet'!R17 -> 0.12
A19: # | B19: COGS Schedule
B21: COGS | C21: ='Historical Data'!K10 -> 9074.34 | D21: ='Historical Data'!L10 -> 9542.09 | E21: =E13*E23 -> 10650.829 | F21: =F13*F23 -> 12023.603 | G21: =G13*G23 -> 13559.952 | H21: =H13*H23 -> 15277.546 | I21: =I13*I23 -> 17195.726 | J21: =J13*J23 -> 19335.639 | K21: =K13*K23 -> 21720.368 | L21: =L13*L23 -> 24375.079 | ... N21: =N13*N23 -> 30606.433
B23: COGS % Revenue | C23: =C21/C13 -> 0.75823909 | D23: =D21/D13 -> 0.76939991 | E23: ='Control Sheet'!I27 -> 0.76 | F23: ='Control Sheet'!J27 -> 0.76 | G23: ='Control Sheet'!K27 -> 0.76 | H23: ='Control Sheet'!L27 -> 0.76 | I23: ='Control Sheet'!M27 -> 0.76 | J23: ='Control Sheet'!N27 -> 0.76 | K23: ='Control Sheet'!O27 -> 0.76 | L23: ='Control Sheet'!P27 -> 0.76 | ... N23: ='Control Sheet'!R27 -> 0.76
A27: # | B27: SG&A Expenses
B29: Total SG&A Expenses | C29: ='Historical Data'!K14 -> 2017.39 | D29: ='Historical Data'!L14 -> 1929.5 | E29: =E$13*E31 -> 2242.2798 | F29: =F$13*F31 -> 2531.2847 | G29: =G$13*G31 -> 2854.7267 | H29: =H$13*H31 -> 3216.3254 | I29: =I$13*I31 -> 3620.1529 | J29: =J$13*J31 -> 4070.6608 | K29: =K$13*K31 -> 4572.709 | L29: =L$13*L31 -> 5131.5957 | ... N29: =N$13*N31 -> 6443.4596
B31: SG&A % Revenue | C31: =C29/C13 -> 0.16857027 | D31: =D29/D13 -> 0.15557987 | E31: ='Control Sheet'!I35 -> 0.16 | F31: ='Control Sheet'!J35 -> 0.16 | G31: ='Control Sheet'!K35 -> 0.16 | H31: ='Control Sheet'!L35 -> 0.16 | I31: ='Control Sheet'!M35 -> 0.16 | J31: ='Control Sheet'!N35 -> 0.16 | K31: ='Control Sheet'!O35 -> 0.16 | L31: ='Control Sheet'!P35 -> 0.16 | ... N31: ='Control Sheet'!R35 -> 0.16
A33: # | B33: Non Current Assets
B35: Tangible Assets & Capex
B37: Net Tangible Assets | C37: ='Historical Data'!K65 -> 1422.38 | D37: ='Historical Data'!L65 -> 1439.17 | E37: =E43 -> 1579.3125 | F37: =F43 -> 1737.5178 | G37: =G43 -> 1915.9382 | H37: =H43 -> 2157.1626 | I37: =I43 -> 2428.6741 | J37: =J43 -> 2733.9736 | K37: =K43 -> 2991.1885 | L37: =L43 -> 3279.8408 | ... N37: =N43 -> 3656.6681
B38: Net Growth YoY % | E38: =E37/D37-1 -> 0.097377299 | F38: =F37/E37-1 -> 0.10017352 | G38: =G37/F37-1 -> 0.10268696 | H38: =H37/G37-1 -> 0.12590406 | I38: =I37/H37-1 -> 0.12586509 | J38: =J37/I37-1 -> 0.12570627 | K38: =K37/J37-1 -> 0.094080966 | L38: =L37/K37-1 -> 0.096500857 | ... N38: =N37/M37-1 -> 0.046082886
B40: Opening Tangible Assets | E40: =D37 -> 1439.17 | F40: =E37 -> 1579.3125 | G40: =F37 -> 1737.5178 | H40: =G37 -> 1915.9382 | I40: =H37 -> 2157.1626 | J40: =I37 -> 2428.6741 | K40: =J37 -> 2733.9736 | L40: =K37 -> 2991.1885 | ... N40: =M37 -> 3495.5816
B41: Add: Capex | E41: =E$13*'Control Sheet'!I137 -> 294.29922 | F41: =F$13*'Control Sheet'!J137 -> 332.23112 | G41: =G$13*'Control Sheet'!K137 -> 374.68288 | H41: =H$13*'Control Sheet'!L137 -> 462.34678 | I41: =I$13*'Control Sheet'!M137 -> 520.39698 | J41: =J$13*'Control Sheet'!N137 -> 585.1575 | K41: =K$13*'Control Sheet'!O137 -> 571.58863 | L41: =L$13*'Control Sheet'!P137 -> 641.44946 | ... N41: =N$13*'Control Sheet'!R137 -> 604.07434
B42: Less: Depreciation | E42: =E13*1.1% -> 154.15674 | F42: =F13*1.1% -> 174.02583 | G42: =G13*1.1% -> 196.26246 | H42: =H13*1.1% -> 221.12237 | I42: =I13*1.1% -> 248.88551 | J42: =J13*1.1% -> 279.85793 | K42: =K13*1.1% -> 314.37374 | L42: =L13*1.1% -> 352.7972 | ... N42: =N13*1.1% -> 442.98785
B43: Closing Tangible Assets | E43: =E40+E41-E42 -> 1579.3125 | F43: =F40+F41-F42 -> 1737.5178 | G43: =G40+G41-G42 -> 1915.9382 | H43: =H40+H41-H42 -> 2157.1626 | I43: =I40+I41-I42 -> 2428.6741 | J43: =J40+J41-J42 -> 2733.9736 | K43: =K40+K41-K42 -> 2991.1885 | L43: =L40+L41-L42 -> 3279.8408 | ... N43: =N40+N41-N42 -> 3656.6681
B46: Depreciation % Closing Tangibles | E46: =E42/E43 -> 0.097610028 | F46: =F42/F43 -> 0.10015772 | G46: =G42/G43 -> 0.10243674 | H46: =H42/H43 -> 0.10250612 | I46: =I42/I43 -> 0.10247794 | J46: =J42/J43 -> 0.10236307 | K46: =K42/K43 -> 0.10509994 | L46: =L42/L43 -> 0.10756534 | ... N46: =N42/N43 -> 0.12114522
B48: Intangible Assets & Capex
B50: Net Intangible Assets | C50: ='Historical Data'!K66 -> 113.33 | D50: ='Historical Data'!L66 -> 155.56 | E50: =E13*E51 -> 140.14249 | F50: =F13*F51 -> 158.2053 | G50: =G13*G51 -> 178.42042 | H50: =H13*H51 -> 201.02034 | I50: =I13*I51 -> 226.25956 | J50: =J13*J51 -> 254.4163 | K50: =K13*K51 -> 285.79431 | L50: =L13*L51 -> 320.72473 | ... N50: =N13*N51 -> 402.71622
B51: Intangible Assets % Revenue | E51: ='Control Sheet'!I39 -> 0.01 | F51: 0.01 | G51: 0.01 | H51: 0.01 | I51: 0.01 | J51: 0.01 | K51: 0.01 | L51: 0.01 | M51: 0.01 | N51: 0.01
B53: Opening Intangible Assets | E53: =D56 -> 155.56 | F53: =E56 -> 140.14249 | G53: =F56 -> 158.2053 | H53: =G56 -> 178.42042 | I53: =H56 -> 201.02034 | J53: =I56 -> 226.25956 | K53: =J56 -> 254.4163 | L53: =K56 -> 285.79431 | ... N53: =M56 -> 359.56806
B54: Addition during the year | E54: =E56-E53+E55 -> 26.625233 | F54: =F56-F53+F55 -> 65.524398 | G54: =G56-G53+G55 -> 73.741247 | H54: =H56-H53+H55 -> 82.906021 | I54: =I56-I53+I55 -> 93.117087 | J54: =J56-J53+J55 -> 104.48164 | K54: =K56-K53+K55 -> 117.1163 | L54: =L56-L53+L55 -> 131.14783 | ... N54: =N56-N53+N55 -> 163.96303
B55: Less: Depreciation | E55: =E13*0.3% -> 42.042746 | F55: =F13*0.3% -> 47.461589 | G55: =G13*0.3% -> 53.526125 | H55: =H13*0.3% -> 60.306101 | I55: =I13*0.3% -> 67.877867 | J55: =J13*0.3% -> 76.324891 | K55: =K13*0.3% -> 85.738294 | L55: =L13*0.3% -> 96.217419 | ... N55: =N13*0.3% -> 120.81487
B56: Closing Intangible Assets | D56: =D50 -> 155.56 | E56: =E50 -> 140.14249 | F56: =F50 -> 158.2053 | G56: =G50 -> 178.42042 | H56: =H50 -> 201.02034 | I56: =I50 -> 226.25956 | J56: =J50 -> 254.4163 | K56: =K50 -> 285.79431 | ... N56: =N50 -> 402.71622
B58: Capital WIP
B59: Capital WIP | C59: ='Historical Data'!K67 -> 73.36 | D59: ='Historical Data'!L67 -> 65.47 | E59: =D59*(1+E60) -> 65.47 | F59: =E59 -> 65.47 | G59: =F59 -> 65.47 | H59: =G59 -> 65.47 | I59: =H59 -> 65.47 | J59: =I59 -> 65.47 | K59: =J59 -> 65.47 | L59: =K59 -> 65.47 | M59: =L59 -> 65.47 | N59: =M59 -> 65.47
B60: Growth YoY % | E60: ='Control Sheet'!I45 -> 0 | F60: ='Control Sheet'!J45 -> 0 | G60: ='Control Sheet'!K45 -> 0 | H60: ='Control Sheet'!L45 -> 0 | I60: ='Control Sheet'!M45 -> 0 | J60: ='Control Sheet'!N45 -> 0 | K60: ='Control Sheet'!O45 -> 0 | L60: ='Control Sheet'!P45 -> 0 | ... N60: ='Control Sheet'!R45 -> 0
B62: Intangible Capital WIP
B63: Capital WIP | C63: ='Historical Data'!K68 -> 49.81 | D63: ='Historical Data'!L68 -> 0 | E63: =D63*(1+E64) -> 0 | F63: =E63 -> 0 | G63: =F63 -> 0 | H63: =G63 -> 0 | I63: =H63 -> 0 | J63: =I63 -> 0 | K63: =J63 -> 0 | L63: =K63 -> 0 | M63: =L63 -> 0 | N63: =M63 -> 0
B64: Growth YoY % | E64: ='Control Sheet'!I51 -> 0 | F64: ='Control Sheet'!J51 -> 0 | G64: ='Control Sheet'!K51 -> 0 | H64: ='Control Sheet'!L51 -> 0 | I64: ='Control Sheet'!M51 -> 0 | J64: ='Control Sheet'!N51 -> 0 | K64: ='Control Sheet'!O51 -> 0 | L64: ='Control Sheet'!P51 -> 0 | ... N64: ='Control Sheet'!R51 -> 0
B66: Non Current Investments
B67: Non Current Investments | C67: ='Historical Data'!K69 -> 17.94 | D67: ='Historical Data'!L69 -> 21.94 | E67: =D67*(1+E68) -> 21.94 | F67: =E67 -> 21.94 | G67: =F67 -> 21.94 | H67: =G67 -> 21.94 | I67: =H67 -> 21.94 | J67: =I67 -> 21.94 | K67: =J67 -> 21.94 | L67: =K67 -> 21.94 | M67: =L67 -> 21.94 | N67: =M67 -> 21.94
B68: Growth YoY % | E68: ='Control Sheet'!I57 -> 0 | F68: ='Control Sheet'!J57 -> 0 | G68: ='Control Sheet'!K57 -> 0 | H68: ='Control Sheet'!L57 -> 0 | I68: ='Control Sheet'!M57 -> 0 | J68: ='Control Sheet'!N57 -> 0 | K68: ='Control Sheet'!O57 -> 0 | L68: ='Control Sheet'!P57 -> 0 | ... N68: ='Control Sheet'!R57 -> 0
B70: Deferred Tax Asset (Net)
B71: Deferred Tax Asset (Net) | C71: ='Historical Data'!K70 -> 8.9 | D71: ='Historical Data'!L70 -> 9.26 | E71: =D71*(1+E72) -> 9.26 | F71: =E71*(1+F72) -> 9.26 | G71: =F71*(1+G72) -> 9.26 | H71: =G71*(1+H72) -> 9.26 | I71: =H71*(1+I72) -> 9.26 | J71: =I71*(1+J72) -> 9.26 | K71: =J71*(1+K72) -> 9.26 | L71: =K71*(1+L72) -> 9.26 | ... N71: =M71*(1+N72) -> 9.26
B72: Growth YoY % | E72: ='Control Sheet'!I63 -> 0 | F72: ='Control Sheet'!J63 -> 0 | G72: ='Control Sheet'!K63 -> 0 | H72: ='Control Sheet'!L63 -> 0 | I72: ='Control Sheet'!M63 -> 0 | J72: ='Control Sheet'!N63 -> 0 | K72: ='Control Sheet'!O63 -> 0 | L72: ='Control Sheet'!P63 -> 0 | ... N72: ='Control Sheet'!R63 -> 0
B74: Long Term Loans And Advances
B75: Long Term Loans And Advances | C75: ='Historical Data'!K71 -> 20.05 | D75: ='Historical Data'!L71 -> 23.31 | E75: =D75*(1+E76) -> 23.31 | F75: =E75*(1+F76) -> 23.31 | G75: =F75*(1+G76) -> 23.31 | H75: =G75*(1+H76) -> 23.31 | I75: =H75*(1+I76) -> 23.31 | J75: =I75*(1+J76) -> 23.31 | K75: =J75*(1+K76) -> 23.31 | L75: =K75*(1+L76) -> 23.31 | ... N75: =M75*(1+N76) -> 23.31
B76: Growth YoY % | E76: ='Control Sheet'!I69 -> 0 | F76: ='Control Sheet'!J69 -> 0 | G76: ='Control Sheet'!K69 -> 0 | H76: ='Control Sheet'!L69 -> 0 | I76: ='Control Sheet'!M69 -> 0 | J76: ='Control Sheet'!N69 -> 0 | K76: ='Control Sheet'!O69 -> 0 | L76: ='Control Sheet'!P69 -> 0 | ... N76: ='Control Sheet'!R69 -> 0
B78: Other Non-Current Assets
B79: Other Non-Current Assets | C79: ='Historical Data'!K72 -> 238.96 | D79: ='Historical Data'!L72 -> 473 | E79: =D79*(1+E80) -> 473 | F79: =E79*(1+F80) -> 473 | G79: =F79*(1+G80) -> 473 | H79: =G79*(1+H80) -> 473 | I79: =H79*(1+I80) -> 473 | J79: =I79*(1+J80) -> 473 | K79: =J79*(1+K80) -> 473 | L79: =K79*(1+L80) -> 473 | ... N79: =M79*(1+N80) -> 473
B80: Growth YoY % | E80: ='Control Sheet'!I75 -> 0 | F80: ='Control Sheet'!J75 -> 0 | G80: ='Control Sheet'!K75 -> 0 | H80: ='Control Sheet'!L75 -> 0 | I80: ='Control Sheet'!M75 -> 0 | J80: ='Control Sheet'!N75 -> 0 | K80: ='Control Sheet'!O75 -> 0 | L80: ='Control Sheet'!P75 -> 0 | ... N80: ='Control Sheet'!R75 -> 0
A82: # | B82: Non Current Liablities
B84: Deferred Tax Liablities (Net) | C84: ='Historical Data'!K49 -> 13.45 | D84: ='Historical Data'!L49 -> 31.6 | E84: =D84*(1+E86) -> 31.6 | F84: =E84 -> 31.6 | G84: =F84 -> 31.6 | H84: =G84 -> 31.6 | I84: =H84 -> 31.6 | J84: =I84 -> 31.6 | K84: =J84 -> 31.6 | L84: =K84 -> 31.6 | M84: =L84 -> 31.6 | N84: =M84 -> 31.6
B86: Growth YoY % | E86: ='Control Sheet'!I103 -> 0 | F86: ='Control Sheet'!J103 -> 0 | G86: ='Control Sheet'!K103 -> 0 | H86: ='Control Sheet'!L103 -> 0 | I86: ='Control Sheet'!M103 -> 0 | J86: ='Control Sheet'!N103 -> 0 | K86: ='Control Sheet'!O103 -> 0 | L86: ='Control Sheet'!P103 -> 0 | ... N86: ='Control Sheet'!R103 -> 0
B88: Other Long Term Liablities | C88: ='Historical Data'!K50 -> 206.73 | D88: ='Historical Data'!L50 -> 191.49 | E88: =D88*(1+E89) -> 191.49 | F88: =E88*(1+F89) -> 191.49 | G88: =F88*(1+G89) -> 191.49 | H88: =G88*(1+H89) -> 191.49 | I88: =H88*(1+I89) -> 191.49 | J88: =I88*(1+J89) -> 191.49 | K88: =J88*(1+K89) -> 191.49 | L88: =K88*(1+L89) -> 191.49 | ... N88: =M88*(1+N89) -> 191.49
B90: Growth YoY % | E90: ='Control Sheet'!I109 -> 0 | F90: ='Control Sheet'!J109 -> 0 | G90: ='Control Sheet'!K109 -> 0 | H90: ='Control Sheet'!L109 -> 0 | I90: ='Control Sheet'!M109 -> 0 | J90: ='Control Sheet'!N109 -> 0 | K90: ='Control Sheet'!O109 -> 0 | L90: ='Control Sheet'!P109 -> 0 | ... N90: ='Control Sheet'!R109 -> 0
B92: Long Term Provisions | C92: ='Historical Data'!K51 -> 25.31 | D92: ='Historical Data'!L51 -> 52.77 | E92: =D92*(1+E94) -> 52.77 | F92: =E92*(1+F94) -> 52.77 | G92: =F92*(1+G94) -> 52.77 | H92: =G92*(1+H94) -> 52.77 | I92: =H92*(1+I94) -> 52.77 | J92: =I92*(1+J94) -> 52.77 | K92: =J92*(1+K94) -> 52.77 | L92: =K92*(1+L94) -> 52.77 | ... N92: =M92*(1+N94) -> 52.77
B94: Growth YoY % | E94: ='Control Sheet'!I115 -> 0 | F94: ='Control Sheet'!J115 -> 0 | G94: ='Control Sheet'!K115 -> 0 | H94: ='Control Sheet'!L115 -> 0 | I94: ='Control Sheet'!M115 -> 0 | J94: ='Control Sheet'!N115 -> 0 | K94: ='Control Sheet'!O115 -> 0 | L94: ='Control Sheet'!P115 -> 0 | ... N94: ='Control Sheet'!R115 -> 0
A96: # | B96: Current Liablities
B98: Other Current Liablities
B99: Other Current Liablities | C99: ='Historical Data'!K57 -> 1206.33 | D99: ='Historical Data'!L57 -> 1160.11 | E99: =D99*(1+E100) -> 1160.11 | F99: =E99*(1+F100) -> 1160.11 | G99: =F99*(1+G100) -> 1160.11 | H99: =G99*(1+H100) -> 1160.11 | I99: =H99*(1+I100) -> 1160.11 | J99: =I99*(1+J100) -> 1160.11 | K99: =J99*(1+K100) -> 1160.11 | L99: =K99*(1+L100) -> 1160.11 | ... N99: =M99*(1+N100) -> 1160.11
B100: Growth YoY % | E100: ='Control Sheet'!I123 -> 0 | F100: ='Control Sheet'!J123 -> 0 | G100: ='Control Sheet'!K123 -> 0 | H100: ='Control Sheet'!L123 -> 0 | I100: ='Control Sheet'!M123 -> 0 | J100: ='Control Sheet'!N123 -> 0 | K100: ='Control Sheet'!O123 -> 0 | L100: ='Control Sheet'!P123 -> 0 | ... N100: ='Control Sheet'!R123 -> 0
B102: Short Term Provisions
B103: Short Term Provisions | C103: ='Historical Data'!K58 -> 111.08 | D103: ='Historical Data'!L58 -> 136.49 | E103: =D103*(1+E104) -> 136.49 | F103: =E103*(1+F104) -> 136.49 | G103: =F103*(1+G104) -> 136.49 | H103: =G103*(1+H104) -> 136.49 | I103: =H103*(1+I104) -> 136.49 | J103: =I103*(1+J104) -> 136.49 | K103: =J103*(1+K104) -> 136.49 | L103: =K103*(1+L104) -> 136.49 | ... N103: =M103*(1+N104) -> 136.49
B104: Growth YoY % | E104: ='Control Sheet'!I129 -> 0 | F104: ='Control Sheet'!J129 -> 0 | G104: ='Control Sheet'!K129 -> 0 | H104: ='Control Sheet'!L129 -> 0 | I104: ='Control Sheet'!M129 -> 0 | J104: ='Control Sheet'!N129 -> 0 | K104: ='Control Sheet'!O129 -> 0 | L104: ='Control Sheet'!P129 -> 0 | ... N104: ='Control Sheet'!R129 -> 0
A106: # | B106: Depreciation & Amortization Schedule
C108: 11
B109: Total Depreciation (Including Amortization) | E109: =E42+E55 -> 196.19948 | F109: =F42+F55 -> 221.48742 | G109: =G42+G55 -> 249.78858 | H109: =H42+H55 -> 281.42847 | I109: =I42+I55 -> 316.76338 | J109: =J42+J55 -> 356.18282 | K109: =K42+K55 -> 400.11204 | L109: =L42+L55 -> 449.01462 | ... N109: =N42+N55 -> 563.80271
B110: Net Depreciable Assets | E110: =E43+E56 -> 1719.455 | F110: =F43+F56 -> 1895.7231 | G110: =G43+G56 -> 2094.3586 | H110: =H43+H56 -> 2358.1829 | I110: =I43+I56 -> 2654.9336 | J110: =J43+J56 -> 2988.3899 | K110: =K43+K56 -> 3276.9828 | L110: =L43+L56 -> 3600.5655 | ... N110: =N43+N56 -> 4059.3843
B112: Depreciation % Net Depreciable Assets | E112: =E109/E110 -> 0.11410562 | F112: =F109/F110 -> 0.11683532 | G112: =G109/G110 -> 0.11926734 | H112: =H109/H110 -> 0.11934124 | I112: =I109/I110 -> 0.11931122 | J112: =J109/J110 -> 0.11918887 | K112: =K109/K110 -> 0.12209769 | L112: =L109/L110 -> 0.12470669 | ... N112: =N109/N110 -> 0.13888873
B113: Total Depreciation % Revenue | E113: =E109/E13 -> 0.014 | F113: =F109/F13 -> 0.014 | G113: =G109/G13 -> 0.014 | H113: =H109/H13 -> 0.014 | I113: =I109/I13 -> 0.014 | J113: =J109/J13 -> 0.014 | K113: =K109/K13 -> 0.014 | L113: =L109/L13 -> 0.014 | ... N113: =N109/N13 -> 0.014
B115: Depreciation & Amortization Watefall Schedule
B117: 2026 | D117: ='Historical Data'!L19 -> 178.79 | E117: =D117 -> 178.79 | F117: =E117 -> 178.79 | G117: =F117 -> 178.79 | H117: =G117 -> 178.79 | I117: =H117 -> 178.79 | J117: =I117 -> 178.79 | K117: =J117 -> 178.79 | L117: =K117 -> 178.79 | ... N117: =M117 -> 178.79
B118: =B117+1 -> 2027 | E118: =E109-E117 -> 17.409482 | F118: =E118 -> 17.409482 | G118: =F118 -> 17.409482 | H118: =G118 -> 17.409482 | I118: =H118 -> 17.409482 | J118: =I118 -> 17.409482 | K118: =J118 -> 17.409482 | L118: =K118 -> 17.409482 | M118: =L118 -> 17.409482 | N118: =M118 -> 17.409482
B119: =B118+1 -> 2028 | F119: =F109-E109 -> 25.287933 | G119: =F119 -> 25.287933 | H119: =G119 -> 25.287933 | I119: =H119 -> 25.287933 | J119: =I119 -> 25.287933 | K119: =J119 -> 25.287933 | L119: =K119 -> 25.287933 | M119: =L119 -> 25.287933 | N119: =M119 -> 25.287933
B120: =B119+1 -> 2029 | G120: =G109-F109 -> 28.30117 | H120: =G120 -> 28.30117 | I120: =H120 -> 28.30117 | J120: =I120 -> 28.30117 | K120: =J120 -> 28.30117 | L120: =K120 -> 28.30117 | M120: =L120 -> 28.30117 | N120: =M120 -> 28.30117
B121: =B120+1 -> 2030 | H121: =H109-G109 -> 31.639887 | I121: =H121 -> 31.639887 | J121: =I121 -> 31.639887 | K121: =J121 -> 31.639887 | L121: =K121 -> 31.639887 | M121: =L121 -> 31.639887 | N121: =M121 -> 31.639887
B122: =B121+1 -> 2031 | I122: =I109-H109 -> 35.334908 | J122: =I122 -> 35.334908 | K122: =J122 -> 35.334908 | L122: =K122 -> 35.334908 | M122: =L122 -> 35.334908 | N122: =M122 -> 35.334908
B123: =B122+1 -> 2032 | J123: =J109-I109 -> 39.419443 | K123: =J123 -> 39.419443 | L123: =K123 -> 39.419443 | M123: =L123 -> 39.419443 | N123: =M123 -> 39.419443
B124: =B123+1 -> 2033 | K124: =K109-J109 -> 43.929215 | L124: =K124 -> 43.929215 | M124: =L124 -> 43.929215 | N124: =M124 -> 43.929215
B125: =B124+1 -> 2034 | L125: =L109-K109 -> 48.902582 | M125: =L125 -> 48.902582 | N125: =M125 -> 48.902582
B126: =B125+1 -> 2035 | M126: =M109-L109 -> 54.38066 | N126: =M126 -> 54.38066
B127: =B126+1 -> 2036 | N127: =N109-M109 -> 60.407434
B128: Total Depreciation | D128: =SUM(D117:D127) -> 178.79 | E128: =SUM(E117:E127) -> 196.19948 | F128: =SUM(F117:F127) -> 221.48742 | G128: =SUM(G117:G127) -> 249.78858 | H128: =SUM(H117:H127) -> 281.42847 | I128: =SUM(I117:I127) -> 316.76338 | J128: =SUM(J117:J127) -> 356.18282 | K128: =SUM(K117:K127) -> 400.11204 | ... N128: =SUM(N117:N127) -> 563.80271
A130: # | B130: Reserves & Surplus (Other Equity) Schedule
B132: Opening Balance | E132: ='Historical Data'!L43 -> 3390.29 | F132: =E135 -> 3873.0617 | G132: =F135 -> 4420.4812 | H132: =G135 -> 5037.8266 | I132: =H135 -> 5733.3442 | J132: =I135 -> 6516.1597 | K132: =J135 -> 7396.3607 | L132: =K135 -> 8385.0841 | M132: =L135 -> 9494.6115 | N132: =M135 -> 10738.47
B133: Add: Net Profit | E133: ='3 - Statement Model'!M30 -> 689.67389 | F133: ='3 - Statement Model'!N30 -> 782.02778 | G133: ='3 - Statement Model'!O30 -> 881.92202 | H133: ='3 - Statement Model'!P30 -> 993.59654 | I133: ='3 - Statement Model'!Q30 -> 1118.308 | J133: ='3 - Statement Model'!R30 -> 1257.4299 | K133: ='3 - Statement Model'!S30 -> 1412.4621 | L133: ='3 - Statement Model'!T30 -> 1585.0391 | ... N133: ='3 - Statement Model'!V30 -> 1990.1013
B134: Less: Dividend Paid | E134: =E133*E137 -> 206.90217 | F134: =F133*F137 -> 234.60833 | G134: =G133*G137 -> 264.57661 | H134: =H133*H137 -> 298.07896 | I134: =I133*I137 -> 335.49239 | J134: =J133*J137 -> 377.22898 | K134: =K133*K137 -> 423.73862 | L134: =L133*L137 -> 475.51172 | ... N134: =N133*N137 -> 597.0304
B135: Closing balance | E135: =E132+E133-E134 -> 3873.0617 | F135: =F132+F133-F134 -> 4420.4812 | G135: =G132+G133-G134 -> 5037.8266 | H135: =H132+H133-H134 -> 5733.3442 | I135: =I132+I133-I134 -> 6516.1597 | J135: =J132+J133-J134 -> 7396.3607 | K135: =K132+K133-K134 -> 8385.0841 | L135: =L132+L133-L134 -> 9494.6115 | ... N135: =N132+N133-N134 -> 12131.541
B137: Dividend Payout Ratio | E137: ='Control Sheet'!I144 -> 0.3 | F137: ='Control Sheet'!J144 -> 0.3 | G137: ='Control Sheet'!K144 -> 0.3 | H137: ='Control Sheet'!L144 -> 0.3 | I137: ='Control Sheet'!M144 -> 0.3 | J137: ='Control Sheet'!N144 -> 0.3 | K137: ='Control Sheet'!O144 -> 0.3 | L137: ='Control Sheet'!P144 -> 0.3 | ... N137: ='Control Sheet'!R144 -> 0.3
A139: # | B139: Working Capital Schedule
B141: Trade Receivables
B142: Revenue | C142: =C13 -> 11967.65 | D142: =D13 -> 12401.99 | E142: =E13 -> 14014.249 | F142: =F13 -> 15820.53 | G142: =G13 -> 17842.042 | H142: =H13 -> 20102.034 | I142: =I13 -> 22625.956 | J142: =J13 -> 25441.63 | ... N142: =N13 -> 40271.622
B143: Trade Receivables | C143: ='Historical Data'!K78 -> 1959.37 | D143: ='Historical Data'!L78 -> 2139.7 | E143: =(E144*E142)/365 -> 2495.6881 | F143: =(F144*F142)/365 -> 2817.3546 | G143: =(G144*G142)/365 -> 3177.3499 | H143: =(H144*H142)/365 -> 3579.8142 | I143: =(I144*I142)/365 -> 4029.2798 | J143: =(J144*J142)/365 -> 4530.7013 | K143: =(K144*K142)/365 -> 5089.4878 | L143: =(L144*L142)/365 -> 5711.5363 | ... N143: =(N144*N142)/365 -> 7171.6588
B144: Trade Receivable Days | C144: =(C143/C142)*365 -> 59.758603 | D144: =(D143/D142)*365 -> 62.972999 | E144: 65 | F144: =E144 -> 65 | G144: =F144 -> 65 | H144: =G144 -> 65 | I144: =H144 -> 65 | J144: =I144 -> 65 | K144: =J144 -> 65 | L144: =K144 -> 65 | M144: =L144 -> 65 | N144: =M144 -> 65
B145: Trade Receivables % Revenue | C145: =C143/C142 -> 0.1637222 | D145: =D143/D142 -> 0.17252876 | E145: =E143/E142 -> 0.17808219 | F145: =F143/F142 -> 0.17808219 | G145: =G143/G142 -> 0.17808219 | H145: =H143/H142 -> 0.17808219 | I145: =I143/I142 -> 0.17808219 | J145: =J143/J142 -> 0.17808219 | ... N145: =N143/N142 -> 0.17808219
B147: Inventory
B148: COGS | C148: =C166 -> 9074.34 | D148: =D166 -> 9542.09 | E148: =E21 -> 10650.829 | F148: =F21 -> 12023.603 | G148: =G21 -> 13559.952 | H148: =H21 -> 15277.546 | I148: =I21 -> 17195.726 | J148: =J21 -> 19335.639 | K148: =K21 -> 21720.368 | L148: =L21 -> 24375.079 | ... N148: =N21 -> 30606.433
B149: Inventory | C149: ='Historical Data'!K77 -> 2149.15 | D149: ='Historical Data'!L77 -> 2166.2 | E149: =(E150*E148)/365 -> 2188.5265 | F149: =(F150*F148)/365 -> 2470.6033 | G149: =(G150*G148)/365 -> 2786.2915 | H149: =(H150*H148)/365 -> 3013.6528 | I149: =(I150*I148)/365 -> 3392.0337 | J149: =(J150*J148)/365 -> 3814.1534 | K149: =(K150*K148)/365 -> 4284.5657 | L149: =(L150*L148)/365 -> 4674.6728 | ... N149: =(N150*N148)/365 -> 5869.7269
B150: Inventory Days | C150: ='Assumptions Working'!L470 -> 71.523684 | D150: ='Assumptions Working'!M470 -> 82.534474 | E150: 75 | F150: =E150 -> 75 | G150: =F150 -> 75 | H150: 72 | I150: =H150 -> 72 | J150: =I150 -> 72 | K150: =J150 -> 72 | L150: 70 | M150: 70 | N150: 70
B151: Inventory % COGS | C151: =C149/C148 -> 0.23683816 | D151: =D149/D148 -> 0.22701526 | E151: =E149/E148 -> 0.20547945 | F151: =F149/F148 -> 0.20547945 | G151: =G149/G148 -> 0.20547945 | H151: =H149/H148 -> 0.19726027 | I151: =I149/I148 -> 0.19726027 | J151: =J149/J148 -> 0.19726027 | ... N151: =N149/N148 -> 0.19178082
B153: Current Investments
B154: Current Investments | C154: ='Historical Data'!K76 -> 414.12 | D154: ='Historical Data'!L76 -> 435.26 | E154: =D154*(1+E155) -> 435.26 | F154: =E154*(1+F155) -> 435.26 | G154: =F154*(1+G155) -> 435.26 | H154: =G154*(1+H155) -> 435.26 | I154: =H154*(1+I155) -> 435.26 | J154: =I154*(1+J155) -> 435.26 | K154: =J154*(1+K155) -> 435.26 | L154: =K154*(1+L155) -> 435.26 | ... N154: =M154*(1+N155) -> 435.26
...

Sheet Ratio Analysis
B2: Ratio Analysis - Bluestar Ltd
B3: All figures in INR Crores.
B5: Fiscal Year Ending | C5: =2022 -> 2022 | D5: =C5+1 -> 2023 | E5: =D5+1 -> 2024 | F5: =E5+1 -> 2025 | G5: =F5+1 -> 2026 | H5: =G5+1 -> 2027 | I5: =H5+1 -> 2028 | J5: =I5+1 -> 2029 | K5: =J5+1 -> 2030 | ... Q5: =P5+1 -> 2036
A7: # | B7: Liquidity Ratio
B9: Current Assets | C9: ='3 - Statement Model'!H80 -> 3483.43 | D9: ='3 - Statement Model'!I80 -> 4250.61 | E9: ='3 - Statement Model'!J80 -> 5040.03 | F9: ='3 - Statement Model'!K80 -> 6312.77 | G9: ='3 - Statement Model'!L80 -> 6388.27 | H9: ='3 - Statement Model'!M80 -> 7892.5474 | I9: ='3 - Statement Model'!N80 -> 8871.5247 | J9: ='3 - Statement Model'!O80 -> 9970.4872 | ... Q9: ='3 - Statement Model'!V80 -> 22646.883
B10: Current Liablities | C10: ='3 - Statement Model'!H57 -> 2969.2 | D10: ='3 - Statement Model'!I57 -> 3783.75 | E10: ='3 - Statement Model'!J57 -> 3879.62 | F10: ='3 - Statement Model'!K57 -> 4944.39 | G10: ='3 - Statement Model'!L57 -> 4866.26 | H10: ='3 - Statement Model'!M57 -> 6012.4907 | I10: ='3 - Statement Model'!N57 -> 6620.3166 | J10: ='3 - Statement Model'!O57 -> 7300.5693 | ... Q10: ='3 - Statement Model'!V57 -> 14848.277
B11: Current Ratio | C11: =C9/C10 -> 1.1731881 | D11: =D9/D10 -> 1.1233855 | E11: =E9/E10 -> 1.299104 | F11: =F9/F10 -> 1.2767541 | G11: =G9/G10 -> 1.3127679 | H11: =H9/H10 -> 1.3126918 | I11: =I9/I10 -> 1.3400454 | J11: =J9/J10 -> 1.3657137 | ... Q11: =Q9/Q10 -> 1.5252196
B13: Current Assets | C13: ='Ratio Analysis'!C9 -> 3483.43 | D13: ='Ratio Analysis'!D9 -> 4250.61 | E13: ='Ratio Analysis'!E9 -> 5040.03 | F13: ='Ratio Analysis'!F9 -> 6312.77 | G13: ='Ratio Analysis'!G9 -> 6388.27 | H13: ='Ratio Analysis'!H9 -> 7892.5474 | I13: ='Ratio Analysis'!I9 -> 8871.5247 | J13: ='Ratio Analysis'!J9 -> 9970.4872 | ... Q13: ='Ratio Analysis'!Q9 -> 22646.883
B14: Inventory | C14: ='3 - Statement Model'!H75 -> 1144.24 | D14: ='3 - Statement Model'!I75 -> 1433.39 | E14: ='3 - Statement Model'!J75 -> 1407.18 | F14: ='3 - Statement Model'!K75 -> 2149.15 | G14: ='3 - Statement Model'!L75 -> 2166.2 | H14: ='3 - Statement Model'!M75 -> 2188.5265 | I14: ='3 - Statement Model'!N75 -> 2470.6033 | J14: ='3 - Statement Model'!O75 -> 2786.2915 | ... Q14: ='3 - Statement Model'!V75 -> 5869.7269
B15: Prepaid Expenses | C15: 0 | D15: =C15 -> 0 | E15: =D15 -> 0 | F15: =E15 -> 0 | G15: =F15 -> 0 | H15: =G15 -> 0 | I15: =H15 -> 0 | J15: =I15 -> 0 | K15: =J15 -> 0 | ... Q15: =P15 -> 0
B16: Current liablities | C16: =C10 -> 2969.2 | D16: =D10 -> 3783.75 | E16: =E10 -> 3879.62 | F16: =F10 -> 4944.39 | G16: =G10 -> 4866.26 | H16: =H10 -> 6012.4907 | I16: =I10 -> 6620.3166 | J16: =J10 -> 7300.5693 | ... Q16: =Q10 -> 14848.277
B17: Quick Ratio | C17: =(C13-C14-C15)/C16 -> 0.78781827 | D17: =(D13-D14-D15)/D16 -> 0.74455765 | E17: =(E13-E14-E15)/E16 -> 0.93639326 | F17: =(F13-F14-F15)/F16 -> 0.84208972 | G17: =(G13-G14-G15)/G16 -> 0.86762113 | H17: =(H13-H14-H15)/H16 -> 0.94869518 | I17: =(I13-I14-I15)/I16 -> 0.96686032 | J17: =(J13-J14-J15)/J16 -> 0.98405967 | ... Q17: =(Q13-Q14-Q15)/Q16 -> 1.129906
B19: Inventory Days | C19: ='Assumptions Working'!I470 -> 78.449746 | D19: ='Assumptions Working'!J470 -> 76.098769 | E19: ='Assumptions Working'!K470 -> 70.130699 | F19: ='Assumptions Working'!L470 -> 71.523684 | G19: ='Assumptions Working'!M470 -> 82.534474 | H19: =Schedule!E150 -> 75 | I19: =Schedule!F150 -> 75 | J19: =Schedule!G150 -> 75 | K19: =Schedule!H150 -> 72 | L19: =Schedule!I150 -> 72 | M19: =Schedule!J150 -> 72 | N19: =Schedule!K150 -> 72 | O19: =Schedule!L150 -> 70 | ... Q19: =Schedule!N150 -> 70
B20: Trade Receivable Days | C20: ='Assumptions Working'!I572 -> 60.396422 | D20: ='Assumptions Working'!J572 -> 62.651016 | E20: ='Assumptions Working'!K572 -> 65.976056 | F20: =Schedule!C144 -> 59.758603 | G20: =Schedule!D144 -> 62.972999 | H20: =Schedule!E144 -> 65 | I20: =Schedule!F144 -> 65 | J20: =Schedule!G144 -> 65 | K20: =Schedule!H144 -> 65 | L20: =Schedule!I144 -> 65 | M20: =Schedule!J144 -> 65 | ... Q20: =Schedule!N144 -> 65
B21: Trade Payable Days | C21: ='Assumptions Working'!I883 -> 141.15427 | D21: ='Assumptions Working'!J883 -> 134.41214 | E21: ='Assumptions Working'!K883 -> 126.59903 | F21: =Schedule!C168 -> 137.87023 | G21: =Schedule!D168 -> 112.56904 | H21: =Schedule!E168 -> 140 | I21: =Schedule!F168 -> 140 | J21: =Schedule!G168 -> 140 | K21: =Schedule!H168 -> 140 | L21: =Schedule!I168 -> 140 | M21: =Schedule!J168 -> 140 | ... Q21: =Schedule!N168 -> 140
B22: Working Capital Days | C22: =365/('3 - Statement Model'!H8/('Ratio Analysis'!C9-'Ratio Analysis'!C10)) -> 31.046475 | D22: =365/('3 - Statement Model'!I8/('Ratio Analysis'!D9-'Ratio Analysis'!D10)) -> 21.361046 | E22: =365/('3 - Statement Model'!J8/('Ratio Analysis'!E9-'Ratio Analysis'!E10)) -> 43.730914 | F22: =365/('3 - Statement Model'!K8/('Ratio Analysis'!F9-'Ratio Analysis'!F10)) -> 41.734066 | G22: =365/('3 - Statement Model'!L8/('Ratio Analysis'!G9-'Ratio Analysis'!G10)) -> 44.793912 | H22: =365/('3 - Statement Model'!M8/('Ratio Analysis'!H9-'Ratio Analysis'!H10)) -> 48.965929 | I22: =365/('3 - Statement Model'!N8/('Ratio Analysis'!I9-'Ratio Analysis'!I10)) -> 51.938271 | J22: =365/('3 - Statement Model'!O8/('Ratio Analysis'!J9-'Ratio Analysis'!J10)) -> 54.619313 | ... Q22: =365/('3 - Statement Model'!V8/('Ratio Analysis'!Q9-'Ratio Analysis'!Q10)) -> 70.682312
B23: Cash Conversion Cycle | C23: =(C19+C20-C21) -> -2.3080989 | D23: =(D19+D20-D21) -> 4.3376472 | E23: =(E19+E20-E21) -> 9.5077292 | F23: =(F19+F20-F21) -> -6.5879381 | G23: =(G19+G20-G21) -> 32.938433 | H23: =(H19+H20-H21) -> 0 | I23: =(I19+I20-I21) -> 0 | J23: =(J19+J20-J21) -> 0 | ... Q23: =(Q19+Q20-Q21) -> -5
A25: # | B25: Leverage Ratio
B27: Total Debt | C27: ='3 - Statement Model'!H46+'3 - Statement Model'!H53 -> 477.83 | D27: ='3 - Statement Model'!I46+'3 - Statement Model'!I53 -> 577.64 | E27: ='3 - Statement Model'!J46+'3 - Statement Model'!J53 -> 166.62 | F27: ='3 - Statement Model'!K46+'3 - Statement Model'!K53 -> 199.36 | G27: ='3 - Statement Model'!L46+'3 - Statement Model'!L53 -> 626.8 | H27: ='3 - Statement Model'!M46+'3 - Statement Model'!M53 -> 630.64119 | I27: ='3 - Statement Model'!N46+'3 - Statement Model'!N53 -> 711.92383 | J27: ='3 - Statement Model'!O46+'3 - Statement Model'!O53 -> 802.89188 | ... Q27: ='3 - Statement Model'!V46+'3 - Statement Model'!V53 -> 1812.223
B28: Total Equity | C28: ='3 - Statement Model'!H42 -> 1017.58 | D28: ='3 - Statement Model'!I42 -> 1330.65 | E28: ='3 - Statement Model'!J42 -> 2610.07 | F28: ='3 - Statement Model'!K42 -> 3065.02 | G28: ='3 - Statement Model'!L42 -> 3431.41 | H28: ='3 - Statement Model'!M42 -> 3914.1817 | I28: ='3 - Statement Model'!N42 -> 4461.6012 | J28: ='3 - Statement Model'!O42 -> 5078.9466 | ... Q28: ='3 - Statement Model'!V42 -> 12172.661
B29: Debt to Equity | C29: =C27/C28 -> 0.46957487 | D29: =D27/D28 -> 0.43410363 | E29: =E27/E28 -> 0.063837368 | F29: =F27/F28 -> 0.065043621 | G29: =G27/G28 -> 0.18266543 | H29: =H27/H28 -> 0.16111699 | I29: =I27/I28 -> 0.15956689 | J29: =J27/J28 -> 0.15808236 | ... Q29: =Q27/Q28 -> 0.14887649
B31: Total Debt | C31: =C27 -> 477.83 | D31: =D27 -> 577.64 | E31: =E27 -> 166.62 | F31: =F27 -> 199.36 | G31: =G27 -> 626.8 | H31: =H27 -> 630.64119 | I31: =I27 -> 711.92383 | J31: =J27 -> 802.89188 | ... Q31: =Q27 -> 1812.223
B32: Total Assets | C32: ='3 - Statement Model'!H82 -> 4312.64 | D32: ='3 - Statement Model'!I82 -> 5399.06 | E32: ='3 - Statement Model'!J82 -> 6618.25 | F32: ='3 - Statement Model'!K82 -> 8257.5 | G32: ='3 - Statement Model'!L82 -> 8575.98 | H32: ='3 - Statement Model'!M82 -> 10204.982 | I32: ='3 - Statement Model'!N82 -> 11360.228 | J32: ='3 - Statement Model'!O82 -> 12657.826 | ... Q32: ='3 - Statement Model'!V82 -> 27299.248
B33: Debt to Assets | C33: =C31/C32 -> 0.11079756 | D33: =D31/D32 -> 0.10698899 | E33: =E31/E32 -> 0.02517584 | F33: =F31/F32 -> 0.0241429 | G33: =G31/G32 -> 0.073087857 | H33: =H31/H32 -> 0.061797382 | I33: =I31/I32 -> 0.062668095 | J33: =J31/J32 -> 0.063430473 | ... Q33: =Q31/Q32 -> 0.066383625
B35: Total Equity | C35: =C28 -> 1017.58 | D35: =D28 -> 1330.65 | E35: =E28 -> 2610.07 | F35: =F28 -> 3065.02 | G35: =G28 -> 3431.41 | H35: =H28 -> 3914.1817 | I35: =I28 -> 4461.6012 | J35: =J28 -> 5078.9466 | ... Q35: =Q28 -> 12172.661
B36: Total Assets | C36: =C32 -> 4312.64 | D36: =D32 -> 5399.06 | E36: =E32 -> 6618.25 | F36: =F32 -> 8257.5 | G36: =G32 -> 8575.98 | H36: =H32 -> 10204.982 | I36: =I32 -> 11360.228 | J36: =J32 -> 12657.826 | ... Q36: =Q32 -> 27299.248
B37: Equity Ratio | C37: =C35/C36 -> 0.23595292 | D37: =D35/D36 -> 0.24645957 | E37: =E35/E36 -> 0.39437465 | F37: =F35/F36 -> 0.37118014 | G37: =G35/G36 -> 0.4001187 | H37: =H35/H36 -> 0.38355595 | I37: =I35/I36 -> 0.39273871 | J37: =J35/J36 -> 0.40124952 | ... Q37: =Q35/Q36 -> 0.4458973
A39: # | B39: Profitability/ Margin Ratio
B41: Gross Profit | C41: ='3 - Statement Model'!H11 -> 1330.9 | D41: ='3 - Statement Model'!I11 -> 1795.65 | E41: ='3 - Statement Model'!J11 -> 2293.39 | F41: ='3 - Statement Model'!K11 -> 2893.31 | G41: ='3 - Statement Model'!L11 -> 2859.9 | H41: ='3 - Statement Model'!M11 -> 3363.4197 | I41: ='3 - Statement Model'!N11 -> 3796.9271 | J41: ='3 - Statement Model'!O11 -> 4282.09 | ... Q41: ='3 - Statement Model'!V11 -> 9665.1894
B42: Total Sales | C42: ='3 - Statement Model'!H8 -> 6045.58 | D42: ='3 - Statement Model'!I8 -> 7977.32 | E42: ='3 - Statement Model'!J8 -> 9685.36 | F42: ='3 - Statement Model'!K8 -> 11967.65 | G42: ='3 - Statement Model'!L8 -> 12401.99 | H42: ='3 - Statement Model'!M8 -> 14014.249 | I42: ='3 - Statement Model'!N8 -> 15820.53 | J42: ='3 - Statement Model'!O8 -> 17842.042 | ... Q42: ='3 - Statement Model'!V8 -> 40271.622
B43: Gross Margin | C43: =C41/C42 -> 0.2201443 | D43: =D41/D42 -> 0.22509439 | E43: =E41/E42 -> 0.23678934 | F43: =F41/F42 -> 0.24176091 | G43: =G41/G42 -> 0.23060009 | H43: =H41/H42 -> 0.24 | I43: =I41/I42 -> 0.24 | J43: =J41/J42 -> 0.24 | ... Q43: =Q41/Q42 -> 0.24
B45: EBITDA | C45: ='3 - Statement Model'!H16 -> 346.47 | D45: ='3 - Statement Model'!I16 -> 492.78 | E45: ='3 - Statement Model'!J16 -> 664.94 | F45: ='3 - Statement Model'!K16 -> 875.92 | G45: ='3 - Statement Model'!L16 -> 930.4 | H45: ='3 - Statement Model'!M16 -> 1121.1399 | I45: ='3 - Statement Model'!N16 -> 1265.6424 | J45: ='3 - Statement Model'!O16 -> 1427.3633 | ... Q45: ='3 - Statement Model'!V16 -> 3221.7298
B46: Total Sales | C46: =C42 -> 6045.58 | D46: =D42 -> 7977.32 | E46: =E42 -> 9685.36 | F46: =F42 -> 11967.65 | G46: =G42 -> 12401.99 | H46: =H42 -> 14014.249 | I46: =I42 -> 15820.53 | J46: =J42 -> 17842.042 | ... Q46: =Q42 -> 40271.622
B47: EBITDA Margin | C47: =C45/C46 -> 0.057309638 | D47: =D45/D46 -> 0.061772625 | E47: =E45/E46 -> 0.068654134 | F47: =F45/F46 -> 0.073190643 | G47: =G45/G46 -> 0.075020219 | H47: =H45/H46 -> 0.08 | I47: =I45/I46 -> 0.08 | J47: =J45/J46 -> 0.08 | ... Q47: =Q45/Q46 -> 0.08
B49: EBIT | C49: ='3 - Statement Model'!H20 -> 260.49 | D49: ='3 - Statement Model'!I20 -> 408 | E49: ='3 - Statement Model'!J20 -> 567.33 | F49: ='3 - Statement Model'!K20 -> 747.55 | G49: ='3 - Statement Model'!L20 -> 751.61 | H49: ='3 - Statement Model'!M20 -> 924.94041 | I49: ='3 - Statement Model'!N20 -> 1044.155 | J49: ='3 - Statement Model'!O20 -> 1177.5748 | ... Q49: ='3 - Statement Model'!V20 -> 2657.9271
B50: Total Sales | C50: =C46 -> 6045.58 | D50: =D46 -> 7977.32 | E50: =E46 -> 9685.36 | F50: =F46 -> 11967.65 | G50: =G46 -> 12401.99 | H50: =H46 -> 14014.249 | I50: =I46 -> 15820.53 | J50: =J46 -> 17842.042 | ... Q50: =Q46 -> 40271.622
B51: EBIT Margin | C51: =C49/C50 -> 0.043087677 | D51: =D49/D50 -> 0.051144996 | E51: =E49/E50 -> 0.058576036 | F51: =F49/F50 -> 0.062464226 | G51: =G49/G50 -> 0.060603984 | H51: =H49/H50 -> 0.066 | I51: =I49/I50 -> 0.066 | J51: =J49/J50 -> 0.066 | ... Q51: =Q49/Q50 -> 0.066
B53: Net Profit | C53: ='3 - Statement Model'!H30 -> 166.91 | D53: ='3 - Statement Model'!I30 -> 400.29 | E53: ='3 - Statement Model'!J30 -> 413.82 | F53: ='3 - Statement Model'!K30 -> 592.61 | G53: ='3 - Statement Model'!L30 -> 526.77 | H53: ='3 - Statement Model'!M30 -> 689.67389 | I53: ='3 - Statement Model'!N30 -> 782.02778 | J53: ='3 - Statement Model'!O30 -> 881.92202 | ... Q53: ='3 - Statement Model'!V30 -> 1990.1013
B54: Total Sales | C54: =C50 -> 6045.58 | D54: =D50 -> 7977.32 | E54: =E50 -> 9685.36 | F54: =F50 -> 11967.65 | G54: =G50 -> 12401.99 | H54: =H50 -> 14014.249 | I54: =I50 -> 15820.53 | J54: =J50 -> 17842.042 | ... Q54: =Q50 -> 40271.622
B55: Net Profit Margin | C55: =C53/C54 -> 0.0276086 | D55: =D53/D54 -> 0.050178506 | E55: =E53/E54 -> 0.042726342 | F55: =F53/F54 -> 0.049517658 | G55: =G53/G54 -> 0.042474635 | H55: =H53/H54 -> 0.049212334 | I55: =I53/I54 -> 0.049431201 | J55: =J53/J54 -> 0.049429433 | ... Q55: =Q53/Q54 -> 0.049416964
B57: Net Income | C57: =C53 -> 166.91 | D57: =D53 -> 400.29 | E57: =E53 -> 413.82 | F57: =F53 -> 592.61 | G57: =G53 -> 526.77 | H57: =H53 -> 689.67389 | I57: =I53 -> 782.02778 | J57: =J53 -> 881.92202 | ... Q57: =Q53 -> 1990.1013
B58: Total Assets | C58: =C32 -> 4312.64 | D58: =D32 -> 5399.06 | E58: =E32 -> 6618.25 | F58: =F32 -> 8257.5 | G58: =G32 -> 8575.98 | H58: =H32 -> 10204.982 | I58: =I32 -> 11360.228 | J58: =J32 -> 12657.826 | ... Q58: =Q32 -> 27299.248
B59: Return on Assets | C59: =C57/C58 -> 0.038702512 | D59: =D57/D58 -> 0.074140684 | E59: =E57/E58 -> 0.062527103 | F59: =F57/F58 -> 0.071766273 | G59: =G57/G58 -> 0.061423884 | H59: =H57/H58 -> 0.067582075 | I59: =I57/I58 -> 0.068839093 | J59: =J57/J58 -> 0.069674052 | ... Q59: =Q57/Q58 -> 0.072899494
B61: Net Income | C61: =C57 -> 166.91 | D61: =D57 -> 400.29 | E61: =E57 -> 413.82 | F61: =F57 -> 592.61 | G61: =G57 -> 526.77 | H61: =H57 -> 689.67389 | I61: =I57 -> 782.02778 | J61: =J57 -> 881.92202 | ... Q61: =Q57 -> 1990.1013
B62: Total Equity | C62: =C35 -> 1017.58 | D62: =D35 -> 1330.65 | E62: =E35 -> 2610.07 | F62: =F35 -> 3065.02 | G62: =G35 -> 3431.41 | H62: =H35 -> 3914.1817 | I62: =I35 -> 4461.6012 | J62: =J35 -> 5078.9466 | ... Q62: =Q35 -> 12172.661
B63: Return on Equity | C63: =C61/C62 -> 0.16402642 | D63: =D61/D62 -> 0.30082291 | E63: =E61/E62 -> 0.15854747 | F63: =F61/F62 -> 0.19334621 | G63: =G61/G62 -> 0.15351415 | H63: =H61/H62 -> 0.17619874 | I63: =I61/I62 -> 0.17527962 | J63: =J61/J62 -> 0.1736427 | ... Q63: =Q61/Q62 -> 0.16348943
A65: # | B65: Efficiency Ratio
B67: Revenue | C67: =C54 -> 6045.58 | D67: =D54 -> 7977.32 | E67: =E54 -> 9685.36 | F67: =F54 -> 11967.65 | G67: =G54 -> 12401.99 | H67: =H54 -> 14014.249 | I67: =I54 -> 15820.53 | J67: =J54 -> 17842.042 | ... Q67: =Q54 -> 40271.622
B68: Total Assets | C68: =C32 -> 4312.64 | D68: =D32 -> 5399.06 | E68: =E32 -> 6618.25 | F68: =F32 -> 8257.5 | G68: =G32 -> 8575.98 | H68: =H32 -> 10204.982 | I68: =I32 -> 11360.228 | J68: =J32 -> 12657.826 | ... Q68: =Q32 -> 27299.248
B69: Asset Turnover | C69: =C67/C68 -> 1.4018281 | D69: =D67/D68 -> 1.4775387 | E69: =E67/E68 -> 1.4634322 | F69: =F67/F68 -> 1.4493067 | G69: =G67/G68 -> 1.4461309 | H69: =H67/H68 -> 1.3732751 | I69: =I67/I68 -> 1.3926243 | J69: =J67/J68 -> 1.4095661 | ... Q69: =Q67/Q68 -> 1.4751917
B71: Change in Revenue | C71: ='Historical Data'!H8-'Historical Data'!G8 -> 1781.99 | D71: =D67-C67 -> 1931.74 | E71: =E67-D67 -> 1708.04 | F71: =F67-E67 -> 2282.29 | G71: =G67-F67 -> 434.34 | H71: =H67-G67 -> 1612.2587 | I71: =I67-H67 -> 1806.2809 | J71: =J67-I67 -> 2021.5121 | K71: =K67-J67 -> 2259.992 | ... Q71: =Q67-P67 -> 4314.8167
B72: Change in Assets | C72: ='Historical Data'!H84-'Historical Data'!G84 -> 763.19 | D72: =D68-C68 -> 1086.42 | E72: =E68-D68 -> 1219.19 | F72: =F68-E68 -> 1639.25 | G72: =G68-F68 -> 318.48 | H72: =H68-G68 -> 1629.0024 | I72: =I68-H68 -> 1155.2454 | J72: =J68-I68 -> 1297.5981 | K72: =K68-J68 -> 1456.0204 | ... Q72: =Q68-P68 -> 2845.0363
B73: Reinvestment Ratio | C73: =C71/C72 -> 2.3349232 | D73: =D71/D72 -> 1.7780785 | E73: =E71/E72 -> 1.4009629 | F73: =F71/F72 -> 1.392277 | G73: =G71/G72 -> 1.3637905 | H73: =H71/H72 -> 0.9897215 | I73: =I71/I72 -> 1.5635475 | J73: =J71/J72 -> 1.5578877 | ... Q73: =Q71/Q72 -> 1.5166122
B75: COGS | C75: ='3 - Statement Model'!H10 -> 4714.68 | D75: ='3 - Statement Model'!I10 -> 6181.67 | E75: ='3 - Statement Model'!J10 -> 7391.97 | F75: ='3 - Statement Model'!K10 -> 9074.34 | G75: ='3 - Statement Model'!L10 -> 9542.09 | H75: ='3 - Statement Model'!M10 -> 10650.829 | I75: ='3 - Statement Model'!N10 -> 12023.603 | J75: ='3 - Statement Model'!O10 -> 13559.952 | ... Q75: ='3 - Statement Model'!V10 -> 30606.433
B76: Inventory | C76: ='3 - Statement Model'!H75 -> 1144.24 | D76: ='3 - Statement Model'!I75 -> 1433.39 | E76: ='3 - Statement Model'!J75 -> 1407.18 | F76: ='3 - Statement Model'!K75 -> 2149.15 | G76: ='3 - Statement Model'!L75 -> 2166.2 | H76: ='3 - Statement Model'!M75 -> 2188.5265 | I76: ='3 - Statement Model'!N75 -> 2470.6033 | J76: ='3 - Statement Model'!O75 -> 2786.2915 | ... Q76: ='3 - Statement Model'!V75 -> 5869.7269
B77: Inventory Turnover Ratio | C77: =C75/C76 -> 4.1203594 | D77: =D75/D76 -> 4.3126225 | E77: =E75/E76 -> 5.253038 | F77: =F75/F76 -> 4.2222925 | G77: =G75/G76 -> 4.4049903 | H77: =H75/H76 -> 4.8666667 | I77: =I75/I76 -> 4.8666667 | J77: =J75/J76 -> 4.8666667 | ... Q77: =Q75/Q76 -> 5.2142857
A79: # | B79: Coverage Ratio
B81: Total Debt | C81: =C31 -> 477.83 | D81: =D31 -> 577.64 | E81: =E31 -> 166.62 | F81: =F31 -> 199.36 | G81: =G31 -> 626.8 | H81: =H31 -> 630.64119 | I81: =I31 -> 711.92383 | J81: =J31 -> 802.89188 | ... Q81: =Q31 -> 1812.223
B82: EBITDA | C82: =C45 -> 346.47 | D82: =D45 -> 492.78 | E82: =E45 -> 664.94 | F82: =F45 -> 875.92 | G82: =G45 -> 930.4 | H82: =H45 -> 1121.1399 | I82: =I45 -> 1265.6424 | J82: =J45 -> 1427.3633 | ... Q82: =Q45 -> 3221.7298
B83: Debt to EBITDA Coverage Ratio | C83: =C81/C82 -> 1.3791382 | D83: =D81/D82 -> 1.1722067 | E83: =E81/E82 -> 0.250579 | F83: =F81/F82 -> 0.22760069 | G83: =G81/G82 -> 0.67368874 | H83: =H81/H82 -> 0.5625 | I83: =I81/I82 -> 0.5625 | J83: =J81/J82 -> 0.5625 | ... Q83: =Q81/Q82 -> 0.5625
B85: EBIT | C85: =C49 -> 260.49 | D85: =D49 -> 408 | E85: =E49 -> 567.33 | F85: =F49 -> 747.55 | G85: =G49 -> 751.61 | H85: =H49 -> 924.94041 | I85: =I49 -> 1044.155 | J85: =J49 -> 1177.5748 | ... Q85: =Q49 -> 2657.9271
B86: Interest Expense | C86: ='3 - Statement Model'!H24 -> 46.4 | D86: ='3 - Statement Model'!I24 -> 54.7 | E86: ='3 - Statement Model'!J24 -> 58.08 | F86: ='3 - Statement Model'!K24 -> 48.8 | G86: ='3 - Statement Model'!L24 -> 72.14 | H86: ='3 - Statement Model'!M24 -> 75.446471 | I86: ='3 - Statement Model'!N24 -> 80.553902 | J86: ='3 - Statement Model'!O24 -> 90.888943 | ... Q86: ='3 - Statement Model'!V24 -> 205.81676
B87: Interest Coverage Ratio | C87: =C85/C86 -> 5.6140086 | D87: =D85/D86 -> 7.4588665 | E87: =E85/E86 -> 9.7680785 | F87: =F85/F86 -> 15.318648 | G87: =G85/G86 -> 10.418769 | H87: =H85/H86 -> 12.259558 | I87: =I85/I86 -> 12.96219 | J87: =J85/J86 -> 12.956194 | ... Q87: =Q85/Q86 -> 12.914046

Sheet 3 - Statement Model
B2: Three Statement Model - Bluestar Ltd
B3: All figures in INR Crores.
B5: Fiscal Year Ending | C5: 2017 | D5: =C5+1 -> 2018 | E5: =D5+1 -> 2019 | F5: =E5+1 -> 2020 | G5: =F5+1 -> 2021 | H5: =G5+1 -> 2022 | I5: =H5+1 -> 2023 | J5: =I5+1 -> 2024 | K5: =J5+1 -> 2025 | ... V5: =U5+1 -> 2036
B7: INCOME STATEMENT
B8: Revenue From Operations | C8: ='Historical Data'!C8 -> 4385.24 | D8: ='Historical Data'!D8 -> 4638.95 | E8: ='Historical Data'!E8 -> 5234.84 | F8: ='Historical Data'!F8 -> 5360.19 | G8: ='Historical Data'!G8 -> 4263.59 | H8: ='Historical Data'!H8 -> 6045.58 | I8: ='Historical Data'!I8 -> 7977.32 | J8: ='Historical Data'!J8 -> 9685.36 | ... L8: ='Historical Data'!L8 -> 12401.99 | M8: =Schedule!E13 -> 14014.249 | N8: =Schedule!F13 -> 15820.53 | O8: =Schedule!G13 -> 17842.042 | P8: =Schedule!H13 -> 20102.034 | Q8: =Schedule!I13 -> 22625.956 | R8: =Schedule!J13 -> 25441.63 | S8: =Schedule!K13 -> 28579.431 | T8: =Schedule!L13 -> 32072.473 | ... V8: =Schedule!N13 -> 40271.622
B9: Revenue Growth % | D9: =D8/C8-1 -> 0.057855442 | E9: =E8/D8-1 -> 0.12845364 | F9: =F8/E8-1 -> 0.023945335 | G9: =G8/F8-1 -> -0.2045823 | H9: =H8/G8-1 -> 0.41795529 | I9: =I8/H8-1 -> 0.31952931 | J9: =J8/I8-1 -> 0.21411201 | K9: =K8/J8-1 -> 0.23564328 | ... V9: =V8/U8-1 -> 0.12
B10: Less: Cost of Goods Sold/ Services | C10: ='Historical Data'!C10 -> 3112.25 | D10: ='Historical Data'!D10 -> 3454.95 | E10: ='Historical Data'!E10 -> 3931.18 | F10: ='Historical Data'!F10 -> 4018.11 | G10: ='Historical Data'!G10 -> 3271.35 | H10: ='Historical Data'!H10 -> 4714.68 | I10: ='Historical Data'!I10 -> 6181.67 | J10: ='Historical Data'!J10 -> 7391.97 | ... L10: ='Historical Data'!L10 -> 9542.09 | M10: =Schedule!E21 -> 10650.829 | N10: =Schedule!F21 -> 12023.603 | O10: =Schedule!G21 -> 13559.952 | P10: =Schedule!H21 -> 15277.546 | Q10: =Schedule!I21 -> 17195.726 | R10: =Schedule!J21 -> 19335.639 | S10: =Schedule!K21 -> 21720.368 | T10: =Schedule!L21 -> 24375.079 | ... V10: =Schedule!N21 -> 30606.433
B11: Gross Profit | C11: =C8-C10 -> 1272.99 | D11: =D8-D10 -> 1184 | E11: =E8-E10 -> 1303.66 | F11: =F8-F10 -> 1342.08 | G11: =G8-G10 -> 992.24 | H11: =H8-H10 -> 1330.9 | I11: =I8-I10 -> 1795.65 | J11: =J8-J10 -> 2293.39 | ... V11: =V8-V10 -> 9665.1894
B12: Gross Margin (%) | C12: =C11/C8 -> 0.2902897 | D12: =D11/D8 -> 0.25523017 | E12: =E11/E8 -> 0.24903531 | F12: =F11/F8 -> 0.25037918 | G12: =G11/G8 -> 0.23272407 | H12: =H11/H8 -> 0.2201443 | I12: =I11/I8 -> 0.22509439 | J12: =J11/J8 -> 0.23678934 | ... V12: =V11/V8 -> 0.24
B14: Less: SG&A Expenses | C14: ='Historical Data'!C14 -> 1050.58 | D14: ='Historical Data'!D14 -> 918.1 | E14: ='Historical Data'!E14 -> 957.12 | F14: ='Historical Data'!F14 -> 1059.3 | G14: ='Historical Data'!G14 -> 752.43 | H14: ='Historical Data'!H14 -> 984.43 | I14: ='Historical Data'!I14 -> 1302.87 | J14: ='Historical Data'!J14 -> 1628.45 | ... L14: ='Historical Data'!L14 -> 1929.5 | M14: =Schedule!E29 -> 2242.2798 | N14: =Schedule!F29 -> 2531.2847 | O14: =Schedule!G29 -> 2854.7267 | P14: =Schedule!H29 -> 3216.3254 | Q14: =Schedule!I29 -> 3620.1529 | R14: =Schedule!J29 -> 4070.6608 | S14: =Schedule!K29 -> 4572.709 | T14: =Schedule!L29 -> 5131.5957 | ... V14: =Schedule!N29 -> 6443.4596
B15: SG&A % Revenue | C15: =C14/C8 -> 0.23957184 | D15: =D14/D8 -> 0.19791117 | E15: =E14/E8 -> 0.18283653 | F15: =F14/F8 -> 0.19762359 | G15: =G14/G8 -> 0.17647804 | H15: =H14/H8 -> 0.16283467 | I15: =I14/I8 -> 0.16332177 | J15: =J14/J8 -> 0.16813521 | ... P15: =P14/P8 -> 0.16 | Q15: =Schedule!I31 -> 0.16 | R15: =Schedule!J31 -> 0.16 | S15: =Schedule!K31 -> 0.16 | T15: =Schedule!L31 -> 0.16 | U15: =Schedule!M31 -> 0.16 | V15: =Schedule!N31 -> 0.16
B16: Earning before Interest Taxes Depreciation & Amortization (EBITDA) | C16: =C11-C14 -> 222.41 | D16: =D11-D14 -> 265.9 | E16: =E11-E14 -> 346.54 | F16: =F11-F14 -> 282.78 | G16: =G11-G14 -> 239.81 | H16: =H11-H14 -> 346.47 | I16: =I11-I14 -> 492.78 | J16: =J11-J14 -> 664.94 | ... V16: =V11-V14 -> 3221.7298
B17: EBITDA Margin (%) | C17: =C16/C8 -> 0.050717863 | D17: =D16/D8 -> 0.057319005 | E17: =E16/E8 -> 0.066198776 | F17: =F16/F8 -> 0.052755593 | G17: =G16/G8 -> 0.056246027 | H17: =H16/H8 -> 0.057309638 | I17: =I16/I8 -> 0.061772625 | J17: =J16/J8 -> 0.068654134 | ... V17: =V16/V8 -> 0.08
B19: Less: Depreciation and Amortization | C19: ='Historical Data'!C19 -> 60.58 | D19: ='Historical Data'!D19 -> 63.81 | E19: ='Historical Data'!E19 -> 74.9 | F19: ='Historical Data'!F19 -> 87.99 | G19: ='Historical Data'!G19 -> 92.29 | H19: ='Historical Data'!H19 -> 85.98 | I19: ='Historical Data'!I19 -> 84.78 | J19: ='Historical Data'!J19 -> 97.61 | ... L19: ='Historical Data'!L19 -> 178.79 | M19: =Schedule!E128 -> 196.19948 | N19: =Schedule!F128 -> 221.48742 | O19: =Schedule!G128 -> 249.78858 | P19: =Schedule!H128 -> 281.42847 | Q19: =Schedule!I128 -> 316.76338 | R19: =Schedule!J128 -> 356.18282 | S19: =Schedule!K128 -> 400.11204 | T19: =Schedule!L128 -> 449.01462 | ... V19: =Schedule!N128 -> 563.80271
B20: Earning before Interest & Taxes (EBIT) | C20: =C16-C19 -> 161.83 | D20: =D16-D19 -> 202.09 | E20: =E16-E19 -> 271.64 | F20: =F16-F19 -> 194.79 | G20: =G16-G19 -> 147.52 | H20: =H16-H19 -> 260.49 | I20: =I16-I19 -> 408 | J20: =J16-J19 -> 567.33 | ... V20: =V16-V19 -> 2657.9271
B21: EBIT Margin (%) | C21: =C20/C8 -> 0.036903339 | D21: =D20/D8 -> 0.043563737 | E21: =E20/E8 -> 0.051890793 | F21: =F20/F8 -> 0.03634013 | G21: =G20/G8 -> 0.03459995 | H21: =H20/H8 -> 0.043087677 | I21: =I20/I8 -> 0.051144996 | J21: =J20/J8 -> 0.058576036 | ... V21: =V20/V8 -> 0.066
B23: Other Income | C23: ='Historical Data'!C23 -> 13.07 | D23: ='Historical Data'!D23 -> 16.95 | E23: ='Historical Data'!E23 -> 24.69 | F23: ='Historical Data'!F23 -> 44.7 | G23: ='Historical Data'!G23 -> 62.35 | H23: ='Historical Data'!H23 -> 35.72 | I23: ='Historical Data'!I23 -> 30.87 | J23: ='Historical Data'!J23 -> 47.42 | ... L23: ='Historical Data'!L23 -> 61.91 | M23: =Schedule!E205 -> 70.071243 | N23: =Schedule!F205 -> 79.102648 | O23: =Schedule!G205 -> 89.210209 | P23: =Schedule!H205 -> 100.51017 | Q23: =Schedule!I205 -> 113.12978 | R23: =Schedule!J205 -> 127.20815 | S23: =Schedule!K205 -> 142.89716 | T23: =Schedule!L205 -> 160.36236 | ... V23: =Schedule!N205 -> 201.35811
B24: Less: Interest Expenses | C24: ='Historical Data'!C24 -> 16.27 | D24: ='Historical Data'!D24 -> 28.74 | E24: ='Historical Data'!E24 -> 47.87 | F24: ='Historical Data'!F24 -> 29.47 | G24: ='Historical Data'!G24 -> 64.72 | H24: ='Historical Data'!H24 -> 46.4 | I24: ='Historical Data'!I24 -> 54.7 | J24: ='Historical Data'!J24 -> 58.08 | ... L24: ='Historical Data'!L24 -> 72.14 | M24: =Schedule!E200 -> 75.446471 | N24: =Schedule!F200 -> 80.553902 | O24: =Schedule!G200 -> 90.888943 | P24: =Schedule!H200 -> 102.449 | Q24: =Schedule!I200 -> 115.36557 | R24: =Schedule!J200 -> 129.78248 | S24: =Schedule!K200 -> 145.85687 | T24: =Schedule!L200 -> 163.76014 | ... V24: =Schedule!N200 -> 205.81676
B25: Less: Other Expense | C25: ='Historical Data'!C25 -> 0 | D25: ='Historical Data'!D25 -> -5.27 | E25: ='Historical Data'!E25 -> -2.68 | F25: ='Historical Data'!F25 -> 4.03 | G25: ='Historical Data'!G25 -> 0 | H25: ='Historical Data'!H25 -> 0 | I25: ='Historical Data'!I25 -> -170.81 | J25: ='Historical Data'!J25 -> 0 | ... L25: ='Historical Data'!L25 -> 38.83 | M25: =Schedule!E210 -> 0 | N25: =Schedule!F210 -> 0 | O25: =Schedule!G210 -> 0 | P25: =Schedule!H210 -> 0 | Q25: =Schedule!I210 -> 0 | R25: =Schedule!J210 -> 0 | S25: =Schedule!K210 -> 0 | T25: =Schedule!L210 -> 0 | ... V25: =Schedule!N210 -> 0
B26: Profit Before Tax (PBT) | C26: =C20+C23-C24-C25 -> 158.63 | D26: =D20+D23-D24-D25 -> 195.57 | E26: =E20+E23-E24-E25 -> 251.14 | F26: =F20+F23-F24-F25 -> 205.99 | G26: =G20+G23-G24-G25 -> 145.15 | H26: =H20+H23-H24-H25 -> 249.81 | I26: =I20+I23-I24-I25 -> 554.98 | J26: =J20+J23-J24-J25 -> 556.67 | ... V26: =V20+V23-V24-V25 -> 2653.4684
B27: EBT Margin (%) | C27: =C26/C8 -> 0.036173619 | D27: =D26/D8 -> 0.042158247 | E27: =E26/E8 -> 0.047974723 | F27: =F26/F8 -> 0.038429608 | G27: =G26/G8 -> 0.03404408 | H27: =H26/H8 -> 0.041321097 | I27: =I26/I8 -> 0.06956973 | J27: =J26/J8 -> 0.057475406 | ... V27: =V26/V8 -> 0.065889286
B29: Less: Tax Expense | C29: ='Historical Data'!C29 -> 36.67 | D29: ='Historical Data'!D29 -> 49.42 | E29: ='Historical Data'!E29 -> 41.99 | F29: ='Historical Data'!F29 -> 65.32 | G29: ='Historical Data'!G29 -> 47.09 | H29: ='Historical Data'!H29 -> 82.9 | I29: ='Historical Data'!I29 -> 154.69 | J29: ='Historical Data'!J29 -> 142.85 | ... L29: ='Historical Data'!L29 -> 175.78 | M29: =Schedule!E221 -> 229.8913 | N29: =Schedule!F221 -> 260.67593 | O29: =Schedule!G221 -> 293.97401 | P29: =Schedule!H221 -> 331.19885 | Q29: =Schedule!I221 -> 372.76932 | R29: =Schedule!J221 -> 419.14332 | S29: =Schedule!K221 -> 470.82069 | T29: =Schedule!L221 -> 528.34636 | ... V29: =Schedule!N221 -> 663.36711
B30: Net Income | C30: =C26-C29 -> 121.96 | D30: =D26-D29 -> 146.15 | E30: =E26-E29 -> 209.15 | F30: =F26-F29 -> 140.67 | G30: =G26-G29 -> 98.06 | H30: =H26-H29 -> 166.91 | I30: =I26-I29 -> 400.29 | J30: =J26-J29 -> 413.82 | ... V30: =V26-V29 -> 1990.1013
B31: Net Income Margin (%) | C31: =C30/C8 -> 0.027811477 | D31: =D30/D8 -> 0.031504974 | E31: =E30/E8 -> 0.039953466 | F31: =F30/F8 -> 0.026243473 | G31: =G30/G8 -> 0.022999397 | H31: =H30/H8 -> 0.0276086 | I31: =I30/I8 -> 0.050178506 | J31: =J30/J8 -> 0.042726342 | ... V31: =V30/V8 -> 0.049416964
B32: Add:Profit from Discontinued Operations | C32: ='Historical Data'!C32 -> 0 | D32: ='Historical Data'!D32 -> 0 | E32: ='Historical Data'!E32 -> 0 | F32: ='Historical Data'!F32 -> 0 | G32: ='Historical Data'!G32 -> 0 | H32: ='Historical Data'!H32 -> 0 | I32: ='Historical Data'!I32 -> 0 | J32: ='Historical Data'!J32 -> 0 | ... L32: ='Historical Data'!L32 -> 0 | M32: =Schedule!E232 -> 0 | N32: =Schedule!F232 -> 0 | O32: =Schedule!G232 -> 0 | P32: =Schedule!H232 -> 0 | Q32: =Schedule!I232 -> 0 | R32: =Schedule!J232 -> 0 | S32: =Schedule!K232 -> 0 | T32: =Schedule!L232 -> 0 | ... V32: =Schedule!N232 -> 0
B33: Less: Loss from Discontinued Operations | C33: ='Historical Data'!C33 -> 0 | D33: ='Historical Data'!D33 -> 0 | E33: ='Historical Data'!E33 -> 0 | F33: ='Historical Data'!F33 -> 0 | G33: ='Historical Data'!G33 -> 0 | H33: ='Historical Data'!H33 -> 0 | I33: ='Historical Data'!I33 -> 0 | J33: ='Historical Data'!J33 -> 0 | ... L33: ='Historical Data'!L33 -> 0 | M33: =Schedule!E233 -> 0 | N33: =Schedule!F233 -> 0 | O33: =Schedule!G233 -> 0 | P33: =Schedule!H233 -> 0 | Q33: =Schedule!I233 -> 0 | R33: =Schedule!J233 -> 0 | S33: =Schedule!K233 -> 0 | T33: =Schedule!L233 -> 0 | ... V33: =Schedule!N233 -> 0
B34: Net Income of the Year | C34: =C30+C32-C33 -> 121.96 | D34: =D30+D32-D33 -> 146.15 | E34: =E30+E32-E33 -> 209.15 | F34: =F30+F32-F33 -> 140.67 | G34: =G30+G32-G33 -> 98.06 | H34: =H30+H32-H33 -> 166.91 | I34: =I30+I32-I33 -> 400.29 | J34: =J30+J32-J33 -> 413.82 | ... V34: =V30+V32-V33 -> 1990.1013
B37: BALANCE SHEET
B38: Equity and Liablities
B39: Shareholder's Funds
B40: Equity Share Capital | C40: ='Historical Data'!C42 -> 19.11 | D40: ='Historical Data'!D42 -> 19.2 | E40: ='Historical Data'!E42 -> 19.26 | F40: ='Historical Data'!F42 -> 19.26 | G40: ='Historical Data'!G42 -> 19.26 | H40: ='Historical Data'!H42 -> 19.26 | I40: ='Historical Data'!I42 -> 19.26 | J40: ='Historical Data'!J42 -> 41.12 | ... L40: ='Historical Data'!L42 -> 41.12 | M40: =Schedule!E237 -> 41.12 | N40: =Schedule!F237 -> 41.12 | O40: =Schedule!G237 -> 41.12 | P40: =Schedule!H237 -> 41.12 | Q40: =Schedule!I237 -> 41.12 | R40: =Schedule!J237 -> 41.12 | S40: =Schedule!K237 -> 41.12 | T40: =Schedule!L237 -> 41.12 | ... V40: =Schedule!N237 -> 41.12
B41: Reserves & Surplus | C41: ='Historical Data'!C43 -> 738.02 | D41: ='Historical Data'!D43 -> 773.53 | E41: ='Historical Data'!E43 -> 853.8 | F41: ='Historical Data'!F43 -> 763.11 | G41: ='Historical Data'!G43 -> 865.92 | H41: ='Historical Data'!H43 -> 998.32 | I41: ='Historical Data'!I43 -> 1311.39 | J41: ='Historical Data'!J43 -> 2568.95 | ... L41: ='Historical Data'!L43 -> 3390.29 | M41: =Schedule!E135 -> 3873.0617 | N41: =Schedule!F135 -> 4420.4812 | O41: =Schedule!G135 -> 5037.8266 | P41: =Schedule!H135 -> 5733.3442 | Q41: =Schedule!I135 -> 6516.1597 | R41: =Schedule!J135 -> 7396.3607 | S41: =Schedule!K135 -> 8385.0841 | T41: =Schedule!L135 -> 9494.6115 | ... V41: =Schedule!N135 -> 12131.541
B42: Total Shareholder's Funds | C42: =C40+C41 -> 757.13 | D42: =D40+D41 -> 792.73 | E42: =E40+E41 -> 873.06 | F42: =F40+F41 -> 782.37 | G42: =G40+G41 -> 885.18 | H42: =H40+H41 -> 1017.58 | I42: =I40+I41 -> 1330.65 | J42: =J40+J41 -> 2610.07 | ... V42: =V40+V41 -> 12172.661
B43: Minority Interest | C43: ='Historical Data'!C45 -> 1.22 | D43: ='Historical Data'!D45 -> 1.52 | E43: ='Historical Data'!E45 -> 1.83 | F43: ='Historical Data'!F45 -> 2.31 | G43: ='Historical Data'!G45 -> 2.68 | H43: ='Historical Data'!H45 -> 2.96 | I43: ='Historical Data'!I45 -> 3.19 | J43: ='Historical Data'!J45 -> 2.55 | ... L43: ='Historical Data'!L45 -> 2.45 | M43: =Schedule!E241 -> 2.45 | N43: =Schedule!F241 -> 2.45 | O43: =Schedule!G241 -> 2.45 | P43: =Schedule!H241 -> 2.45 | Q43: =Schedule!I241 -> 2.45 | R43: =Schedule!J241 -> 2.45 | S43: =Schedule!K241 -> 2.45 | T43: =Schedule!L241 -> 2.45 | ... V43: =Schedule!N241 -> 2.45
B45: Non Current Liablities
B46: Long Term Borrowings | C46: ='Historical Data'!C48 -> 20.2 | D46: ='Historical Data'!D48 -> 25.9 | E46: ='Historical Data'!E48 -> 8.65 | F46: ='Historical Data'!F48 -> 47.71 | G46: ='Historical Data'!G48 -> 349.26 | H46: ='Historical Data'!H48 -> 241.57 | I46: ='Historical Data'!I48 -> 161.74 | J46: ='Historical Data'!J48 -> 0 | ... L46: ='Historical Data'!L48 -> 0 | M46: =Schedule!E181 -> 0 | N46: =Schedule!F181 -> 0 | O46: =Schedule!G181 -> 0 | P46: =Schedule!H181 -> 0 | Q46: =Schedule!I181 -> 0 | R46: =Schedule!J181 -> 0 | S46: =Schedule!K181 -> 0 | T46: =Schedule!L181 -> 0 | ... V46: =Schedule!N181 -> 0
B47: Deferred Tax Liabilities | C47: ='Historical Data'!C49 -> 0 | D47: ='Historical Data'!D49 -> 0 | E47: ='Historical Data'!E49 -> 0 | F47: ='Historical Data'!F49 -> 0 | G47: ='Historical Data'!G49 -> 0 | H47: ='Historical Data'!H49 -> 0 | I47: ='Historical Data'!I49 -> 0 | J47: ='Historical Data'!J49 -> 6.98 | ... L47: ='Historical Data'!L49 -> 31.6 | M47: =Schedule!E84 -> 31.6 | N47: =Schedule!F84 -> 31.6 | O47: =Schedule!G84 -> 31.6 | P47: =Schedule!H84 -> 31.6 | Q47: =Schedule!I84 -> 31.6 | R47: =Schedule!J84 -> 31.6 | S47: =Schedule!K84 -> 31.6 | T47: =Schedule!L84 -> 31.6 | ... V47: =Schedule!N84 -> 31.6
B48: Other Long Term Liabilities | C48: ='Historical Data'!C50 -> 4.08 | D48: ='Historical Data'!D50 -> 6.27 | E48: ='Historical Data'!E50 -> 6.45 | F48: ='Historical Data'!F50 -> 47.92 | G48: ='Historical Data'!G50 -> 40.06 | H48: ='Historical Data'!H50 -> 71.27 | I48: ='Historical Data'!I50 -> 108.32 | J48: ='Historical Data'!J50 -> 103.1 | ... L48: ='Historical Data'!L50 -> 191.49 | M48: =Schedule!E88 -> 191.49 | N48: =Schedule!F88 -> 191.49 | O48: =Schedule!G88 -> 191.49 | P48: =Schedule!H88 -> 191.49 | Q48: =Schedule!I88 -> 191.49 | R48: =Schedule!J88 -> 191.49 | S48: =Schedule!K88 -> 191.49 | T48: =Schedule!L88 -> 191.49 | ... V48: =Schedule!N88 -> 191.49
B49: Long Term Provisions | C49: ='Historical Data'!C51 -> 11.17 | D49: ='Historical Data'!D51 -> 12.54 | E49: ='Historical Data'!E51 -> 12.06 | F49: ='Historical Data'!F51 -> 13.26 | G49: ='Historical Data'!G51 -> 10.82 | H49: ='Historical Data'!H51 -> 10.06 | I49: ='Historical Data'!I51 -> 11.41 | J49: ='Historical Data'!J51 -> 15.93 | ... L49: ='Historical Data'!L51 -> 52.77 | M49: =Schedule!E92 -> 52.77 | N49: =Schedule!F92 -> 52.77 | O49: =Schedule!G92 -> 52.77 | P49: =Schedule!H92 -> 52.77 | Q49: =Schedule!I92 -> 52.77 | R49: =Schedule!J92 -> 52.77 | S49: =Schedule!K92 -> 52.77 | T49: =Schedule!L92 -> 52.77 | ... V49: =Schedule!N92 -> 52.77
B50: Total Non-Current Liabilities | C50: =SUM(C46:C49) -> 35.45 | D50: =SUM(D46:D49) -> 44.71 | E50: =SUM(E46:E49) -> 27.16 | F50: =SUM(F46:F49) -> 108.89 | G50: =SUM(G46:G49) -> 400.14 | H50: =SUM(H46:H49) -> 322.9 | I50: =SUM(I46:I49) -> 281.47 | J50: =SUM(J46:J49) -> 126.01 | ... V50: =SUM(V46:V49) -> 275.86
B52: Current Liablities
B53: Short Term Borrowings | C53: ='Historical Data'!C55 -> 195.92 | D53: ='Historical Data'!D55 -> 344.02 | E53: ='Historical Data'!E55 -> 335.89 | F53: ='Historical Data'!F55 -> 401.23 | G53: ='Historical Data'!G55 -> 102.34 | H53: ='Historical Data'!H55 -> 236.26 | I53: ='Historical Data'!I55 -> 415.9 | J53: ='Historical Data'!J55 -> 166.62 | ... L53: ='Historical Data'!L55 -> 626.8 | M53: =Schedule!E188 -> 630.64119 | N53: =Schedule!F188 -> 711.92383 | O53: =Schedule!G188 -> 802.89188 | P53: =Schedule!H188 -> 904.59152 | Q53: =Schedule!I188 -> 1018.168 | R53: =Schedule!J188 -> 1144.8734 | S53: =Schedule!K188 -> 1286.0744 | T53: =Schedule!L188 -> 1443.2613 | ... V53: =Schedule!N188 -> 1812.223
B54: Trade Payables | C54: ='Historical Data'!C56 -> 1177.23 | D54: ='Historical Data'!D56 -> 1532.69 | E54: ='Historical Data'!E56 -> 1534.62 | F54: ='Historical Data'!F56 -> 1582.36 | G54: ='Historical Data'!G56 -> 1604.89 | H54: ='Historical Data'!H56 -> 2041.67 | I54: ='Historical Data'!I56 -> 2511.16 | J54: ='Historical Data'!J56 -> 2616.6 | ... L54: ='Historical Data'!L56 -> 2942.86 | M54: =Schedule!E167 -> 4085.2495 | N54: =Schedule!F167 -> 4611.7928 | O54: =Schedule!G167 -> 5201.0774 | P54: =Schedule!H167 -> 5859.8805 | Q54: =Schedule!I167 -> 6595.6211 | R54: =Schedule!J167 -> 7416.4095 | S54: =Schedule!K167 -> 8331.1 | T54: =Schedule!L167 -> 9349.3455 | ... V54: =Schedule!N167 -> 11739.454
B55: Other Current Liabilities | C55: ='Historical Data'!C57 -> 443.38 | D55: ='Historical Data'!D57 -> 461.55 | E55: ='Historical Data'!E57 -> 491.4 | F55: ='Historical Data'!F57 -> 497.12 | G55: ='Historical Data'!G57 -> 505.85 | H55: ='Historical Data'!H57 -> 630.45 | I55: ='Historical Data'!I57 -> 791.69 | J55: ='Historical Data'!J57 -> 1019.54 | ... L55: ='Historical Data'!L57 -> 1160.11 | M55: =Schedule!E99 -> 1160.11 | N55: =Schedule!F99 -> 1160.11 | O55: =Schedule!G99 -> 1160.11 | P55: =Schedule!H99 -> 1160.11 | Q55: =Schedule!I99 -> 1160.11 | R55: =Schedule!J99 -> 1160.11 | S55: =Schedule!K99 -> 1160.11 | T55: =Schedule!L99 -> 1160.11 | ... V55: =Schedule!N99 -> 1160.11
B56: Short Term Provisions | C56: ='Historical Data'!C58 -> 39.85 | D56: ='Historical Data'!D58 -> 59 | E56: ='Historical Data'!E58 -> 87 | F56: ='Historical Data'!F58 -> 64.98 | G56: ='Historical Data'!G58 -> 48.37 | H56: ='Historical Data'!H58 -> 60.82 | I56: ='Historical Data'!I58 -> 65 | J56: ='Historical Data'!J58 -> 76.86 | ... L56: ='Historical Data'!L58 -> 136.49 | M56: =Schedule!E103 -> 136.49 | N56: =Schedule!F103 -> 136.49 | O56: =Schedule!G103 -> 136.49 | P56: =Schedule!H103 -> 136.49 | Q56: =Schedule!I103 -> 136.49 | R56: =Schedule!J103 -> 136.49 | S56: =Schedule!K103 -> 136.49 | T56: =Schedule!L103 -> 136.49 | ... V56: =Schedule!N103 -> 136.49
B57: Total Current Liabilities | C57: =SUM(C53:C56) -> 1856.38 | D57: =SUM(D53:D56) -> 2397.26 | E57: =SUM(E53:E56) -> 2448.91 | F57: =SUM(F53:F56) -> 2545.69 | G57: =SUM(G53:G56) -> 2261.45 | H57: =SUM(H53:H56) -> 2969.2 | I57: =SUM(I53:I56) -> 3783.75 | J57: =SUM(J53:J56) -> 3879.62 | ... V57: =SUM(V53:V56) -> 14848.277
B59: Total Equity and Liablities | C59: =SUM(C42,C43,C50,C57) -> 2650.18 | D59: =SUM(D42,D43,D50,D57) -> 3236.22 | E59: =SUM(E42,E43,E50,E57) -> 3350.96 | F59: =SUM(F42,F43,F50,F57) -> 3439.26 | G59: =SUM(G42,G43,G50,G57) -> 3549.45 | H59: =SUM(H42,H43,H50,H57) -> 4312.64 | I59: =SUM(I42,I43,I50,I57) -> 5399.06 | J59: =SUM(J42,J43,J50,J57) -> 6618.25 | ... M59: =SUM(M42,M43,M50,M57) -> 10204.982 | N59: =SUM(N42,L86,N43,N50,N57) -> 11360.228 | O59: =SUM(O42,O43,O50,O57) -> 12657.826 | P59: =SUM(P42,P43,P50,P57) -> 14113.846 | Q59: =SUM(Q42,Q43,Q50,Q57) -> 15745.979 | R59: =SUM(R42,R43,R50,R57) -> 17573.674 | S59: =SUM(S42,S43,S50,S57) -> 19618.289 | T59: =SUM(T42,T43,T50,T57) -> 21903.248 | U59: =SUM(U42,U43,U50,U57) -> 24454.211 | V59: =SUM(V42,V43,V50,V57) -> 27299.248
B61: Assets
B62: Non Current Assets
B63: Tangible Assets | C63: ='Historical Data'!C65 -> 312.38 | D63: ='Historical Data'!D65 -> 335.87 | E63: ='Historical Data'!E65 -> 349.88 | F63: ='Historical Data'!F65 -> 392.4 | G63: ='Historical Data'!G65 -> 331.25 | H63: ='Historical Data'!H65 -> 391.13 | I63: ='Historical Data'!I65 -> 799.93 | J63: ='Historical Data'!J65 -> 1071.32 | ... L63: ='Historical Data'!L65 -> 1439.17 | M63: =Schedule!E43 -> 1579.3125 | N63: =Schedule!F43 -> 1737.5178 | O63: =Schedule!G43 -> 1915.9382 | P63: =Schedule!H43 -> 2157.1626 | Q63: =Schedule!I43 -> 2428.6741 | R63: =Schedule!J43 -> 2733.9736 | S63: =Schedule!K43 -> 2991.1885 | T63: =Schedule!L43 -> 3279.8408 | ... V63: =Schedule!N43 -> 3656.6681
B64: Intangible Assets | C64: ='Historical Data'!C66 -> 43.73 | D64: ='Historical Data'!D66 -> 56.13 | E64: ='Historical Data'!E66 -> 50.32 | F64: ='Historical Data'!F66 -> 51.39 | G64: ='Historical Data'!G66 -> 52.31 | H64: ='Historical Data'!H66 -> 41.67 | I64: ='Historical Data'!I66 -> 58.96 | J64: ='Historical Data'!J66 -> 93.22 | ... L64: ='Historical Data'!L66 -> 155.56 | M64: =Schedule!E56 -> 140.14249 | N64: =Schedule!F56 -> 158.2053 | O64: =Schedule!G56 -> 178.42042 | P64: =Schedule!H56 -> 201.02034 | Q64: =Schedule!I56 -> 226.25956 | R64: =Schedule!J56 -> 254.4163 | S64: =Schedule!K56 -> 285.79431 | T64: =Schedule!L56 -> 320.72473 | ... V64: =Schedule!N56 -> 402.71622
B65: Capital Work-In-Progress | C65: ='Historical Data'!C67 -> 21.51 | D65: ='Historical Data'!D67 -> 18.38 | E65: ='Historical Data'!E67 -> 30.77 | F65: ='Historical Data'!F67 -> 56.35 | G65: ='Historical Data'!G67 -> 68.11 | H65: ='Historical Data'!H67 -> 145.09 | I65: ='Historical Data'!I67 -> 60.93 | J65: ='Historical Data'!J67 -> 108.06 | ... L65: ='Historical Data'!L67 -> 65.47 | M65: =Schedule!E59 -> 65.47 | N65: =Schedule!F59 -> 65.47 | O65: =Schedule!G59 -> 65.47 | P65: =Schedule!H59 -> 65.47 | Q65: =Schedule!I59 -> 65.47 | R65: =Schedule!J59 -> 65.47 | S65: =Schedule!K59 -> 65.47 | T65: =Schedule!L59 -> 65.47 | ... V65: =Schedule!N59 -> 65.47
B66: Intangible Assets Under Development | C66: ='Historical Data'!C68 -> 12.09 | D66: ='Historical Data'!D68 -> 6.97 | E66: ='Historical Data'!E68 -> 10.45 | F66: ='Historical Data'!F68 -> 11.01 | G66: ='Historical Data'!G68 -> 3.42 | H66: ='Historical Data'!H68 -> 7.2 | I66: ='Historical Data'!I68 -> 22.39 | J66: ='Historical Data'!J68 -> 19 | ... L66: ='Historical Data'!L68 -> 0 | M66: =Schedule!E63 -> 0 | N66: =Schedule!F63 -> 0 | O66: =Schedule!G63 -> 0 | P66: =Schedule!H63 -> 0 | Q66: =Schedule!I63 -> 0 | R66: =Schedule!J63 -> 0 | S66: =Schedule!K63 -> 0 | T66: =Schedule!L63 -> 0 | ... V66: =Schedule!N63 -> 0
B67: Non-Current Investments | C67: ='Historical Data'!C69 -> 10.97 | D67: ='Historical Data'!D69 -> 13.24 | E67: ='Historical Data'!E69 -> 14.63 | F67: ='Historical Data'!F69 -> 16.87 | G67: ='Historical Data'!G69 -> 15.91 | H67: ='Historical Data'!H69 -> 17.31 | I67: ='Historical Data'!I69 -> 18.22 | J67: ='Historical Data'!J69 -> 17.88 | ... L67: ='Historical Data'!L69 -> 21.94 | M67: =Schedule!E67 -> 21.94 | N67: =Schedule!F67 -> 21.94 | O67: =Schedule!G67 -> 21.94 | P67: =Schedule!H67 -> 21.94 | Q67: =Schedule!I67 -> 21.94 | R67: =Schedule!J67 -> 21.94 | S67: =Schedule!K67 -> 21.94 | T67: =Schedule!L67 -> 21.94 | ... V67: =Schedule!N67 -> 21.94
B68: Deferred Tax Assets [Net] | C68: ='Historical Data'!C70 -> 107.66 | D68: ='Historical Data'!D70 -> 113.57 | E68: ='Historical Data'!E70 -> 107.55 | F68: ='Historical Data'!F70 -> 81.75 | G68: ='Historical Data'!G70 -> 47.49 | H68: ='Historical Data'!H70 -> 27.57 | I68: ='Historical Data'!I70 -> 7.94 | J68: ='Historical Data'!J70 -> 7.28 | ... L68: ='Historical Data'!L70 -> 9.26 | M68: =Schedule!E71 -> 9.26 | N68: =Schedule!F71 -> 9.26 | O68: =Schedule!G71 -> 9.26 | P68: =Schedule!H71 -> 9.26 | Q68: =Schedule!I71 -> 9.26 | R68: =Schedule!J71 -> 9.26 | S68: =Schedule!K71 -> 9.26 | T68: =Schedule!L71 -> 9.26 | ... V68: =Schedule!N71 -> 9.26
B69: Long Term Loans And Advances | C69: ='Historical Data'!C71 -> 17.31 | D69: ='Historical Data'!D71 -> 18.17 | E69: ='Historical Data'!E71 -> 19.82 | F69: ='Historical Data'!F71 -> 19.28 | G69: ='Historical Data'!G71 -> 22.42 | H69: ='Historical Data'!H71 -> 3.34 | I69: ='Historical Data'!I71 -> 4.69 | J69: ='Historical Data'!J71 -> 5.86 | ... L69: ='Historical Data'!L71 -> 23.31 | M69: =Schedule!E75 -> 23.31 | N69: =Schedule!F75 -> 23.31 | O69: =Schedule!G75 -> 23.31 | P69: =Schedule!H75 -> 23.31 | Q69: =Schedule!I75 -> 23.31 | R69: =Schedule!J75 -> 23.31 | S69: =Schedule!K75 -> 23.31 | T69: =Schedule!L75 -> 23.31 | ... V69: =Schedule!N75 -> 23.31
B70: Other Non-Current Assets | C70: ='Historical Data'!C72 -> 103.08 | D70: ='Historical Data'!D72 -> 95.38 | E70: ='Historical Data'!E72 -> 106.96 | F70: ='Historical Data'!F72 -> 159 | G70: ='Historical Data'!G72 -> 148.98 | H70: ='Historical Data'!H72 -> 195.9 | I70: ='Historical Data'!I72 -> 175.39 | J70: ='Historical Data'!J72 -> 255.6 | ... L70: ='Historical Data'!L72 -> 473 | M70: =Schedule!E79 -> 473 | N70: =Schedule!F79 -> 473 | O70: =Schedule!G79 -> 473 | P70: =Schedule!H79 -> 473 | Q70: =Schedule!I79 -> 473 | R70: =Schedule!J79 -> 473 | S70: =Schedule!K79 -> 473 | T70: =Schedule!L79 -> 473 | ... V70: =Schedule!N79 -> 473
B71: Total Non-Current Assets | C71: =SUM(C63:C70) -> 628.73 | D71: =SUM(D63:D70) -> 657.71 | E71: =SUM(E63:E70) -> 690.38 | F71: =SUM(F63:F70) -> 788.05 | G71: =SUM(G63:G70) -> 689.89 | H71: =SUM(H63:H70) -> 829.21 | I71: =SUM(I63:I70) -> 1148.45 | J71: =SUM(J63:J70) -> 1578.22 | ... V71: =SUM(V63:V70) -> 4652.3643
B73: Current Assets
B74: Current Investments | C74: ='Historical Data'!C76 -> 0 | D74: ='Historical Data'!D76 -> 0 | E74: ='Historical Data'!E76 -> 0 | F74: ='Historical Data'!F76 -> 0 | G74: ='Historical Data'!G76 -> 279.06 | H74: ='Historical Data'!H76 -> 145.03 | I74: ='Historical Data'!I76 -> 129.88 | J74: ='Historical Data'!J76 -> 248.92 | ... L74: ='Historical Data'!L76 -> 435.26 | M74: =Schedule!E154 -> 435.26 | N74: =Schedule!F154 -> 435.26 | O74: =Schedule!G154 -> 435.26 | P74: =Schedule!H154 -> 435.26 | Q74: =Schedule!I154 -> 435.26 | R74: =Schedule!J154 -> 435.26 | S74: =Schedule!K154 -> 435.26 | T74: =Schedule!L154 -> 435.26 | ... V74: =Schedule!N154 -> 435.26
B75: Inventories | C75: ='Historical Data'!C77 -> 595.58 | D75: ='Historical Data'!D77 -> 1017.08 | E75: ='Historical Data'!E77 -> 869.32 | F75: ='Historical Data'!F77 -> 869.82 | G75: ='Historical Data'!G77 -> 882.42 | H75: ='Historical Data'!H77 -> 1144.24 | I75: ='Historical Data'!I77 -> 1433.39 | J75: ='Historical Data'!J77 -> 1407.18 | ... L75: ='Historical Data'!L77 -> 2166.2 | M75: =Schedule!E149 -> 2188.5265 | N75: =Schedule!F149 -> 2470.6033 | O75: =Schedule!G149 -> 2786.2915 | P75: =Schedule!H149 -> 3013.6528 | Q75: =Schedule!I149 -> 3392.0337 | R75: =Schedule!J149 -> 3814.1534 | S75: =Schedule!K149 -> 4284.5657 | T75: =Schedule!L149 -> 4674.6728 | ... V75: =Schedule!N149 -> 5869.7269
B76: Trade Receivables | C76: ='Historical Data'!C78 -> 938.98 | D76: ='Historical Data'!D78 -> 950.42 | E76: ='Historical Data'!E78 -> 1112.05 | F76: ='Historical Data'!F78 -> 837.67 | G76: ='Historical Data'!G78 -> 810.98 | H76: ='Historical Data'!H78 -> 1189.74 | I76: ='Historical Data'!I78 -> 1548.82 | J76: ='Historical Data'!J78 -> 1952.56 | ... L76: ='Historical Data'!L78 -> 2139.7 | M76: =Schedule!E143 -> 2495.6881 | N76: =Schedule!F143 -> 2817.3546 | O76: =Schedule!G143 -> 3177.3499 | P76: =Schedule!H143 -> 3579.8142 | Q76: =Schedule!I143 -> 4029.2798 | R76: =Schedule!J143 -> 4530.7013 | S76: =Schedule!K143 -> 5089.4878 | T76: =Schedule!L143 -> 5711.5363 | ... V76: =Schedule!N143 -> 7171.6588
B77: Cash And Cash Equivalents | C77: ='Historical Data'!C79 -> 96.57 | D77: ='Historical Data'!D79 -> 80.88 | E77: ='Historical Data'!E79 -> 100.94 | F77: ='Historical Data'!F79 -> 293.94 | G77: ='Historical Data'!G79 -> 332.16 | H77: ='Historical Data'!H79 -> 269.66 | I77: ='Historical Data'!I79 -> 247.27 | J77: ='Historical Data'!J79 -> 377.37 | ... L77: ='Historical Data'!L79 -> 402.07 | M77: =M108 -> 1528.0328 | N77: =N108 -> 1903.2668 | O77: =O108 -> 2326.5459 | P77: =P108 -> 2888.9162 | Q77: =Q108 -> 3396.4517 | R77: =R108 -> 3967.1489 | S77: =S108 -> 4693.9722 | T77: =T108 -> 5643.1938 | ... V77: =V108 -> 7925.1976
B78: Short Term Loans And Advances | C78: ='Historical Data'!C80 -> 4.01 | D78: ='Historical Data'!D80 -> 14.22 | E78: ='Historical Data'!E80 -> 11.34 | F78: ='Historical Data'!F80 -> 14.63 | G78: ='Historical Data'!G80 -> 20.13 | H78: ='Historical Data'!H80 -> 3.18 | I78: ='Historical Data'!I80 -> 1.92 | J78: ='Historical Data'!J80 -> 2.62 | ... L78: ='Historical Data'!L80 -> 4.81 | M78: =Schedule!E158 -> 4.81 | N78: =Schedule!F158 -> 4.81 | O78: =Schedule!G158 -> 4.81 | P78: =Schedule!H158 -> 4.81 | Q78: =Schedule!I158 -> 4.81 | R78: =Schedule!J158 -> 4.81 | S78: =Schedule!K158 -> 4.81 | T78: =Schedule!L158 -> 4.81 | ... V78: =Schedule!N158 -> 4.81
B79: OtherCurrentAssets | C79: ='Historical Data'!C81 -> 386.31 | D79: ='Historical Data'!D81 -> 515.91 | E79: ='Historical Data'!E81 -> 566.93 | F79: ='Historical Data'!F81 -> 635.15 | G79: ='Historical Data'!G81 -> 534.81 | H79: ='Historical Data'!H81 -> 731.58 | I79: ='Historical Data'!I81 -> 889.33 | J79: ='Historical Data'!J81 -> 1051.38 | ... L79: ='Historical Data'!L81 -> 1240.23 | M79: =Schedule!E162 -> 1240.23 | N79: =Schedule!F162 -> 1240.23 | O79: =Schedule!G162 -> 1240.23 | P79: =Schedule!H162 -> 1240.23 | Q79: =Schedule!I162 -> 1240.23 | R79: =Schedule!J162 -> 1240.23 | S79: =Schedule!K162 -> 1240.23 | T79: =Schedule!L162 -> 1240.23 | ... V79: =Schedule!N162 -> 1240.23
B80: Total Current Assets | C80: =SUM(C74:C79) -> 2021.45 | D80: =SUM(D74:D79) -> 2578.51 | E80: =SUM(E74:E79) -> 2660.58 | F80: =SUM(F74:F79) -> 2651.21 | G80: =SUM(G74:G79) -> 2859.56 | H80: =SUM(H74:H79) -> 3483.43 | I80: =SUM(I74:I79) -> 4250.61 | J80: =SUM(J74:J79) -> 5040.03 | ... V80: =SUM(V74:V79) -> 22646.883
B82: Total Assets | C82: =SUM(C71,C80) -> 2650.18 | D82: =SUM(D71,D80) -> 3236.22 | E82: =SUM(E71,E80) -> 3350.96 | F82: =SUM(F71,F80) -> 3439.26 | G82: =SUM(G71,G80) -> 3549.45 | H82: =SUM(H71,H80) -> 4312.64 | I82: =SUM(I71,I80) -> 5399.06 | J82: =SUM(J71,J80) -> 6618.25 | ... V82: =SUM(V71,V80) -> 27299.248
B85: CASHFLOW STATEMENT
B87: Profit before Tax | M87: =M26 -> 919.56519 | N87: =N26 -> 1042.7037 | O87: =O26 -> 1175.896 | P87: =P26 -> 1324.7954 | Q87: =Q26 -> 1491.0773 | R87: =R26 -> 1676.5733 | S87: =S26 -> 1883.2828 | T87: =T26 -> 2113.3854 | ... V87: =V26 -> 2653.4684
B88: Add: Depreciation | M88: =M19 -> 196.19948 | N88: =N19 -> 221.48742 | O88: =O19 -> 249.78858 | P88: =P19 -> 281.42847 | Q88: =Q19 -> 316.76338 | R88: =R19 -> 356.18282 | S88: =S19 -> 400.11204 | T88: =T19 -> 449.01462 | ... V88: =V19 -> 563.80271
B89: Add: Interest Expense | M89: =M24 -> 75.446471 | N89: =N24 -> 80.553902 | O89: =O24 -> 90.888943 | P89: =P24 -> 102.449 | Q89: =Q24 -> 115.36557 | R89: =R24 -> 129.78248 | S89: =S24 -> 145.85687 | T89: =T24 -> 163.76014 | ... V89: =V24 -> 205.81676
B90: Less: Other Income | M90: =M23 -> 70.071243 | N90: =N23 -> 79.102648 | O90: =O23 -> 89.210209 | P90: =P23 -> 100.51017 | Q90: =Q23 -> 113.12978 | R90: =R23 -> 127.20815 | S90: =S23 -> 142.89716 | T90: =T23 -> 160.36236 | ... V90: =V23 -> 201.35811
B91: Less: Increase in net working capital | M91: =Schedule!E175 -> -764.07485 | N91: =Schedule!F175 -> 77.199953 | O91: =Schedule!G175 -> 86.398874 | P91: =Schedule!H175 -> -28.977431 | Q91: =Schedule!I175 -> 92.105866 | R91: =Schedule!J175 -> 102.75283 | S91: =Schedule!K175 -> 114.50825 | T91: =Schedule!L175 -> -6.0899854 | ... V91: =Schedule!N175 -> 139.4927
B92: Less: Tax paid | M92: =M29 -> 229.8913 | N92: =N29 -> 260.67593 | O92: =O29 -> 293.97401 | P92: =P29 -> 331.19885 | Q92: =Q29 -> 372.76932 | R92: =R29 -> 419.14332 | S92: =S29 -> 470.82069 | T92: =T29 -> 528.34636 | ... V92: =V29 -> 663.36711
B93: Net Cash From Operating Activities | C93: 128.97 | D93: -29.01 | E93: 152.22 | F93: 398.34 | G93: 308.35 | H93: 57.33 | I93: 308.1 | J93: 246.83 | K93: 662.2 | L93: 41.44 | M93: =M87+M88+M89-M90-M91-M92 -> 1655.3234 | N93: =N87+N88+N89-N90-N91-N92 -> 927.76649 | O93: =O87+O88+O89-O90-O91-O92 -> 1046.9905 | P93: =P87+P88+P89-P90-P91-P92 -> 1305.9413 | Q93: =Q87+Q88+Q89-Q90-Q91-Q92 -> 1345.2013 | R93: =R87+R88+R89-R90-R91-R92 -> 1513.4343 | S93: =S87+S88+S89-S90-S91-S92 -> 1701.0256 | T93: =T87+T88+T89-T90-T91-T92 -> 2043.5415 | ... V93: =V87+V88+V89-V90-V91-V92 -> 2418.87
B96: Net Purchase of Fixed Assets (Capex) | M96: =-(Schedule!E41+Schedule!E54) -> -320.92446 | N96: =-(Schedule!F41+Schedule!F54) -> -397.75552 | O96: =-(Schedule!G41+Schedule!G54) -> -448.42412 | P96: =-(Schedule!H41+Schedule!H54) -> -545.2528 | Q96: =-(Schedule!I41+Schedule!I54) -> -613.51407 | R96: =-(Schedule!J41+Schedule!J54) -> -689.63913 | S96: =-(Schedule!K41+Schedule!K54) -> -688.70493 | T96: =-(Schedule!L41+Schedule!L54) -> -772.59729 | ... V96: =-(Schedule!N41+Schedule!N54) -> -768.03737
B97: Other Income | M97: =M23 -> 70.071243 | N97: =N23 -> 79.102648 | O97: =O23 -> 89.210209 | P97: =P23 -> 100.51017 | Q97: =Q23 -> 113.12978 | R97: =R23 -> 127.20815 | S97: =S23 -> 142.89716 | T97: =T23 -> 160.36236 | ... V97: =V23 -> 201.35811
B98: Net Cash Used In Investing Activities | C98: 72.78 | D98: -65.63 | E98: -77.92 | F98: -64.41 | G98: -245.69 | H98: -2.36 | I98: -86.12 | J98: -698.64 | K98: -494.91 | L98: -175.93 | M98: =M96+M97 -> -250.85321 | N98: =N96+N97 -> -318.65287 | O98: =O96+O97 -> -359.21391 | P98: =P96+P97 -> -444.74263 | Q98: =Q96+Q97 -> -500.38429 | R98: =R96+R97 -> -562.43098 | S98: =S96+S97 -> -545.80777 | T98: =T96+T97 -> -612.23493 | ... V98: =V96+V97 -> -566.67926
B100: Proceeds from Long term Borrowings | M100: =Schedule!E184 -> 0 | N100: =Schedule!F184 -> 0 | O100: =Schedule!G184 -> 0 | P100: =Schedule!H184 -> 0 | Q100: =Schedule!I184 -> 0 | R100: =Schedule!J184 -> 0 | S100: =Schedule!K184 -> 0 | T100: =Schedule!L184 -> 0 | ... V100: =Schedule!N184 -> 0
B101: Proceeds from Short term Borrowings | M101: =Schedule!E191 -> 3.8411915 | N101: =Schedule!F191 -> 81.282642 | O101: =Schedule!G191 -> 90.968045 | P101: =Schedule!H191 -> 101.69964 | Q101: =Schedule!I191 -> 113.57649 | R101: =Schedule!J191 -> 126.70535 | S101: =Schedule!K191 -> 141.20105 | T101: =Schedule!L191 -> 157.18687 | ... V101: =Schedule!N191 -> 194.16675
B102: Dividend Paid | M102: =Schedule!E134 -> 206.90217 | N102: =Schedule!F134 -> 234.60833 | O102: =Schedule!G134 -> 264.57661 | P102: =Schedule!H134 -> 298.07896 | Q102: =Schedule!I134 -> 335.49239 | R102: =Schedule!J134 -> 377.22898 | S102: =Schedule!K134 -> 423.73862 | T102: =Schedule!L134 -> 475.51172 | ... V102: =Schedule!N134 -> 597.0304
B103: Interest Paid | M103: =M24 -> 75.446471 | N103: =N24 -> 80.553902 | O103: =O24 -> 90.888943 | P103: =P24 -> 102.449 | Q103: =Q24 -> 115.36557 | R103: =R24 -> 129.78248 | S103: =S24 -> 145.85687 | T103: =T24 -> 163.76014 | ... V103: =V24 -> 205.81676
B104: Net Cash Used From Financing Activities | C104: -215.43 | D104: 72.78 | E104: -104.65 | F104: -137.54 | G104: 15.35 | H104: -150.1 | I104: -247.77 | J104: 539.09 | K104: -126.1 | L104: 127.22 | M104: =M100+M101-M102-M103 -> -278.50745 | N104: =N100+N101-N102-N103 -> -233.87959 | O104: =O100+O101-O102-O103 -> -264.4975 | P104: =P100+P101-P102-P103 -> -298.82833 | Q104: =Q100+Q101-Q102-Q103 -> -337.28147 | R104: =R100+R101-R102-R103 -> -380.30611 | S104: =S100+S101-S102-S103 -> -428.39444 | T104: =T100+T101-T102-T103 -> -482.08499 | ... V104: =V100+V101-V102-V103 -> -608.6804
B106: Net Change in Cash | M106: =M93+M98+M104 -> 1125.9628 | N106: =N93+N98+N104 -> 375.23403 | O106: =O93+O98+O104 -> 423.27904 | P106: =P93+P98+P104 -> 562.37032 | Q106: =Q93+Q98+Q104 -> 507.53551 | R106: =R93+R98+R104 -> 570.69717 | S106: =S93+S98+S104 -> 726.82336 | T106: =T93+T98+T104 -> 949.22154 | ... V106: =V93+V98+V104 -> 1243.5103
B107: Opening Cash Balance | M107: =L77 -> 402.07 | N107: =M77 -> 1528.0328 | O107: =N77 -> 1903.2668 | P107: =O77 -> 2326.5459 | Q107: =P77 -> 2888.9162 | R107: =Q77 -> 3396.4517 | S107: =R77 -> 3967.1489 | T107: =S77 -> 4693.9722 | ... V107: =U77 -> 6681.6873
B108: Closing Cash Balance | M108: =M106+M107 -> 1528.0328 | N108: =N106+N107 -> 1903.2668 | O108: =O106+O107 -> 2326.5459 | P108: =P106+P107 -> 2888.9162 | Q108: =Q106+Q107 -> 3396.4517 | R108: =R106+R107 -> 3967.1489 | S108: =S106+S107 -> 4693.9722 | T108: =T106+T107 -> 5643.1938 | ... V108: =V106+V107 -> 7925.1976

Sheet Common Sized
B2: Common Size Statement - Bluestar Ltd
B3: All figures in INR Crores.
B5: Fiscal Year Ending | C5: 2017 | D5: =C5+1 -> 2018 | E5: =D5+1 -> 2019 | F5: =E5+1 -> 2020 | G5: =F5+1 -> 2021 | H5: =G5+1 -> 2022 | I5: =H5+1 -> 2023 | J5: =I5+1 -> 2024 | K5: =J5+1 -> 2025 | ... V5: =U5+1 -> 2036
B7: INCOME STATEMENT
B8: Revenue From Operations | C8: ='3 - Statement Model'!C8/'3 - Statement Model'!C$8 -> 1 | D8: ='3 - Statement Model'!D8/'3 - Statement Model'!D$8 -> 1 | E8: ='3 - Statement Model'!E8/'3 - Statement Model'!E$8 -> 1 | F8: ='3 - Statement Model'!F8/'3 - Statement Model'!F$8 -> 1 | G8: ='3 - Statement Model'!G8/'3 - Statement Model'!G$8 -> 1 | H8: ='3 - Statement Model'!H8/'3 - Statement Model'!H$8 -> 1 | I8: ='3 - Statement Model'!I8/'3 - Statement Model'!I$8 -> 1 | J8: ='3 - Statement Model'!J8/'3 - Statement Model'!J$8 -> 1 | ... V8: ='3 - Statement Model'!V8/'3 - Statement Model'!V$8 -> 1
B9: Less: Cost of Goods Sold/ Services | C9: ='3 - Statement Model'!C10/'3 - Statement Model'!C$8 -> 0.7097103 | D9: ='3 - Statement Model'!D10/'3 - Statement Model'!D$8 -> 0.74476983 | E9: ='3 - Statement Model'!E10/'3 - Statement Model'!E$8 -> 0.75096469 | F9: ='3 - Statement Model'!F10/'3 - Statement Model'!F$8 -> 0.74962082 | G9: ='3 - Statement Model'!G10/'3 - Statement Model'!G$8 -> 0.76727593 | H9: ='3 - Statement Model'!H10/'3 - Statement Model'!H$8 -> 0.7798557 | I9: ='3 - Statement Model'!I10/'3 - Statement Model'!I$8 -> 0.77490561 | J9: ='3 - Statement Model'!J10/'3 - Statement Model'!J$8 -> 0.76321066 | ... V9: ='3 - Statement Model'!V10/'3 - Statement Model'!V$8 -> 0.76
B10: Gross Profit | C10: =C8-C9 -> 0.2902897 | D10: =D8-D9 -> 0.25523017 | E10: =E8-E9 -> 0.24903531 | F10: =F8-F9 -> 0.25037918 | G10: =G8-G9 -> 0.23272407 | H10: =H8-H9 -> 0.2201443 | I10: =I8-I9 -> 0.22509439 | J10: =J8-J9 -> 0.23678934 | ... V10: =V8-V9 -> 0.24
B11: Less: SG&A Expenses | C11: ='3 - Statement Model'!C14/'3 - Statement Model'!C$8 -> 0.23957184 | D11: ='3 - Statement Model'!D14/'3 - Statement Model'!D$8 -> 0.19791117 | E11: ='3 - Statement Model'!E14/'3 - Statement Model'!E$8 -> 0.18283653 | F11: ='3 - Statement Model'!F14/'3 - Statement Model'!F$8 -> 0.19762359 | G11: ='3 - Statement Model'!G14/'3 - Statement Model'!G$8 -> 0.17647804 | H11: ='3 - Statement Model'!H14/'3 - Statement Model'!H$8 -> 0.16283467 | I11: ='3 - Statement Model'!I14/'3 - Statement Model'!I$8 -> 0.16332177 | J11: ='3 - Statement Model'!J14/'3 - Statement Model'!J$8 -> 0.16813521 | ... V11: ='3 - Statement Model'!V14/'3 - Statement Model'!V$8 -> 0.16
B12: Earning before Interest Taxes Depreciation & Amortization (EBITDA) | C12: =C10-C11 -> 0.050717863 | D12: =D10-D11 -> 0.057319005 | E12: =E10-E11 -> 0.066198776 | F12: =F10-F11 -> 0.052755593 | G12: =G10-G11 -> 0.056246027 | H12: =H10-H11 -> 0.057309638 | I12: =I10-I11 -> 0.061772625 | J12: =J10-J11 -> 0.068654134 | ... V12: =V10-V11 -> 0.08
B13: Less: Depreciation and Amortization | C13: ='3 - Statement Model'!C19/'3 - Statement Model'!C$8 -> 0.013814523 | D13: ='3 - Statement Model'!D19/'3 - Statement Model'!D$8 -> 0.013755268 | E13: ='3 - Statement Model'!E19/'3 - Statement Model'!E$8 -> 0.014307983 | F13: ='3 - Statement Model'!F19/'3 - Statement Model'!F$8 -> 0.016415463 | G13: ='3 - Statement Model'!G19/'3 - Statement Model'!G$8 -> 0.021646078 | H13: ='3 - Statement Model'!H19/'3 - Statement Model'!H$8 -> 0.014221961 | I13: ='3 - Statement Model'!I19/'3 - Statement Model'!I$8 -> 0.010627629 | J13: ='3 - Statement Model'!J19/'3 - Statement Model'!J$8 -> 0.010078097 | ... V13: ='3 - Statement Model'!V19/'3 - Statement Model'!V$8 -> 0.014
B14: Earning before Interest & Taxes (EBIT) | C14: =C12-C13 -> 0.036903339 | D14: =D12-D13 -> 0.043563737 | E14: =E12-E13 -> 0.051890793 | F14: =F12-F13 -> 0.03634013 | G14: =G12-G13 -> 0.03459995 | H14: =H12-H13 -> 0.043087677 | I14: =I12-I13 -> 0.051144996 | J14: =J12-J13 -> 0.058576036 | ... V14: =V12-V13 -> 0.066
B15: Add: Other Income | C15: ='3 - Statement Model'!C23/'3 - Statement Model'!C$8 -> 0.0029804526 | D15: ='3 - Statement Model'!D23/'3 - Statement Model'!D$8 -> 0.0036538441 | E15: ='3 - Statement Model'!E23/'3 - Statement Model'!E$8 -> 0.0047164765 | F15: ='3 - Statement Model'!F23/'3 - Statement Model'!F$8 -> 0.0083392566 | G15: ='3 - Statement Model'!G23/'3 - Statement Model'!G$8 -> 0.014623826 | H15: ='3 - Statement Model'!H23/'3 - Statement Model'!H$8 -> 0.0059084488 | I15: ='3 - Statement Model'!I23/'3 - Statement Model'!I$8 -> 0.0038697207 | J15: ='3 - Statement Model'!J23/'3 - Statement Model'!J$8 -> 0.0048960493 | ... V15: ='3 - Statement Model'!V23/'3 - Statement Model'!V$8 -> 0.005
B16: Less: Interest Expenses | C16: ='3 - Statement Model'!C24/'3 - Statement Model'!C$8 -> 0.0037101732 | D16: ='3 - Statement Model'!D24/'3 - Statement Model'!D$8 -> 0.0061953675 | E16: ='3 - Statement Model'!E24/'3 - Statement Model'!E$8 -> 0.0091445011 | F16: ='3 - Statement Model'!F24/'3 - Statement Model'!F$8 -> 0.0054979394 | G16: ='3 - Statement Model'!G24/'3 - Statement Model'!G$8 -> 0.015179696 | H16: ='3 - Statement Model'!H24/'3 - Statement Model'!H$8 -> 0.0076750287 | I16: ='3 - Statement Model'!I24/'3 - Statement Model'!I$8 -> 0.0068569394 | J16: ='3 - Statement Model'!J24/'3 - Statement Model'!J$8 -> 0.0059966795 | ... V16: ='3 - Statement Model'!V24/'3 - Statement Model'!V$8 -> 0.0051107143
B17: Less: Other Expense | C17: ='3 - Statement Model'!C25/'3 - Statement Model'!C$8 -> 0 | D17: ='3 - Statement Model'!D25/'3 - Statement Model'!D$8 -> -0.0011360329 | E17: ='3 - Statement Model'!E25/'3 - Statement Model'!E$8 -> -0.00051195452 | F17: ='3 - Statement Model'!F25/'3 - Statement Model'!F$8 -> 0.00075183902 | G17: ='3 - Statement Model'!G25/'3 - Statement Model'!G$8 -> 0 | H17: ='3 - Statement Model'!H25/'3 - Statement Model'!H$8 -> 0 | I17: ='3 - Statement Model'!I25/'3 - Statement Model'!I$8 -> -0.021411953 | J17: ='3 - Statement Model'!J25/'3 - Statement Model'!J$8 -> 0 | ... V17: ='3 - Statement Model'!V25/'3 - Statement Model'!V$8 -> 0
B18: Profit Before Tax (PBT) | C18: =C14+C15-C16-C17 -> 0.036173619 | D18: =D14+D15-D16-D17 -> 0.042158247 | E18: =E14+E15-E16-E17 -> 0.047974723 | F18: =F14+F15-F16-F17 -> 0.038429608 | G18: =G14+G15-G16-G17 -> 0.03404408 | H18: =H14+H15-H16-H17 -> 0.041321097 | I18: =I14+I15-I16-I17 -> 0.06956973 | J18: =J14+J15-J16-J17 -> 0.057475406 | ... V18: =V14+V15-V16-V17 -> 0.065889286
B19: Less: Tax Expense | C19: ='3 - Statement Model'!C29/'3 - Statement Model'!C$8 -> 0.0083621421 | D19: ='3 - Statement Model'!D29/'3 - Statement Model'!D$8 -> 0.010653273 | E19: ='3 - Statement Model'!E29/'3 - Statement Model'!E$8 -> 0.0080212576 | F19: ='3 - Statement Model'!F29/'3 - Statement Model'!F$8 -> 0.012186135 | G19: ='3 - Statement Model'!G29/'3 - Statement Model'!G$8 -> 0.011044683 | H19: ='3 - Statement Model'!H29/'3 - Statement Model'!H$8 -> 0.013712497 | I19: ='3 - Statement Model'!I29/'3 - Statement Model'!I$8 -> 0.019391224 | J19: ='3 - Statement Model'!J29/'3 - Statement Model'!J$8 -> 0.014749065 | ... V19: ='3 - Statement Model'!V29/'3 - Statement Model'!V$8 -> 0.016472321
B20: Net Income | C20: =C18-C19 -> 0.027811477 | D20: =D18-D19 -> 0.031504974 | E20: =E18-E19 -> 0.039953466 | F20: =F18-F19 -> 0.026243473 | G20: =G18-G19 -> 0.022999397 | H20: =H18-H19 -> 0.0276086 | I20: =I18-I19 -> 0.050178506 | J20: =J18-J19 -> 0.042726342 | ... V20: =V18-V19 -> 0.049416964
B21: Add:Profit from Discontinued Operations | C21: ='3 - Statement Model'!C32/'3 - Statement Model'!C$8 -> 0 | D21: ='3 - Statement Model'!D32/'3 - Statement Model'!D$8 -> 0 | E21: ='3 - Statement Model'!E32/'3 - Statement Model'!E$8 -> 0 | F21: ='3 - Statement Model'!F32/'3 - Statement Model'!F$8 -> 0 | G21: ='3 - Statement Model'!G32/'3 - Statement Model'!G$8 -> 0 | H21: ='3 - Statement Model'!H32/'3 - Statement Model'!H$8 -> 0 | I21: ='3 - Statement Model'!I32/'3 - Statement Model'!I$8 -> 0 | J21: ='3 - Statement Model'!J32/'3 - Statement Model'!J$8 -> 0 | ... V21: ='3 - Statement Model'!V32/'3 - Statement Model'!V$8 -> 0
B22: Less: Loss from Discontinued Operations | C22: ='3 - Statement Model'!C33/'3 - Statement Model'!C$8 -> 0 | D22: ='3 - Statement Model'!D33/'3 - Statement Model'!D$8 -> 0 | E22: ='3 - Statement Model'!E33/'3 - Statement Model'!E$8 -> 0 | F22: ='3 - Statement Model'!F33/'3 - Statement Model'!F$8 -> 0 | G22: ='3 - Statement Model'!G33/'3 - Statement Model'!G$8 -> 0 | H22: ='3 - Statement Model'!H33/'3 - Statement Model'!H$8 -> 0 | I22: ='3 - Statement Model'!I33/'3 - Statement Model'!I$8 -> 0 | J22: ='3 - Statement Model'!J33/'3 - Statement Model'!J$8 -> 0 | ... V22: ='3 - Statement Model'!V33/'3 - Statement Model'!V$8 -> 0
B23: Net Income of the Year | C23: =C20+C21-C22 -> 0.027811477 | D23: =D20+D21-D22 -> 0.031504974 | E23: =E20+E21-E22 -> 0.039953466 | F23: =F20+F21-F22 -> 0.026243473 | G23: =G20+G21-G22 -> 0.022999397 | H23: =H20+H21-H22 -> 0.0276086 | I23: =I20+I21-I22 -> 0.050178506 | J23: =J20+J21-J22 -> 0.042726342 | ... V23: =V20+V21-V22 -> 0.049416964
B26: BALANCE SHEET
B27: Equity and Liablities
B28: Shareholder's Funds
B29: Equity Share Capital | C29: ='3 - Statement Model'!C40/'3 - Statement Model'!C$59 -> 0.007210831 | D29: ='3 - Statement Model'!D40/'3 - Statement Model'!D$59 -> 0.0059328476 | E29: ='3 - Statement Model'!E40/'3 - Statement Model'!E$59 -> 0.0057476067 | F29: ='3 - Statement Model'!F40/'3 - Statement Model'!F$59 -> 0.0056000419 | G29: ='3 - Statement Model'!G40/'3 - Statement Model'!G$59 -> 0.0054261928 | H29: ='3 - Statement Model'!H40/'3 - Statement Model'!H$59 -> 0.004465942 | I29: ='3 - Statement Model'!I40/'3 - Statement Model'!I$59 -> 0.0035672876 | J29: ='3 - Statement Model'!J40/'3 - Statement Model'!J$59 -> 0.0062131228 | ... V29: ='3 - Statement Model'!V40/'3 - Statement Model'!V$59 -> 0.0015062686
B30: Reserves & Surplus | C30: ='3 - Statement Model'!C41/'3 - Statement Model'!C$59 -> 0.2784792 | D30: ='3 - Statement Model'!D41/'3 - Statement Model'!D$59 -> 0.23902269 | E30: ='3 - Statement Model'!E41/'3 - Statement Model'!E$59 -> 0.25479266 | F30: ='3 - Statement Model'!F41/'3 - Statement Model'!F$59 -> 0.22188203 | G30: ='3 - Statement Model'!G41/'3 - Statement Model'!G$59 -> 0.24395892 | H30: ='3 - Statement Model'!H41/'3 - Statement Model'!H$59 -> 0.23148698 | I30: ='3 - Statement Model'!I41/'3 - Statement Model'!I$59 -> 0.24289228 | J30: ='3 - Statement Model'!J41/'3 - Statement Model'!J$59 -> 0.38816152 | ... V30: ='3 - Statement Model'!V41/'3 - Statement Model'!V$59 -> 0.44439103
B31: Total Shareholder's Funds | C31: =C29+C30 -> 0.28569003 | D31: =D29+D30 -> 0.24495553 | E31: =E29+E30 -> 0.26054026 | F31: =F29+F30 -> 0.22748207 | G31: =G29+G30 -> 0.24938512 | H31: =H29+H30 -> 0.23595292 | I31: =I29+I30 -> 0.24645957 | J31: =J29+J30 -> 0.39437465 | ... V31: =V29+V30 -> 0.4458973
B32: Minority Interest | C32: ='3 - Statement Model'!C43/'3 - Statement Model'!C$59 -> 0.00046034609 | D32: ='3 - Statement Model'!D43/'3 - Statement Model'!D$59 -> 0.00046968377 | E32: ='3 - Statement Model'!E43/'3 - Statement Model'!E$59 -> 0.00054611216 | F32: ='3 - Statement Model'!F43/'3 - Statement Model'!F$59 -> 0.00067165611 | G32: ='3 - Statement Model'!G43/'3 - Statement Model'!G$59 -> 0.00075504656 | H32: ='3 - Statement Model'!H43/'3 - Statement Model'!H$59 -> 0.00068635453 | I32: ='3 - Statement Model'!I43/'3 - Statement Model'!I$59 -> 0.00059084359 | J32: ='3 - Statement Model'!J43/'3 - Statement Model'!J$59 -> 0.00038529823 | ... V32: ='3 - Statement Model'!V43/'3 - Statement Model'!V$59 -> 8.9746063e-05
B34: Non Current Liablities
B35: Long Term Borrowings | C35: ='3 - Statement Model'!C46/'3 - Statement Model'!C$59 -> 0.0076221238 | D35: ='3 - Statement Model'!D46/'3 - Statement Model'!D$59 -> 0.0080031642 | E35: ='3 - Statement Model'!E46/'3 - Statement Model'!E$59 -> 0.0025813498 | F35: ='3 - Statement Model'!F46/'3 - Statement Model'!F$59 -> 0.01387217 | G35: ='3 - Statement Model'!G46/'3 - Statement Model'!G$59 -> 0.098398343 | H35: ='3 - Statement Model'!H46/'3 - Statement Model'!H$59 -> 0.056014413 | I35: ='3 - Statement Model'!I46/'3 - Statement Model'!I$59 -> 0.029957067 | J35: ='3 - Statement Model'!J46/'3 - Statement Model'!J$59 -> 0 | ... V35: ='3 - Statement Model'!V46/'3 - Statement Model'!V$59 -> 0
B36: Deferred Tax Liabilities | C36: ='3 - Statement Model'!C47/'3 - Statement Model'!C$59 -> 0 | D36: ='3 - Statement Model'!D47/'3 - Statement Model'!D$59 -> 0 | E36: ='3 - Statement Model'!E47/'3 - Statement Model'!E$59 -> 0 | F36: ='3 - Statement Model'!F47/'3 - Statement Model'!F$59 -> 0 | G36: ='3 - Statement Model'!G47/'3 - Statement Model'!G$59 -> 0 | H36: ='3 - Statement Model'!H47/'3 - Statement Model'!H$59 -> 0 | I36: ='3 - Statement Model'!I47/'3 - Statement Model'!I$59 -> 0 | J36: ='3 - Statement Model'!J47/'3 - Statement Model'!J$59 -> 0.0010546595 | ... V36: ='3 - Statement Model'!V47/'3 - Statement Model'!V$59 -> 0.0011575411
B37: Other Long Term Liabilities | C37: ='3 - Statement Model'!C48/'3 - Statement Model'!C$59 -> 0.0015395181 | D37: ='3 - Statement Model'!D48/'3 - Statement Model'!D$59 -> 0.0019374455 | E37: ='3 - Statement Model'!E48/'3 - Statement Model'!E$59 -> 0.0019248215 | F37: ='3 - Statement Model'!F48/'3 - Statement Model'!F$59 -> 0.01393323 | G37: ='3 - Statement Model'!G48/'3 - Statement Model'!G$59 -> 0.011286256 | H37: ='3 - Statement Model'!H48/'3 - Statement Model'!H$59 -> 0.01652584 | I37: ='3 - Statement Model'!I48/'3 - Statement Model'!I$59 -> 0.020062752 | J37: ='3 - Statement Model'!J48/'3 - Statement Model'!J$59 -> 0.015578136 | ... V37: ='3 - Statement Model'!V48/'3 - Statement Model'!V$59 -> 0.007014479
B38: Long Term Provisions | C38: ='3 - Statement Model'!C49/'3 - Statement Model'!C$59 -> 0.0042148081 | D38: ='3 - Statement Model'!D49/'3 - Statement Model'!D$59 -> 0.0038748911 | E38: ='3 - Statement Model'!E49/'3 - Statement Model'!E$59 -> 0.0035989687 | F38: ='3 - Statement Model'!F49/'3 - Statement Model'!F$59 -> 0.0038554805 | G38: ='3 - Statement Model'!G49/'3 - Statement Model'!G$59 -> 0.0030483596 | H38: ='3 - Statement Model'!H49/'3 - Statement Model'!H$59 -> 0.0023326779 | I38: ='3 - Statement Model'!I49/'3 - Statement Model'!I$59 -> 0.0021133308 | J38: ='3 - Statement Model'!J49/'3 - Statement Model'!J$59 -> 0.0024069807 | ... V38: ='3 - Statement Model'!V49/'3 - Statement Model'!V$59 -> 0.0019330203
B39: Total Non-Current Liabilities | C39: =SUM(C35:C38) -> 0.01337645 | D39: =SUM(D35:D38) -> 0.013815501 | E39: =SUM(E35:E38) -> 0.00810514 | F39: =SUM(F35:F38) -> 0.031660881 | G39: =SUM(G35:G38) -> 0.11273296 | H39: =SUM(H35:H38) -> 0.074872932 | I39: =SUM(I35:I38) -> 0.052133149 | J39: =SUM(J35:J38) -> 0.019039776 | ... V39: =SUM(V35:V38) -> 0.01010504
B41: Current Liablities
B42: Short Term Borrowings | C42: ='3 - Statement Model'!C53/'3 - Statement Model'!C$59 -> 0.073927054 | D42: ='3 - Statement Model'!D53/'3 - Statement Model'!D$59 -> 0.10630303 | E42: ='3 - Statement Model'!E53/'3 - Statement Model'!E$59 -> 0.10023695 | F42: ='3 - Statement Model'!F53/'3 - Statement Model'!F$59 -> 0.11666172 | G42: ='3 - Statement Model'!G53/'3 - Statement Model'!G$59 -> 0.028832636 | H42: ='3 - Statement Model'!H53/'3 - Statement Model'!H$59 -> 0.054783149 | I42: ='3 - Statement Model'!I53/'3 - Statement Model'!I$59 -> 0.077031928 | J42: ='3 - Statement Model'!J53/'3 - Statement Model'!J$59 -> 0.02517584 | ... V42: ='3 - Statement Model'!V53/'3 - Statement Model'!V$59 -> 0.066383625
B43: Trade Payables | C43: ='3 - Statement Model'!C54/'3 - Statement Model'!C$59 -> 0.44420756 | D43: ='3 - Statement Model'!D54/'3 - Statement Model'!D$59 -> 0.47360501 | E43: ='3 - Statement Model'!E54/'3 - Statement Model'!E$59 -> 0.45796428 | F43: ='3 - Statement Model'!F54/'3 - Statement Model'!F$59 -> 0.46008734 | G43: ='3 - Statement Model'!G54/'3 - Statement Model'!G$59 -> 0.45215174 | H43: ='3 - Statement Model'!H54/'3 - Statement Model'!H$59 -> 0.47341536 | I43: ='3 - Statement Model'!I54/'3 - Statement Model'!I$59 -> 0.46511059 | J43: ='3 - Statement Model'!J54/'3 - Statement Model'!J$59 -> 0.39536131 | ... V43: ='3 - Statement Model'!V54/'3 - Statement Model'!V$59 -> 0.43002847
B44: Other Current Liabilities | C44: ='3 - Statement Model'!C55/'3 - Statement Model'!C$59 -> 0.16730184 | D44: ='3 - Statement Model'!D55/'3 - Statement Model'!D$59 -> 0.14262009 | E44: ='3 - Statement Model'!E55/'3 - Statement Model'!E$59 -> 0.14664454 | F44: ='3 - Statement Model'!F55/'3 - Statement Model'!F$59 -> 0.14454272 | G44: ='3 - Statement Model'!G55/'3 - Statement Model'!G$59 -> 0.14251504 | H44: ='3 - Statement Model'!H55/'3 - Statement Model'!H$59 -> 0.14618656 | I44: ='3 - Statement Model'!I55/'3 - Statement Model'!I$59 -> 0.14663478 | J44: ='3 - Statement Model'!J55/'3 - Statement Model'!J$59 -> 0.15404979 | ... V44: ='3 - Statement Model'!V55/'3 - Statement Model'!V$59 -> 0.042496043
B45: Short Term Provisions | C45: ='3 - Statement Model'!C56/'3 - Statement Model'!C$59 -> 0.015036714 | D45: ='3 - Statement Model'!D56/'3 - Statement Model'!D$59 -> 0.018231146 | E45: ='3 - Statement Model'!E56/'3 - Statement Model'!E$59 -> 0.025962709 | F45: ='3 - Statement Model'!F56/'3 - Statement Model'!F$59 -> 0.018893599 | G45: ='3 - Statement Model'!G56/'3 - Statement Model'!G$59 -> 0.013627463 | H45: ='3 - Statement Model'!H56/'3 - Statement Model'!H$59 -> 0.014102731 | I45: ='3 - Statement Model'!I56/'3 - Statement Model'!I$59 -> 0.012039133 | J45: ='3 - Statement Model'!J56/'3 - Statement Model'!J$59 -> 0.011613342 | ... V45: ='3 - Statement Model'!V56/'3 - Statement Model'!V$59 -> 0.0049997715
B46: Total Current Liabilities | C46: =SUM(C42:C45) -> 0.70047318 | D46: =SUM(D42:D45) -> 0.74075928 | E46: =SUM(E42:E45) -> 0.73080848 | F46: =SUM(F42:F45) -> 0.74018539 | G46: =SUM(G42:G45) -> 0.63712688 | H46: =SUM(H42:H45) -> 0.68848779 | I46: =SUM(I42:I45) -> 0.70081644 | J46: =SUM(J42:J45) -> 0.58620028 | ... V46: =SUM(V42:V45) -> 0.54390791
B48: Total Equity and Liablities | C48: ='3 - Statement Model'!C59/'3 - Statement Model'!C$59 -> 1 | D48: ='3 - Statement Model'!D59/'3 - Statement Model'!D$59 -> 1 | E48: ='3 - Statement Model'!E59/'3 - Statement Model'!E$59 -> 1 | F48: ='3 - Statement Model'!F59/'3 - Statement Model'!F$59 -> 1 | G48: ='3 - Statement Model'!G59/'3 - Statement Model'!G$59 -> 1 | H48: ='3 - Statement Model'!H59/'3 - Statement Model'!H$59 -> 1 | I48: ='3 - Statement Model'!I59/'3 - Statement Model'!I$59 -> 1 | J48: ='3 - Statement Model'!J59/'3 - Statement Model'!J$59 -> 1 | ... V48: ='3 - Statement Model'!V59/'3 - Statement Model'!V$59 -> 1
B50: Assets
B51: Non Current Assets
B52: Tangible Assets | C52: ='3 - Statement Model'!C63/'3 - Statement Model'!C$82 -> 0.11787124 | D52: ='3 - Statement Model'!D63/'3 - Statement Model'!D$82 -> 0.10378466 | E52: ='3 - Statement Model'!E63/'3 - Statement Model'!E$82 -> 0.10441187 | F52: ='3 - Statement Model'!F63/'3 - Statement Model'!F$82 -> 0.11409431 | G52: ='3 - Statement Model'!G63/'3 - Statement Model'!G$82 -> 0.093324318 | H52: ='3 - Statement Model'!H63/'3 - Statement Model'!H$82 -> 0.090693867 | I52: ='3 - Statement Model'!I63/'3 - Statement Model'!I$82 -> 0.14816098 | J52: ='3 - Statement Model'!J63/'3 - Statement Model'!J$82 -> 0.16187361 | ... V52: ='3 - Statement Model'!V63/'3 - Statement Model'!V$82 -> 0.13394758
B53: Intangible Assets | C53: ='3 - Statement Model'!C64/'3 - Statement Model'!C$82 -> 0.016500766 | D53: ='3 - Statement Model'!D64/'3 - Statement Model'!D$82 -> 0.017344309 | E53: ='3 - Statement Model'!E64/'3 - Statement Model'!E$82 -> 0.015016592 | F53: ='3 - Statement Model'!F64/'3 - Statement Model'!F$82 -> 0.014942168 | G53: ='3 - Statement Model'!G64/'3 - Statement Model'!G$82 -> 0.014737495 | H53: ='3 - Statement Model'!H64/'3 - Statement Model'!H$82 -> 0.009662295 | I53: ='3 - Statement Model'!I64/'3 - Statement Model'!I$82 -> 0.010920419 | J53: ='3 - Statement Model'!J64/'3 - Statement Model'!J$82 -> 0.014085294 | ... V53: ='3 - Statement Model'!V64/'3 - Statement Model'!V$82 -> 0.014751917
B54: Capital Work-In-Progress | C54: ='3 - Statement Model'!C65/'3 - Statement Model'!C$82 -> 0.0081164298 | D54: ='3 - Statement Model'!D65/'3 - Statement Model'!D$82 -> 0.0056794655 | E54: ='3 - Statement Model'!E65/'3 - Statement Model'!E$82 -> 0.0091824432 | F54: ='3 - Statement Model'!F65/'3 - Statement Model'!F$82 -> 0.016384338 | G54: ='3 - Statement Model'!G65/'3 - Statement Model'!G$82 -> 0.019188888 | H54: ='3 - Statement Model'!H65/'3 - Statement Model'!H$82 -> 0.033642966 | I54: ='3 - Statement Model'!I65/'3 - Statement Model'!I$82 -> 0.011285298 | J54: ='3 - Statement Model'!J65/'3 - Statement Model'!J$82 -> 0.016327579 | ... V54: ='3 - Statement Model'!V65/'3 - Statement Model'!V$82 -> 0.0023982346
B55: Intangible Assets Under Development | C55: ='3 - Statement Model'!C66/'3 - Statement Model'!C$82 -> 0.0045619543 | D55: ='3 - Statement Model'!D66/'3 - Statement Model'!D$82 -> 0.0021537473 | E55: ='3 - Statement Model'!E66/'3 - Statement Model'!E$82 -> 0.0031185093 | F55: ='3 - Statement Model'!F66/'3 - Statement Model'!F$82 -> 0.00320127 | G55: ='3 - Statement Model'!G66/'3 - Statement Model'!G$82 -> 0.00096352956 | H55: ='3 - Statement Model'!H66/'3 - Statement Model'!H$82 -> 0.001669511 | I55: ='3 - Statement Model'!I66/'3 - Statement Model'!I$82 -> 0.0041470182 | J55: ='3 - Statement Model'!J66/'3 - Statement Model'!J$82 -> 0.0028708495 | ... V55: ='3 - Statement Model'!V66/'3 - Statement Model'!V$82 -> 0
B56: Non-Current Investments | C56: ='3 - Statement Model'!C67/'3 - Statement Model'!C$82 -> 0.0041393415 | D56: ='3 - Statement Model'!D67/'3 - Statement Model'!D$82 -> 0.0040911928 | E56: ='3 - Statement Model'!E67/'3 - Statement Model'!E$82 -> 0.0043659131 | F56: ='3 - Statement Model'!F67/'3 - Statement Model'!F$82 -> 0.0049051249 | G56: ='3 - Statement Model'!G67/'3 - Statement Model'!G$82 -> 0.0044823846 | H56: ='3 - Statement Model'!H67/'3 - Statement Model'!H$82 -> 0.0040137827 | I56: ='3 - Statement Model'!I67/'3 - Statement Model'!I$82 -> 0.0033746615 | J56: ='3 - Statement Model'!J67/'3 - Statement Model'!J$82 -> 0.0027016205 | ... V56: ='3 - Statement Model'!V67/'3 - Statement Model'!V$82 -> 0.00080368515
B57: Deferred Tax Assets [Net] | C57: ='3 - Statement Model'!C68/'3 - Statement Model'!C$82 -> 0.040623656 | D57: ='3 - Statement Model'!D68/'3 - Statement Model'!D$82 -> 0.035093411 | E57: ='3 - Statement Model'!E68/'3 - Statement Model'!E$82 -> 0.03209528 | F57: ='3 - Statement Model'!F68/'3 - Statement Model'!F$82 -> 0.023769648 | G57: ='3 - Statement Model'!G68/'3 - Statement Model'!G$82 -> 0.013379538 | H57: ='3 - Statement Model'!H68/'3 - Statement Model'!H$82 -> 0.0063928359 | I57: ='3 - Statement Model'!I68/'3 - Statement Model'!I$82 -> 0.0014706264 | J57: ='3 - Statement Model'!J68/'3 - Statement Model'!J$82 -> 0.0010999887 | ... V57: ='3 - Statement Model'!V68/'3 - Statement Model'!V$82 -> 0.00033920349
B58: Long Term Loans And Advances | C58: ='3 - Statement Model'!C69/'3 - Statement Model'!C$82 -> 0.0065316318 | D58: ='3 - Statement Model'!D69/'3 - Statement Model'!D$82 -> 0.005614575 | E58: ='3 - Statement Model'!E69/'3 - Statement Model'!E$82 -> 0.0059147229 | F58: ='3 - Statement Model'!F69/'3 - Statement Model'!F$82 -> 0.0056058571 | G58: ='3 - Statement Model'!G69/'3 - Statement Model'!G$82 -> 0.0063164716 | H58: ='3 - Statement Model'!H69/'3 - Statement Model'!H$82 -> 0.00077446761 | I58: ='3 - Statement Model'!I69/'3 - Statement Model'!I$82 -> 0.00086866973 | J58: ='3 - Statement Model'!J69/'3 - Statement Model'!J$82 -> 0.00088543044 | ... V58: ='3 - Statement Model'!V69/'3 - Statement Model'!V$82 -> 0.00085386969
B59: Other Non-Current Assets | C59: ='3 - Statement Model'!C70/'3 - Statement Model'!C$82 -> 0.038895471 | D59: ='3 - Statement Model'!D70/'3 - Statement Model'!D$82 -> 0.029472656 | E59: ='3 - Statement Model'!E70/'3 - Statement Model'!E$82 -> 0.031919211 | F59: ='3 - Statement Model'!F70/'3 - Statement Model'!F$82 -> 0.046230875 | G59: ='3 - Statement Model'!G70/'3 - Statement Model'!G$82 -> 0.0419727 | H59: ='3 - Statement Model'!H70/'3 - Statement Model'!H$82 -> 0.045424612 | I59: ='3 - Statement Model'!I70/'3 - Statement Model'!I$82 -> 0.032485284 | J59: ='3 - Statement Model'!J70/'3 - Statement Model'!J$82 -> 0.038620481 | ... V59: ='3 - Statement Model'!V70/'3 - Statement Model'!V$82 -> 0.017326485
B60: Total Non-Current Assets | C60: =SUM(C52:C59) -> 0.23724049 | D60: =SUM(D52:D59) -> 0.20323402 | E60: =SUM(E52:E59) -> 0.20602454 | F60: =SUM(F52:F59) -> 0.22913359 | G60: =SUM(G52:G59) -> 0.19436532 | H60: =SUM(H52:H59) -> 0.19227434 | I60: =SUM(I52:I59) -> 0.21271295 | J60: =SUM(J52:J59) -> 0.23846485 | ... V60: =SUM(V52:V59) -> 0.17042097
B62: Current Assets
B63: Current Investments | C63: ='3 - Statement Model'!C74/'3 - Statement Model'!C$82 -> 0 | D63: ='3 - Statement Model'!D74/'3 - Statement Model'!D$82 -> 0 | E63: ='3 - Statement Model'!E74/'3 - Statement Model'!E$82 -> 0 | F63: ='3 - Statement Model'!F74/'3 - Statement Model'!F$82 -> 0 | G63: ='3 - Statement Model'!G74/'3 - Statement Model'!G$82 -> 0.078620631 | H63: ='3 - Statement Model'!H74/'3 - Statement Model'!H$82 -> 0.033629053 | I63: ='3 - Statement Model'!I74/'3 - Statement Model'!I$82 -> 0.024056039 | J63: ='3 - Statement Model'!J74/'3 - Statement Model'!J$82 -> 0.037611151 | ... V63: ='3 - Statement Model'!V74/'3 - Statement Model'!V$82 -> 0.015944029
B64: Inventories | C64: ='3 - Statement Model'!C75/'3 - Statement Model'!C$82 -> 0.22473191 | D64: ='3 - Statement Model'!D75/'3 - Statement Model'!D$82 -> 0.31428024 | E64: ='3 - Statement Model'!E75/'3 - Statement Model'!E$82 -> 0.25942417 | F64: ='3 - Statement Model'!F75/'3 - Statement Model'!F$82 -> 0.25290906 | G64: ='3 - Statement Model'!G75/'3 - Statement Model'!G$82 -> 0.24860753 | H64: ='3 - Statement Model'!H75/'3 - Statement Model'!H$82 -> 0.2653224 | I64: ='3 - Statement Model'!I75/'3 - Statement Model'!I$82 -> 0.26548881 | J64: ='3 - Statement Model'!J75/'3 - Statement Model'!J$82 -> 0.21262116 | ... V64: ='3 - Statement Model'!V75/'3 - Statement Model'!V$82 -> 0.21501424
B65: Trade Receivables | C65: ='3 - Statement Model'!C76/'3 - Statement Model'!C$82 -> 0.35430801 | D65: ='3 - Statement Model'!D76/'3 - Statement Model'!D$82 -> 0.29368214 | E65: ='3 - Statement Model'!E76/'3 - Statement Model'!E$82 -> 0.33186012 | F65: ='3 - Statement Model'!F76/'3 - Statement Model'!F$82 -> 0.24356111 | G65: ='3 - Statement Model'!G76/'3 - Statement Model'!G$82 -> 0.22848047 | H65: ='3 - Statement Model'!H76/'3 - Statement Model'!H$82 -> 0.27587278 | I65: ='3 - Statement Model'!I76/'3 - Statement Model'!I$82 -> 0.28686845 | J65: ='3 - Statement Model'!J76/'3 - Statement Model'!J$82 -> 0.29502663 | ... V65: ='3 - Statement Model'!V76/'3 - Statement Model'!V$82 -> 0.26270536
B66: Cash And Cash Equivalents | C66: ='3 - Statement Model'!C77/'3 - Statement Model'!C$82 -> 0.036439034 | D66: ='3 - Statement Model'!D77/'3 - Statement Model'!D$82 -> 0.02499212 | E66: ='3 - Statement Model'!E77/'3 - Statement Model'!E$82 -> 0.030122711 | F66: ='3 - Statement Model'!F77/'3 - Statement Model'!F$82 -> 0.08546606 | G66: ='3 - Statement Model'!G77/'3 - Statement Model'!G$82 -> 0.093580696 | H66: ='3 - Statement Model'!H77/'3 - Statement Model'!H$82 -> 0.062527825 | I66: ='3 - Statement Model'!I77/'3 - Statement Model'!I$82 -> 0.045798713 | J66: ='3 - Statement Model'!J77/'3 - Statement Model'!J$82 -> 0.057019605 | ... V66: ='3 - Statement Model'!V77/'3 - Statement Model'!V$82 -> 0.29030828
B67: Short Term Loans And Advances | C67: ='3 - Statement Model'!C78/'3 - Statement Model'!C$82 -> 0.0015131048 | D67: ='3 - Statement Model'!D78/'3 - Statement Model'!D$82 -> 0.0043940152 | E67: ='3 - Statement Model'!E78/'3 - Statement Model'!E$82 -> 0.0033841049 | F67: ='3 - Statement Model'!F78/'3 - Statement Model'!F$82 -> 0.004253822 | G67: ='3 - Statement Model'!G78/'3 - Statement Model'!G$82 -> 0.0056713012 | H67: ='3 - Statement Model'!H78/'3 - Statement Model'!H$82 -> 0.00073736737 | I67: ='3 - Statement Model'!I78/'3 - Statement Model'!I$82 -> 0.00035561746 | J67: ='3 - Statement Model'!J78/'3 - Statement Model'!J$82 -> 0.00039587504 | ... V67: ='3 - Statement Model'!V78/'3 - Statement Model'!V$82 -> 0.00017619533
B68: OtherCurrentAssets | C68: ='3 - Statement Model'!C79/'3 - Statement Model'!C$82 -> 0.14576746 | D68: ='3 - Statement Model'!D79/'3 - Statement Model'!D$82 -> 0.15941747 | E68: ='3 - Statement Model'!E79/'3 - Statement Model'!E$82 -> 0.16918435 | F68: ='3 - Statement Model'!F79/'3 - Statement Model'!F$82 -> 0.18467635 | G68: ='3 - Statement Model'!G79/'3 - Statement Model'!G$82 -> 0.15067405 | H68: ='3 - Statement Model'!H79/'3 - Statement Model'!H$82 -> 0.16963623 | I68: ='3 - Statement Model'!I79/'3 - Statement Model'!I$82 -> 0.16471941 | J68: ='3 - Statement Model'!J79/'3 - Statement Model'!J$82 -> 0.15886073 | ... V68: ='3 - Statement Model'!V79/'3 - Statement Model'!V$82 -> 0.045430922
B69: Total Current Assets | C69: ='3 - Statement Model'!C80/'3 - Statement Model'!C$82 -> 0.76275951 | D69: =SUM(D63:D68) -> 0.79676598 | E69: =SUM(E63:E68) -> 0.79397546 | F69: =SUM(F63:F68) -> 0.77086641 | G69: =SUM(G63:G68) -> 0.80563468 | H69: =SUM(H63:H68) -> 0.80772566 | I69: =SUM(I63:I68) -> 0.78728705 | J69: =SUM(J63:J68) -> 0.76153515 | K69: =SUM(K63:K68) -> 0.76448925 | ... V69: =SUM(V63:V68) -> 0.82957903
B71: Total Assets | C71: ='3 - Statement Model'!C82/'3 - Statement Model'!C$82 -> 1 | D71: =SUM(D60,D69) -> 1 | E71: =SUM(E60,E69) -> 1 | F71: =SUM(F60,F69) -> 1 | G71: =SUM(G60,G69) -> 1 | H71: =SUM(H60,H69) -> 1 | I71: =SUM(I60,I69) -> 1 | J71: =SUM(J60,J69) -> 1 | K71: =SUM(K60,K69) -> 1 | ... V71: =SUM(V60,V69) -> 1

Sheet Valuation>>>

Sheet DCF Analysis
B2: DCF Analysis - Blue Star Ltd
B3: All figures in INR Crores.
B5: Fiscal Year Ending | E5: =2027 -> 2027 | F5: =E5+1 -> 2028 | G5: =F5+1 -> 2029 | H5: =G5+1 -> 2030 | I5: =H5+1 -> 2031 | J5: =I5+1 -> 2032 | K5: =J5+1 -> 2033 | L5: =K5+1 -> 2034 | M5: =L5+1 -> 2035 | N5: =M5+1 -> 2036
A7: # | B7: Free Cash Flow to Firm (FCFF)
B9: EBITDA | E9: ='3 - Statement Model'!M16 -> 1121.1399 | F9: ='3 - Statement Model'!N16 -> 1265.6424 | G9: ='3 - Statement Model'!O16 -> 1427.3633 | H9: ='3 - Statement Model'!P16 -> 1608.1627 | I9: ='3 - Statement Model'!Q16 -> 1810.0765 | J9: ='3 - Statement Model'!R16 -> 2035.3304 | K9: ='3 - Statement Model'!S16 -> 2286.3545 | L9: ='3 - Statement Model'!T16 -> 2565.7978 | ... N9: ='3 - Statement Model'!V16 -> 3221.7298
B10: Less: Depreciation & Amortization | E10: ='3 - Statement Model'!M19 -> 196.19948 | F10: ='3 - Statement Model'!N19 -> 221.48742 | G10: ='3 - Statement Model'!O19 -> 249.78858 | H10: ='3 - Statement Model'!P19 -> 281.42847 | I10: ='3 - Statement Model'!Q19 -> 316.76338 | J10: ='3 - Statement Model'!R19 -> 356.18282 | K10: ='3 - Statement Model'!S19 -> 400.11204 | L10: ='3 - Statement Model'!T19 -> 449.01462 | ... N10: ='3 - Statement Model'!V19 -> 563.80271
B11: EBIT | E11: =E9-E10 -> 924.94041 | F11: =F9-F10 -> 1044.155 | G11: =G9-G10 -> 1177.5748 | H11: =H9-H10 -> 1326.7342 | I11: =I9-I10 -> 1493.3131 | J11: =J9-J10 -> 1679.1476 | K11: =K9-K10 -> 1886.2425 | L11: =L9-L10 -> 2116.7832 | ... N11: =N9-N10 -> 2657.9271
B12: Less: Tax | E12: ='3 - Statement Model'!M29 -> 229.8913 | F12: ='3 - Statement Model'!N29 -> 260.67593 | G12: ='3 - Statement Model'!O29 -> 293.97401 | H12: ='3 - Statement Model'!P29 -> 331.19885 | I12: ='3 - Statement Model'!Q29 -> 372.76932 | J12: ='3 - Statement Model'!R29 -> 419.14332 | K12: ='3 - Statement Model'!S29 -> 470.82069 | L12: ='3 - Statement Model'!T29 -> 528.34636 | ... N12: ='3 - Statement Model'!V29 -> 663.36711
B13: EBIT (1-T)/NOPAT | E13: =E11-E12 -> 695.04912 | F13: =F11-F12 -> 783.47903 | G13: =G11-G12 -> 883.60075 | H13: =H11-H12 -> 995.53538 | I13: =I11-I12 -> 1120.5438 | J13: =J11-J12 -> 1260.0043 | K13: =K11-K12 -> 1415.4218 | L13: =L11-L12 -> 1588.4369 | ... N13: =N11-N12 -> 1994.56
B14: Add: Depreciation & Amortization | E14: =E10 -> 196.19948 | F14: =F10 -> 221.48742 | G14: =G10 -> 249.78858 | H14: =H10 -> 281.42847 | I14: =I10 -> 316.76338 | J14: =J10 -> 356.18282 | K14: =K10 -> 400.11204 | L14: =L10 -> 449.01462 | ... N14: =N10 -> 563.80271
B15: Cash NOPAT | E15: =E13+E14 -> 891.2486 | F15: =F13+F14 -> 1004.9664 | G15: =G13+G14 -> 1133.3893 | H15: =H13+H14 -> 1276.9639 | I15: =I13+I14 -> 1437.3071 | J15: =J13+J14 -> 1616.1871 | K15: =K13+K14 -> 1815.5338 | L15: =L13+L14 -> 2037.4515 | ... N15: =N13+N14 -> 2558.3627
B16: Less: Reinvestments
B17: Change in Operating Working Capital | E17: =Schedule!E175 -> -764.07485 | F17: =Schedule!F175 -> 77.199953 | G17: =Schedule!G175 -> 86.398874 | H17: =Schedule!H175 -> -28.977431 | I17: =Schedule!I175 -> 92.105866 | J17: =Schedule!J175 -> 102.75283 | K17: =Schedule!K175 -> 114.50825 | L17: =Schedule!L175 -> -6.0899854 | ... N17: =Schedule!N175 -> 139.4927
B18: Capex during the Year | E18: =-'3 - Statement Model'!M96 -> 320.92446 | F18: =-'3 - Statement Model'!N96 -> 397.75552 | G18: =-'3 - Statement Model'!O96 -> 448.42412 | H18: =-'3 - Statement Model'!P96 -> 545.2528 | I18: =-'3 - Statement Model'!Q96 -> 613.51407 | J18: =-'3 - Statement Model'!R96 -> 689.63913 | K18: =-'3 - Statement Model'!S96 -> 688.70493 | L18: =-'3 - Statement Model'!T96 -> 772.59729 | ... N18: =-'3 - Statement Model'!V96 -> 768.03737
B19: Free Cash Flow to Firm | E19: =E15-E17-E18 -> 1334.399 | F19: =F15-F17-F18 -> 530.01097 | G19: =G15-G17-G18 -> 598.56634 | H19: =H15-H17-H18 -> 760.68848 | I19: =I15-I17-I18 -> 731.6872 | J19: =J15-J17-J18 -> 823.79514 | K19: =K15-K17-K18 -> 1012.3206 | L19: =L15-L17-L18 -> 1270.9442 | ... N19: =N15-N17-N18 -> 1650.8326
U20: Yes
B21: Discount Period (Years) | C21: Mid Year? | D21: Yes | E21: =IF(D21="Yes",(F5-E5)/2,(F5-E5)) -> 0.5 | F21: =E21+1 -> 1.5 | G21: =F21+1 -> 2.5 | H21: =G21+1 -> 3.5 | I21: =H21+1 -> 4.5 | J21: =I21+1 -> 5.5 | K21: =J21+1 -> 6.5 | L21: =K21+1 -> 7.5 | M21: =L21+1 -> 8.5 | N21: =M21+1 -> 9.5 | U21: No
B22: Discount Rate (WACC) | C22: 0.14
B23: Present Value Factor | E23: =1/(1+$C$22)^E21 -> 0.93658581 | F23: =1/(1+$C$22)^F21 -> 0.8215665 | G23: =1/(1+$C$22)^G21 -> 0.72067237 | H23: =1/(1+$C$22)^H21 -> 0.63216875 | I23: =1/(1+$C$22)^I21 -> 0.55453399 | J23: =1/(1+$C$22)^J21 -> 0.48643332 | K23: =1/(1+$C$22)^K21 -> 0.4266959 | L23: =1/(1+$C$22)^L21 -> 0.37429465 | ... N23: =1/(1+$C$22)^N21 -> 0.28800758
B25: Present Value of Free Cash Flow to Firm | E25: =E19*E23 -> 1249.7792 | F25: =F19*F23 -> 435.43926 | G25: =G19*G23 -> 431.37022 | H25: =H19*H23 -> 480.88349 | I25: =I19*I23 -> 405.74542 | J25: =J19*J23 -> 400.72141 | K25: =K19*K23 -> 431.95306 | L25: =L19*L23 -> 475.7076 | ... N25: =N19*N23 -> 475.4523
A27: # | B27: DCF Calculation - Perpetuity Growth
B29: Perpetual Growth Rate | C29: 0.05
B30: Terminal Year FCFF x (1+PGR) | C30: =N19*(1+C29) -> 1733.3742 | K30: Terminal Growth Rate
B31: Terminal Value | C31: =C30/(C22-C29) -> 19259.714 | G31: =C39 -> 11496.897 | H31: 0.04 | I31: 0.05 | J31: 0.06 | K31: 0.07 | L31: 0.08
B32: PV of Terminal Value | C32: =C31*N23 -> 5546.9435 | G32: 0.12 | H32: 13692.215 | I32: 14817.239 | J32: 16317.271 | K32: 18417.316 | L32: 21567.383
B33: Present Value of FCFFs | C33: =SUM(E25:N25) -> 5246.9339 | F33: WACC | G33: 0.13 | H33: 12131.239 | I33: 12942.58 | J33: 13985.734 | K33: 15376.605 | L33: 17323.825
B34: Enterprise Value | C34: =SUM(C32:C33) -> 10793.877 | G34: 0.14 | H34: 10894.658 | I34: 11496.897 | J34: 12249.697 | K34: 13217.582 | L34: 14508.095
B35: Less: Debt | C35: ='3 - Statement Model'!L46+'3 - Statement Model'!L53 -> 626.8 | G35: 0.15 | H35: 9893.1301 | I35: 10350.617 | J35: 10909.768 | K35: 11608.706 | L35: 12507.341
B36: Add: Cash | C36: ='3 - Statement Model'!L77 -> 402.07 | G36: 0.16 | H36: 9067.1624 | I36: 9421.3523 | J36: 9846.3802 | K36: 10365.859 | L36: 11015.207
B37: Less: Minority Interest | C37: ='3 - Statement Model'!L43 -> 2.45
B38: Add: Non Operating Assets | C38: ='3 - Statement Model'!L67+'3 - Statement Model'!L70+'3 - Statement Model'!L74 -> 930.2
B39: Equity Value | C39: =C34-C35-C37+C36+C38 -> 11496.897
B40: Less: Value of Option | C40: ='Option value'!E28 -> 9.8386967
B41: Equity Value for Shareholders | C41: =C39-C40 -> 11487.059
B42: Divide: No of shares outstanding | C42: ='Option value'!E10 -> 20.6
B43: Equity Value/Share | C43: =C41/C42 -> 557.62421
A45: # | B45: DCF Calculation - Exit Multiple
B47: Exit Multiple - EV/EBITDA | C47: ='Relative Valuation'!AC9 -> 33.215777
B48: Terminal Year EBITDA | C48: ='3 - Statement Model'!V16 -> 3221.7298 | K48: Terminal Growth Rate
B49: Terminal Value | C49: =C47*C48 -> 107012.26 | G49: =C57 -> 36770.295 | H49: 31 | I49: 32 | J49: 33 | K49: 34 | L49: 35
B50: PV of Terminal Value | C50: =C49*N23 -> 30820.341 | G50: 0.12 | H50: 40410.941 | I50: 41508.727 | J50: 42606.514 | K50: 43704.3 | L50: 44802.087
B51: Present Value of FCFFs | C51: =C33 -> 5246.9339 | F51: WACC | G51: 0.13 | H51: 37433.062 | I51: 38441.953 | J51: 39450.843 | K51: 40459.733 | L51: 41468.623
B52: Enterprise Value | C52: =SUM(C50:C51) -> 36067.275 | G52: 0.14 | H52: 34714.314 | I52: 35642.197 | J52: 36570.079 | K52: 37497.962 | L52: 38425.844
B53: Less: Debt | C53: =C35 -> 626.8 | G53: 0.15 | H53: 32229.964 | I53: 33083.967 | J53: 33937.971 | K53: 34791.974 | L53: 35645.978
B54: Add: Cash | C54: =C36 -> 402.07 | G54: 0.16 | H54: 29957.834 | I54: 30744.405 | J54: 31530.977 | K54: 32317.549 | L54: 33104.12
B55: Less: Minority Interest | C55: =C37 -> 2.45
B56: Add: Non Operating Assets | C56: =C38 -> 930.2
B57: Equity Value | C57: =C52-C53-C55+C54+C56 -> 36770.295
B58: Less: Value of Option | C58: =C40 -> 9.8386967
B59: Equity Value for Shareholders | C59: =C57-C58 -> 36760.457
B60: Divide: No of shares outstanding | C60: =C42 -> 20.6
B61: Equity Value/Share | C61: =C59/C60 -> 1784.4882

Sheet WACC Analysis
B2: Weighted Average Cost of Capital - Blue Star Ltd
B4: Particulars | D4: Low | E4: Mid | F4: High | H4: Risk Free Rate
B6: Risk Free Rate | D6: ='Input Sheet'!C10-'Input Sheet'!C12 -> 0.0477 | E6: =D6 -> 0.0477 | F6: =E6 -> 0.0477 | H6: ="We have considered "&TEXT(E6,"0.00%")&" as the risk free rate in estimation of cost of equity of "&TEXT(E11,"0.00%")&". The risk free rate of India is calculated by considering local currency 10 years government bond yield adjusted for default spread of India." -> We have considered 4.77% as the risk free rate in estimation of cost of equity of 7.74%. The risk free rate of India is calculated by considering local currency 10 years government bond yield adjusted for default spread of India.
B7: Equity Risk Premium | D7: ='Input Sheet'!C13+'Input Sheet'!C12 -> 0.0627 | E7: =D7 -> 0.0627 | F7: =E7 -> 0.0627
B8: Asset Beta | D8: =E8-'Input Sheet'!C15 -> 0.35 | E8: ='Input Sheet'!C14 -> 0.4 | F8: =E8+'Input Sheet'!C15 -> 0.45
B9: D/E Ratio | D9: ='Input Sheet'!C16 -> 0.18266543 | E9: =D9 -> 0.18266543 | F9: =E9 -> 0.18266543
B10: Equity Beta | D10: =D8*(1+(D9*(1-'Input Sheet'!C18))) -> 0.39787296 | E10: =E8*(1+(E9*(1-'Input Sheet'!D18))) -> 0.47306617 | F10: =F8*(1+(F9*(1-'Input Sheet'!E18))) -> 0.53219945 | H10: Asset Beta
B11: CAPM Cost of Equity | D11: =D6+D7*D10 -> 0.072646634 | E11: =E6+E7*E10 -> 0.077361249 | F11: =F6+F7*F10 -> 0.081068905 | H11: ="We have estimated an asset beta range of "&TEXT(D8,"0.00")&" to "&TEXT(F8,"0.00")&", with a mid point of "&TEXT(E8,"0.00")&" based on observed median of 5 year monthly asset beta of benchmark listed companies adjusted for blume effect." -> We have estimated an asset beta range of 0.35 to 0.45, with a mid point of 0.40 based on observed median of 5 year monthly asset beta of benchmark listed companies adjusted for blume effect.
B13: Small Size Premium | D13: =7.6% -> 0.076 | E13: =D13 -> 0.076 | F13: =E13 -> 0.076
B14: Asset Specific Premium | D14: ='Input Sheet'!C25 -> 0 | E14: =D14 -> 0 | F14: =E14 -> 0
B15: Modified Cost of Equity | D15: =D11+D13+D14 -> 0.14864663 | E15: =E11+E13+E14 -> 0.15336125 | F15: =F11+F13+F14 -> 0.15706891 | H15: Equity Risk Premium (ERP)
H16: ="An ERP of "&TEXT(E7,"0.00%")&" has been adopted based on US Implied Equity Risk Premium, relative equity volatility of ICE BoFA Public Sector Issuers Emerging Mkts Index, S&P Emerging BMI Index and country risk premium of India." -> An ERP of 6.27% has been adopted based on US Implied Equity Risk Premium, relative equity volatility of ICE BoFA Public Sector Issuers Emerging Mkts Index, S&P Emerging BMI Index and country risk premium of India.
B17: Pre Tax Cost of Debt | D17: ='Input Sheet'!C10+(IF('Input Sheet'!C19="No",'Input Sheet'!C23,VLOOKUP('Input Sheet'!C21,'Damodaran Data'!I4:J19,2,FALSE))) -> 0.0726 | E17: =D17 -> 0.0726 | F17: =E17 -> 0.0726
B18: Marginal Tax Rate | D18: ='Input Sheet'!C18 -> 0.2512 | E18: =D18 -> 0.2512 | F18: =E18 -> 0.2512
B19: Post Tax Cost of Debt | D19: =D17*(1-D18) -> 0.05436288 | E19: =E17*(1-E18) -> 0.05436288 | F19: =F17*(1-F18) -> 0.05436288
H20: Cost of Debt
B21: Capital Gearing (D/D+E) | D21: ='Input Sheet'!C17 -> 0.15445233 | E21: =D21 -> 0.15445233 | F21: =E21 -> 0.15445233 | H21: For the purpose of assessing the cost of debt we have used country's risk free rate and country's deafult spread and corporate default spread based on company's debt rating and interest coverage ratio
B22: Weighted Average Cost of Capital | D22: =(D19*D21)+(D15*(1-D21)) -> 0.13408429 | E22: =(E19*E21)+(E15*(1-E21)) -> 0.13807072 | F22: =(F19*F21)+(F15*(1-F21)) -> 0.14120572
B23: Weighted Average Cost of Capital (Rounded) | D23: =ROUNDUP(D22,2) -> 0.14 | E23: =ROUNDUP(E22,2) -> 0.14 | F23: =ROUNDUP(F22,2) -> 0.15
B25: 1. Tax rate is considered the Marginal Tax Rate of India 2. Asset Beta is considered the median of the 5-year beta of comps adjusted for the Blume effect 3. Equity Beta = Asset Beta * (1+(1-Tax Rate%)*Debt/Equity) | H25: Small Size Premium
H26: Empirically, small-sized assets have exceeded the returns compared to large-sized assets. We have used the study on size premium conducted by Incwert, which is based on the difference between actual returns and CAPM expected returns arranged on a decile basis by market capitalization of Indian companies.
B30: Blue Star Ltd
A31: # | B31: Beta Analysis - 2 Years Weekly | M31: 0.2512
B32: Comparable Company | D32: Ticker | E32: No of weekly Observations | F32: Market Cap (Crores) | G32: Asset Beta | H32: 2 Years Avg D/E | I32: Equity Beta | J32: 2 Years avg D/D+E | L32: Considered? | M32: Narrow set
N33: Y
B34: Voltas | D34: VOLTAS.NS | E34: 104 | F34: 44917.82 | G34: =I34/(1+(H34*(1-$M$31))) -> 1.1608067 | H34: 0.0681 | I34: 1.22 | J34: 0.0638 | L34: Y | M34: =IF(L34="Y","TRUE","FALSE") -> TRUE | N34: N
B35: Amber Enterprise | D35: AMBER.NS | E35: =E34 -> 104 | F35: 28014.38 | G35: =I35/(1+(H35*(1-$M$31))) -> 0.62808319 | H35: 0.508 | I35: 0.867 | J35: 0.3364 | L35: N | M35: =IF(L35="Y","TRUE","FALSE") -> FALSE
B36: V-Guard Industries | D36: VGUARD.NS | E36: =E35 -> 104 | F36: 13602.88 | G36: =I36/(1+(H36*(1-$M$31))) -> 0.66884816 | H36: 0.0622 | I36: 0.7 | J36: 0.0586 | L36: Y | M36: =IF(L36="Y","TRUE","FALSE") -> TRUE
B37: Crompton Gr. Con | D37: CROMPTON.NS | E37: =E36 -> 104 | F37: 17826.82 | G37: =I37/(1+(H37*(1-$M$31))) -> 0.68427077 | H37: 0.0912 | I37: 0.731 | J37: 0.0827 | L37: Y | M37: =IF(L37="Y","TRUE","FALSE") -> TRUE
B38: Carrier | D38: CARR | E38: =E37 -> 104 | F38: 5772 | G38: =I38/(1+(H38*(1-$M$31))) -> 0.79640584 | H38: 0.878 | I38: 1.32 | J38: 0.5072 | L38: N | M38: =IF(L38="Y","TRUE","FALSE") -> FALSE
B39: BOSCH-HCIL | D39: BOSCH-HCIL.NS | E39: =E38 -> 104 | F39: 3828 | G39: =I39/(1+(H39*(1-$M$31))) -> 0.70714182 | H39: 0.0545 | I39: 0.736 | J39: 0.0516 | L39: Y | M39: =IF(L39="Y","TRUE","FALSE") -> TRUE
B42: Median - Broad Set | G42: =MEDIAN(G34:G39) -> 0.6957063 | H42: =MEDIAN(H34:H39) -> 0.07965 | I42: =MEDIAN(I34:I39) -> 0.8015 | J42: =MEDIAN(J34:J39) -> 0.07325
B43: Average: Broad Set | G43: =AVERAGE(G34:G39) -> 0.77425941 | H43: =AVERAGE(H34:H39) -> 0.277 | I43: =AVERAGE(I34:I39) -> 0.929 | J43: =AVERAGE(J34:J39) -> 0.18338333
B45: Median - Considered Set | G45: {=MEDIAN(IF($M$34:$M$39,G34:G39))} -> 0.6957063 | H45: {=MEDIAN(IF($M$34:$M$39,H34:H39))} -> 0.06515 | I45: {=MEDIAN(IF($M$34:$M$39,I34:I39))} -> 0.7335 | J45: {=MEDIAN(IF($M$34:$M$39,J34:J39))} -> 0.0612
B46: Average: Considered Set | G46: {=AVERAGE(IF($M$34:$M$39,G34:G39))} -> 0.80526685 | H46: {=AVERAGE(IF($M$34:$M$39,H34:H39))} -> 0.069 | I46: {=AVERAGE(IF($M$34:$M$39,I34:I39))} -> 0.84675 | J46: {=AVERAGE(IF($M$34:$M$39,J34:J39))} -> 0.064175
A49: # | B49: Beta Analysis - 5 Years Monthly | M49: 0.2512
B50: Comparable Company | D50: Ticker | E50: No of Monthly Observations | F50: Market Cap (Crores) | G50: Asset Beta | H50: 5 Years Avg D/E | I50: Equity Beta | J50: 5 Years avg D/D+E | L50: Considered? | M50: Narrow set
B52: Voltas | D52: VOLTAS.NS | E52: 60 | F52: 44917.82 | G52: =I52/(1+(H52*(1-$M$49))) -> 0.11612194 | H52: 0.0446 | I52: 0.12 | J52: 0.0427 | L52: Y | M52: =IF(L52="Y","TRUE","FALSE") -> TRUE
B53: Amber Enterprise | D53: AMBER.NS | E53: =E52 -> 60 | F53: 28014.38 | G53: =I53/(1+(H53*(1-$M$49))) -> 0.13118035 | H53: 0.3952 | I53: 0.17 | J53: 0.2832 | L53: N | M53: =IF(L53="Y","TRUE","FALSE") -> FALSE
B54: V-Guard Industries | D54: VGUARD.NS | E54: =E53 -> 60 | F54: 13602.88 | G54: =I54/(1+(H54*(1-$M$49))) -> 0.018091264 | H54: 0.1409 | I54: 0.02 | J54: 0.1235 | L54: Y | M54: =IF(L54="Y","TRUE","FALSE") -> TRUE
B55: Crompton Gr. Con | D55: CROMPTON.NS | E55: =E54 -> 60 | F55: 17826.82 | G55: =I55/(1+(H55*(1-$M$49))) -> 0.22875622 | H55: 0.1824 | I55: 0.26 | J55: 0.1543 | L55: Y | M55: =IF(L55="Y","TRUE","FALSE") -> TRUE
B56: Carrier | D56: CARRIER | E56: =E55 -> 60 | F56: 5772 | G56: =I56/(1+(H56*(1-$M$49))) -> 0.70682955 | H56: 1.1963 | I56: 1.34 | J56: 0.6113 | L56: N | M56: =IF(L56="Y","TRUE","FALSE") -> FALSE
B57: BOSCH-HCIL | D57: BOSCH-HCIL.NS | E57: =E56 -> 60 | F57: 3828 | G57: =I57/(1+(H57*(1-$M$49))) -> 0.55634152 | H57: 0.1048 | I57: 0.6 | J57: 0.0948 | L57: Y | M57: =IF(L57="Y","TRUE","FALSE") -> TRUE
B60: Median - Broad Set | G60: =MEDIAN(G52:G57) -> 0.17996829 | H60: =MEDIAN(H52:H57) -> 0.16165 | I60: =MEDIAN(I52:I57) -> 0.215 | J60: =MEDIAN(J52:J57) -> 0.1389
B61: Average: Broad Set | G61: =AVERAGE(G52:G57) -> 0.29288681 | H61: =AVERAGE(H52:H57) -> 0.34403333 | I61: =AVERAGE(I52:I57) -> 0.41833333 | J61: =AVERAGE(J52:J57) -> 0.2183
B63: Median - Considered Set | G63: {=MEDIAN(IF($M$52:$M$57,G52:G57))} -> 0.17243908 | H63: {=MEDIAN(IF($M$52:$M$57,H52:H57))} -> 0.12285 | I63: {=MEDIAN(IF($M$52:$M$57,I52:I57))} -> 0.19 | J63: {=MEDIAN(IF($M$52:$M$57,J52:J57))} -> 0.10915
B64: Average: Considered Set | G64: {=MEDIAN(IF($M$52:$M$57,G53:G58))} -> 0.17996829 | H64: {=MEDIAN(IF($M$52:$M$57,H53:H58))} -> 0.2888 | I64: {=MEDIAN(IF($M$52:$M$57,I53:I58))} -> 0.215 | J64: {=MEDIAN(IF($M$52:$M$57,J53:J58))} -> 0.21875
A67: # | B67: Blume Beta Analysis - 5 Years Monthly | D67: 2/3* Beta + 1/3*Market Beta | M67: 0.2512
B68: Comparable Company | D68: Ticker | E68: No of Monthly Observations | F68: Market Cap (Crores) | G68: Asset Beta | H68: 5 Years Avg D/E | I68: Equity Beta | J68: 5 Years avg D/D+E | L68: Considered? | M68: Narrow set
B70: Voltas | D70: VOLTAS.NS | E70: 60 | F70: 44917.82 | G70: =I70/(1+(H70*(1-$M$67))) -> 0.39678866 | H70: 0.0446 | I70: =0.33+0.667*I52 -> 0.41004 | J70: 0.0427 | L70: Y | M70: =IF(L70="Y","TRUE","FALSE") -> TRUE
B71: Amber Enterprise | D71: AMBER.NS | E71: =E70 -> 60 | F71: 28014.38 | G71: =I71/(1+(H71*(1-$M$67))) -> 0.34214151 | H71: 0.3952 | I71: =0.33+0.667*I53 -> 0.44339 | J71: 0.2832 | L71: N | M71: =IF(L71="Y","TRUE","FALSE") -> FALSE
B72: V-Guard Industries | D72: VGUARD.NS | E72: =E71 -> 60 | F72: 13602.88 | G72: =I72/(1+(H72*(1-$M$67))) -> 0.31057274 | H72: 0.1409 | I72: =0.33+0.667*I54 -> 0.34334 | J72: 0.1235 | L72: Y | M72: =IF(L72="Y","TRUE","FALSE") -> TRUE
B73: Crompton Gr. Con | D73: CROMPTON.NS | E73: =E72 -> 60 | F73: 17826.82 | G73: =I73/(1+(H73*(1-$M$67))) -> 0.44292483 | H73: 0.1824 | I73: =0.33+0.667*I55 -> 0.50342 | J73: 0.1543 | L73: Y | M73: =IF(L73="Y","TRUE","FALSE") -> TRUE
B74: Carrier | D74: CARRIER | E74: =E73 -> 60 | F74: 5772 | G74: =I74/(1+(H74*(1-$M$67))) -> 0.64552528 | H74: 1.1963 | I74: =0.33+0.667*I56 -> 1.22378 | J74: 0.6113 | L74: N | M74: =IF(L74="Y","TRUE","FALSE") -> FALSE
B75: BOSCH-HCIL | D75: BOSCH-HCIL.NS | E75: =E74 -> 60 | F75: 3828 | G75: =I75/(1+(H75*(1-$M$67))) -> 0.67706763 | H75: 0.1048 | I75: =0.33+0.667*I57 -> 0.7302 | J75: 0.0948 | L75: Y | M75: =IF(L75="Y","TRUE","FALSE") -> TRUE
B78: Median - Broad Set | G78: =MEDIAN(G70:G75) -> 0.41985674 | H78: =MEDIAN(H70:H75) -> 0.16165 | I78: =MEDIAN(I70:I75) -> 0.473405 | J78: =MEDIAN(J70:J75) -> 0.1389
B79: Average: Broad Set | G79: =AVERAGE(G70:G75) -> 0.46917011 | H79: =AVERAGE(H70:H75) -> 0.34403333 | I79: =AVERAGE(I70:I75) -> 0.60902833 | J79: =AVERAGE(J70:J75) -> 0.2183
B81: Median - Considered Set | G81: {=MEDIAN(IF($M$70:$M$75,G70:G75))} -> 0.41985674 | H81: {=MEDIAN(IF($M$70:$M$75,H70:H75))} -> 0.12285 | I81: {=MEDIAN(IF($M$70:$M$75,I70:I75))} -> 0.45673 | J81: {=MEDIAN(IF($M$70:$M$75,J70:J75))} -> 0.10915
B82: Average: Considered Set | G82: {=AVERAGE(IF($M$70:$M$75,G70:G75))} -> 0.45683846 | H82: {=AVERAGE(IF($M$70:$M$75,H70:H75))} -> 0.118175 | I82: {=AVERAGE(IF($M$70:$M$75,I70:I75))} -> 0.49675 | J82: {=AVERAGE(IF($M$70:$M$75,J70:J75))} -> 0.103825
B84: We are taking 0.40 as asset beta of HVAC unit | D84: (median basis)
B87: Source: Investing.com, Topstockresearch.com, Stockanalysis.com, Damodaran

Sheet DCF Simulation
B2: MONTECARLO SIMULATION - BLUESTAR LTD - 10000 ITERATIONS
B4: Simulation Parameters
B5: Parameter | C5: Distribution | D5: Min | E5: Max | F5: Mean | G5: Standard deviation
B6: Revenue Growth | C6: Normal | D6: 0.036 | E6: 0.418 | F6: =(E6+D6)/2 -> 0.227 | G6: =(E6-D6)/4 -> 0.0955
B7: EBITDA Margin | C7: Normal | D7: 0.051 | E7: 0.075 | F7: =(E7+D7)/2 -> 0.063 | G7: =(E7-D7)/4 -> 0.006
B8: WACC | C8: Normal | D8: 0.14 | E8: 0.15 | F8: =(E8+D8)/2 -> 0.145 | G8: =(E8-D8)/4 -> 0.0025
B9: PGR | C9: Normal | D9: 0.02 | E9: 0.06 | F9: =(E9+D9)/2 -> 0.04 | G9: =(E9-D9)/4 -> 0.01
B11: Engine Inputs
B12: Base Revenue | C12: ='3 - Statement Model'!L8 -> 12401.99
B13: Net Equity Bridge | C13: ='Historical Data'!L69+'Historical Data'!L72+'Historical Data'!L76+'Historical Data'!L79-'Historical Data'!L55-'Historical Data'!L48-'Historical Data'!L45-'Option value'!E28 -> 693.1813
B14: Shares Outstanding | C14: =20.6 -> 20.6
B15: CMP | C15: 1605
B17: Simulation Results | L17: Summary Statistics
B18: # | C18: Revenue Growth | D18: EBITDA Margin | E18: WACC | F18: PGR | G18: Enterprise Value | H18: Equity Value | I18: Price/Share | L18: Current Market Price | M18: 1605
B19: 1 | C19: =_xlfn.NORM.INV(RAND(),$F$6,$G$6) -> 0.1330754 | D19: =_xlfn.NORM.INV(RAND(),$F$7,$G$7) -> 0.061140308 | E19: =_xlfn.NORM.INV(RAND(),$F$8,$G$8) -> 0.1446563 | F19: =_xlfn.NORM.INV(RAND(),$F$9,$G$9) -> 0.047061203 | G19: =IF(E19>F19,($C$12*(1+C19)*D19)/(E19-F19),0) -> 8803.387 | H19: =G19+$C$13 -> 9496.5683 | I19: =H19/'Option value'!$E$10 -> 460.99846 | L19: Mean Price | M19: =AVERAGE(I19:I10018) -> 483.50313
B20: =B19+1 -> 2 | C20: =_xlfn.NORM.INV(RAND(),$F$6,$G$6) -> 0.36573378 | D20: =_xlfn.NORM.INV(RAND(),$F$7,$G$7) -> 0.061229803 | E20: =_xlfn.NORM.INV(RAND(),$F$8,$G$8) -> 0.14324758 | F20: =RAND()*($E$9-$D$9)+$D$9 -> 0.044505152 | G20: =IF(E20>F20,($C$12*(1+C20)*D20)/(E20-F20),0) -> 10503.076 | H20: =G20+$C$13 -> 11196.257 | I20: =H20/'Option value'!$E$10 -> 543.50762 | L20: Median Price | M20: =MEDIAN(I19:I10018) -> 477.69884
B21: =B20+1 -> 3 | C21: =_xlfn.NORM.INV(RAND(),$F$6,$G$6) -> 0.2862741 | D21: =_xlfn.NORM.INV(RAND(),$F$7,$G$7) -> 0.065751898 | E21: =_xlfn.NORM.INV(RAND(),$F$8,$G$8) -> 0.14662394 | F21: =RAND()*($E$9-$D$9)+$D$9 -> 0.05888217 | G21: =IF(E21>F21,($C$12*(1+C21)*D21)/(E21-F21),0) -> 11954.373 | H21: =G21+$C$13 -> 12647.554 | I21: =H21/'Option value'!$E$10 -> 613.95894 | L21: Standard Deviation (In Rs) | M21: =_xlfn.STDEV.P(I19:I10018) -> 75.981751
B22: =B21+1 -> 4 | C22: =_xlfn.NORM.INV(RAND(),$F$6,$G$6) -> 0.44680299 | D22: =_xlfn.NORM.INV(RAND(),$F$7,$G$7) -> 0.074306468 | E22: =_xlfn.NORM.INV(RAND(),$F$8,$G$8) -> 0.14252201 | F22: =RAND()*($E$9-$D$9)+$D$9 -> 0.032298002 | G22: =IF(E22>F22,($C$12*(1+C22)*D22)/(E22-F22),0) -> 12096.263 | H22: =G22+$C$13 -> 12789.444 | I22: =H22/'Option value'!$E$10 -> 620.84679 | L22: Minimum Price (In Rs) | M22: =MIN(I19:I10018) -> 265.22395
B23: =B22+1 -> 5 | C23: =_xlfn.NORM.INV(RAND(),$F$6,$G$6) -> 0.19269803 | D23: =_xlfn.NORM.INV(RAND(),$F$7,$G$7) -> 0.05832474 | E23: =_xlfn.NORM.INV(RAND(),$F$8,$G$8) -> 0.14300615 | F23: =RAND()*($E$9-$D$9)+$D$9 -> 0.05380842 | G23: =IF(E23>F23,($C$12*(1+C23)*D23)/(E23-F23),0) -> 9672.1028 | H23: =G23+$C$13 -> 10365.284 | I23: =H23/'Option value'!$E$10 -> 503.16913 | L23: Maximum Price (In Rs) | M23: =MAX(I19:I10018) -> 817.96531
B24: =B23+1 -> 6 | C24: =_xlfn.NORM.INV(RAND(),$F$6,$G$6) -> 0.28469563 | D24: =_xlfn.NORM.INV(RAND(),$F$7,$G$7) -> 0.060786093 | E24: =_xlfn.NORM.INV(RAND(),$F$8,$G$8) -> 0.1482226 | F24: =RAND()*($E$9-$D$9)+$D$9 -> 0.04750646 | G24: =IF(E24>F24,($C$12*(1+C24)*D24)/(E24-F24),0) -> 9616.0515 | H24: =G24+$C$13 -> 10309.233 | I24: =H24/'Option value'!$E$10 -> 500.4482 | L24: 25th Percentile | M24: =PERCENTILE(I19:I10018,0.25) -> 428.35215
B25: =B24+1 -> 7 | C25: =_xlfn.NORM.INV(RAND(),$F$6,$G$6) -> 0.29153556 | D25: =_xlfn.NORM.INV(RAND(),$F$7,$G$7) -> 0.060641883 | E25: =_xlfn.NORM.INV(RAND(),$F$8,$G$8) -> 0.14280051 | F25: =RAND()*($E$9-$D$9)+$D$9 -> 0.055257871 | G25: =IF(E25>F25,($C$12*(1+C25)*D25)/(E25-F25),0) -> 11095.6 | H25: =G25+$C$13 -> 11788.782 | I25: =H25/'Option value'!$E$10 -> 572.27096 | L25: 75th Percentile | M25: =PERCENTILE(I19:I10018,0.75) -> 531.56101
B26: =B25+1 -> 8 | C26: =_xlfn.NORM.INV(RAND(),$F$6,$G$6) -> 0.16938779 | D26: =_xlfn.NORM.INV(RAND(),$F$7,$G$7) -> 0.068313032 | E26: =_xlfn.NORM.INV(RAND(),$F$8,$G$8) -> 0.13970211 | F26: =RAND()*($E$9-$D$9)+$D$9 -> 0.036187177 | G26: =IF(E26>F26,($C$12*(1+C26)*D26)/(E26-F26),0) -> 9570.8496 | H26: =G26+$C$13 -> 10264.031 | I26: =H26/'Option value'!$E$10 -> 498.25393 | L26: 5th Percentile (Bear Case) | M26: =PERCENTILE(I19:I10018,0.05) -> 369.64191
B27: =B26+1 -> 9 | C27: =_xlfn.NORM.INV(RAND(),$F$6,$G$6) -> 0.21659069 | D27: =_xlfn.NORM.INV(RAND(),$F$7,$G$7) -> 0.050975218 | E27: =_xlfn.NORM.INV(RAND(),$F$8,$G$8) -> 0.13946404 | F27: =RAND()*($E$9-$D$9)+$D$9 -> 0.029745385 | G27: =IF(E27>F27,($C$12*(1+C27)*D27)/(E27-F27),0) -> 7009.9429 | H27: =G27+$C$13 -> 7703.1242 | I27: =H27/'Option value'!$E$10 -> 373.93807 | L27: 95th Percentile (Bull Case) | M27: =PERCENTILE(I19:I10018,0.95) -> 618.99034
B28: =B27+1 -> 10 | C28: =_xlfn.NORM.INV(RAND(),$F$6,$G$6) -> 0.45100349 | D28: =_xlfn.NORM.INV(RAND(),$F$7,$G$7) -> 0.063198128 | E28: =_xlfn.NORM.INV(RAND(),$F$8,$G$8) -> 0.14822325 | F28: =RAND()*($E$9-$D$9)+$D$9 -> 0.032486771 | G28: =IF(E28>F28,($C$12*(1+C28)*D28)/(E28-F28),0) -> 9826.3847 | H28: =G28+$C$13 -> 10519.566 | I28: =H28/'Option value'!$E$10 -> 510.65854 | L28: % above Current Market Price | M28: =COUNTIF(I19:I5018,">"&M18)/COUNTA(I19:I5018) -> 0
B29: =B28+1 -> 11 | C29: =_xlfn.NORM.INV(RAND(),$F$6,$G$6) -> 0.27635894 | D29: =_xlfn.NORM.INV(RAND(),$F$7,$G$7) -> 0.056959977 | E29: =_xlfn.NORM.INV(RAND(),$F$8,$G$8) -> 0.14357245 | F29: =RAND()*($E$9-$D$9)+$D$9 -> 0.031866404 | G29: =IF(E29>F29,($C$12*(1+C29)*D29)/(E29-F29),0) -> 8071.5571 | H29: =G29+$C$13 -> 8764.7384 | I29: =H29/'Option value'!$E$10 -> 425.47274 | L29: Mean Enterprise Value | M29: =AVERAGE(G19:G10018) -> 9266.9833
B30: =B29+1 -> 12 | C30: =_xlfn.NORM.INV(RAND(),$F$6,$G$6) -> 0.17529895 | D30: =_xlfn.NORM.INV(RAND(),$F$7,$G$7) -> 0.064987878 | E30: =_xlfn.NORM.INV(RAND(),$F$8,$G$8) -> 0.1465958 | F30: =RAND()*($E$9-$D$9)+$D$9 -> 0.045541421 | G30: =IF(E30>F30,($C$12*(1+C30)*D30)/(E30-F30),0) -> 9373.827 | H30: =G30+$C$13 -> 10067.008 | I30: =H30/'Option value'!$E$10 -> 488.68972 | L30: Median Enterprise Value | M30: =MEDIAN(G19:G10018) -> 9147.4147
B31: =B30+1 -> 13 | C31: =_xlfn.NORM.INV(RAND(),$F$6,$G$6) -> 0.2296504 | D31: =_xlfn.NORM.INV(RAND(),$F$7,$G$7) -> 0.055950173 | E31: =_xlfn.NORM.INV(RAND(),$F$8,$G$8) -> 0.14415313 | F31: =RAND()*($E$9-$D$9)+$D$9 -> 0.045920878 | G31: =IF(E31>F31,($C$12*(1+C31)*D31)/(E31-F31),0) -> 8686.0109 | H31: =G31+$C$13 -> 9379.1922 | I31: =H31/'Option value'!$E$10 -> 455.30059
B32: =B31+1 -> 14 | C32: =_xlfn.NORM.INV(RAND(),$F$6,$G$6) -> 0.27993073 | D32: =_xlfn.NORM.INV(RAND(),$F$7,$G$7) -> 0.059230271 | E32: =_xlfn.NORM.INV(RAND(),$F$8,$G$8) -> 0.14203121 | F32: =RAND()*($E$9-$D$9)+$D$9 -> 0.059559298 | G32: =IF(E32>F32,($C$12*(1+C32)*D32)/(E32-F32),0) -> 11400.279 | H32: =G32+$C$13 -> 12093.461 | I32: =H32/'Option value'!$E$10 -> 587.06119
B33: =B32+1 -> 15 | C33: =_xlfn.NORM.INV(RAND(),$F$6,$G$6) -> 0.20793646 | D33: =_xlfn.NORM.INV(RAND(),$F$7,$G$7) -> 0.06248715 | E33: =_xlfn.NORM.INV(RAND(),$F$8,$G$8) -> 0.14567846 | F33: =RAND()*($E$9-$D$9)+$D$9 -> 0.037657406 | G33: =IF(E33>F33,($C$12*(1+C33)*D33)/(E33-F33),0) -> 8665.9819 | H33: =G33+$C$13 -> 9359.1632 | I33: =H33/'Option value'!$E$10 -> 454.32831 | L33: Histogram (Rs 100 Bins)
B34: =B33+1 -> 16 | C34: =_xlfn.NORM.INV(RAND(),$F$6,$G$6) -> 0.26066931 | D34: =_xlfn.NORM.INV(RAND(),$F$7,$G$7) -> 0.0622998 | E34: =_xlfn.NORM.INV(RAND(),$F$8,$G$8) -> 0.14814756 | F34: =RAND()*($E$9-$D$9)+$D$9 -> 0.053184058 | G34: =IF(E34>F34,($C$12*(1+C34)*D34)/(E34-F34),0) -> 10257.051 | H34: =G34+$C$13 -> 10950.232 | I34: =H34/'Option value'!$E$10 -> 531.56466 | L34: Bin (<=) | M34: Count | N34: CMP
B35: =B34+1 -> 17 | C35: =_xlfn.NORM.INV(RAND(),$F$6,$G$6) -> 0.21027828 | D35: =_xlfn.NORM.INV(RAND(),$F$7,$G$7) -> 0.060096689 | E35: =_xlfn.NORM.INV(RAND(),$F$8,$G$8) -> 0.14436267 | F35: =RAND()*($E$9-$D$9)+$D$9 -> 0.033170778 | G35: =IF(E35>F35,($C$12*(1+C35)*D35)/(E35-F35),0) -> 8112.4879 | H35: =G35+$C$13 -> 8805.6692 | I35: =H35/'Option value'!$E$10 -> 427.45967 | L35: 200 | M35: {=FREQUENCY(I19:I10018,L35:L45)} -> 0 | N35: 1605
B36: =B35+1 -> 18 | C36: =_xlfn.NORM.INV(RAND(),$F$6,$G$6) -> 0.14479405 | D36: =_xlfn.NORM.INV(RAND(),$F$7,$G$7) -> 0.058794733 | E36: =_xlfn.NORM.INV(RAND(),$F$8,$G$8) -> 0.14724157 | F36: =RAND()*($E$9-$D$9)+$D$9 -> 0.058358951 | G36: =IF(E36>F36,($C$12*(1+C36)*D36)/(E36-F36),0) -> 9391.6162 | H36: =G36+$C$13 -> 10084.798 | I36: =H36/'Option value'!$E$10 -> 489.55328 | L36: =L35+100 -> 300 | M36: 9 | N36: =N35 -> 1605
B37: =B36+1 -> 19 | C37: =_xlfn.NORM.INV(RAND(),$F$6,$G$6) -> 0.15011579 | D37: =_xlfn.NORM.INV(RAND(),$F$7,$G$7) -> 0.057551168 | E37: =_xlfn.NORM.INV(RAND(),$F$8,$G$8) -> 0.14840247 | F37: =RAND()*($E$9-$D$9)+$D$9 -> 0.055550072 | G37: =IF(E37>F37,($C$12*(1+C37)*D37)/(E37-F37),0) -> 8840.8492 | H37: =G37+$C$13 -> 9534.0305 | I37: =H37/'Option value'!$E$10 -> 462.81701 | L37: =L36+100 -> 400 | M37: 1301 | N37: =N36 -> 1605
B38: =B37+1 -> 20 | C38: =_xlfn.NORM.INV(RAND(),$F$6,$G$6) -> 0.14106238 | D38: =_xlfn.NORM.INV(RAND(),$F$7,$G$7) -> 0.063883036 | E38: =_xlfn.NORM.INV(RAND(),$F$8,$G$8) -> 0.14085238 | F38: =RAND()*($E$9-$D$9)+$D$9 -> 0.035057113 | G38: =IF(E38>F38,($C$12*(1+C38)*D38)/(E38-F38),0) -> 8545.1573 | H38: =G38+$C$13 -> 9238.3386 | I38: =H38/'Option value'!$E$10 -> 448.46304 | L38: =L37+100 -> 500 | M38: 4828 | N38: =N37 -> 1605
B39: =B38+1 -> 21 | C39: =_xlfn.NORM.INV(RAND(),$F$6,$G$6) -> 0.19817948 | D39: =_xlfn.NORM.INV(RAND(),$F$7,$G$7) -> 0.079153024 | E39: =_xlfn.NORM.INV(RAND(),$F$8,$G$8) -> 0.1455566 | F39: =RAND()*($E$9-$D$9)+$D$9 -> 0.042811573 | G39: =IF(E39>F39,($C$12*(1+C39)*D39)/(E39-F39),0) -> 11447.745 | H39: =G39+$C$13 -> 12140.926 | I39: =H39/'Option value'!$E$10 -> 589.36535 | L39: =L38+100 -> 600 | M39: 3107 | N39: =N38 -> 1605
B40: =B39+1 -> 22 | C40: =_xlfn.NORM.INV(RAND(),$F$6,$G$6) -> 0.33008175 | D40: =_xlfn.NORM.INV(RAND(),$F$7,$G$7) -> 0.064856379 | E40: =_xlfn.NORM.INV(RAND(),$F$8,$G$8) -> 0.14375273 | F40: =RAND()*($E$9-$D$9)+$D$9 -> 0.042779715 | G40: =IF(E40>F40,($C$12*(1+C40)*D40)/(E40-F40),0) -> 10595.394 | H40: =G40+$C$13 -> 11288.575 | I40: =H40/'Option value'!$E$10 -> 547.98908 | L40: =L39+100 -> 700 | M40: 698 | N40: =N39 -> 1605
B41: =B40+1 -> 23 | C41: =_xlfn.NORM.INV(RAND(),$F$6,$G$6) -> 0.28091643 | D41: =_xlfn.NORM.INV(RAND(),$F$7,$G$7) -> 0.058575879 | E41: =_xlfn.NORM.INV(RAND(),$F$8,$G$8) -> 0.14730218 | F41: =RAND()*($E$9-$D$9)+$D$9 -> 0.028187714 | G41: =IF(E41>F41,($C$12*(1+C41)*D41)/(E41-F41),0) -> 7812.0766 | H41: =G41+$C$13 -> 8505.2579 | I41: =H41/'Option value'!$E$10 -> 412.87659 | L41: =L40+100 -> 800 | M41: 55 | N41: =N40 -> 1605
B42: =B41+1 -> 24 | C42: =_xlfn.NORM.INV(RAND(),$F$6,$G$6) -> 0.27838345 | D42: =_xlfn.NORM.INV(RAND(),$F$7,$G$7) -> 0.069338373 | E42: =_xlfn.NORM.INV(RAND(),$F$8,$G$8) -> 0.14595404 | F42: =RAND()*($E$9-$D$9)+$D$9 -> 0.047798803 | G42: =IF(E42>F42,($C$12*(1+C42)*D42)/(E42-F42),0) -> 11199.863 | H42: =G42+$C$13 -> 11893.044 | I42: =H42/'Option value'!$E$10 -> 577.33222 | L42: =L41+100 -> 900 | M42: 2 | N42: =N41 -> 1605
B43: =B42+1 -> 25 | C43: =_xlfn.NORM.INV(RAND(),$F$6,$G$6) -> 0.3418229 | D43: =_xlfn.NORM.INV(RAND(),$F$7,$G$7) -> 0.05880614 | E43: =_xlfn.NORM.INV(RAND(),$F$8,$G$8) -> 0.1442124 | F43: =RAND()*($E$9-$D$9)+$D$9 -> 0.055246959 | G43: =IF(E43>F43,($C$12*(1+C43)*D43)/(E43-F43),0) -> 10999.88 | H43: =G43+$C$13 -> 11693.061 | I43: =H43/'Option value'!$E$10 -> 567.62433 | L43: =L42+100 -> 1000 | M43: 0 | N43: =N42 -> 1605
B44: =B43+1 -> 26 | C44: =_xlfn.NORM.INV(RAND(),$F$6,$G$6) -> 0.29803507 | D44: =_xlfn.NORM.INV(RAND(),$F$7,$G$7) -> 0.06418382 | E44: =_xlfn.NORM.INV(RAND(),$F$8,$G$8) -> 0.14168807 | F44: =RAND()*($E$9-$D$9)+$D$9 -> 0.028162102 | G44: =IF(E44>F44,($C$12*(1+C44)*D44)/(E44-F44),0) -> 9101.3987 | H44: =G44+$C$13 -> 9794.58 | I44: =H44/'Option value'!$E$10 -> 475.46505 | L44: =L43+100 -> 1100 | M44: 0 | N44: =N43 -> 1605
B45: =B44+1 -> 27 | C45: =_xlfn.NORM.INV(RAND(),$F$6,$G$6) -> 0.22308585 | D45: =_xlfn.NORM.INV(RAND(),$F$7,$G$7) -> 0.06387444 | E45: =_xlfn.NORM.INV(RAND(),$F$8,$G$8) -> 0.1437501 | F45: =RAND()*($E$9-$D$9)+$D$9 -> 0.02581587 | G45: =IF(E45>F45,($C$12*(1+C45)*D45)/(E45-F45),0) -> 8215.5291 | H45: =G45+$C$13 -> 8908.7104 | I45: =H45/'Option value'!$E$10 -> 432.46167 | L45: =L44+100 -> 1200 | M45: 0 | N45: =N44 -> 1605
B46: =B45+1 -> 28 | C46: =_xlfn.NORM.INV(RAND(),$F$6,$G$6) -> 0.12289682 | D46: =_xlfn.NORM.INV(RAND(),$F$7,$G$7) -> 0.059946375 | E46: =_xlfn.NORM.INV(RAND(),$F$8,$G$8) -> 0.14870434 | F46: =RAND()*($E$9-$D$9)+$D$9 -> 0.055187887 | G46: =IF(E46>F46,($C$12*(1+C46)*D46)/(E46-F46),0) -> 8927.0124 | H46: =G46+$C$13 -> 9620.1937 | I46: =H46/'Option value'!$E$10 -> 466.99969 | L46: 1300 | M46: 0 | N46: =N45 -> 1605
B47: =B46+1 -> 29 | C47: =_xlfn.NORM.INV(RAND(),$F$6,$G$6) -> 0.50656221 | D47: =_xlfn.NORM.INV(RAND(),$F$7,$G$7) -> 0.059834094 | E47: =_xlfn.NORM.INV(RAND(),$F$8,$G$8) -> 0.1458616 | F47: =RAND()*($E$9-$D$9)+$D$9 -> 0.045462748 | G47: =IF(E47>F47,($C$12*(1+C47)*D47)/(E47-F47),0) -> 11135.211 | H47: =G47+$C$13 -> 11828.392 | I47: =H47/'Option value'!$E$10 -> 574.19378
B48: =B47+1 -> 30 | C48: =_xlfn.NORM.INV(RAND(),$F$6,$G$6) -> 0.22619166 | D48: =_xlfn.NORM.INV(RAND(),$F$7,$G$7) -> 0.065915713 | E48: =_xlfn.NORM.INV(RAND(),$F$8,$G$8) -> 0.14543951 | F48: =RAND()*($E$9-$D$9)+$D$9 -> 0.056050069 | G48: =IF(E48>F48,($C$12*(1+C48)*D48)/(E48-F48),0) -> 11213.791 | H48: =G48+$C$13 -> 11906.972 | I48: =H48/'Option value'!$E$10 -> 578.00837
B49: =B48+1 -> 31 | C49: =_xlfn.NORM.INV(RAND(),$F$6,$G$6) -> 0.097433105 | D49: =_xlfn.NORM.INV(RAND(),$F$7,$G$7) -> 0.066535878 | E49: =_xlfn.NORM.INV(RAND(),$F$8,$G$8) -> 0.14540519 | F49: =RAND()*($E$9-$D$9)+$D$9 -> 0.057720544 | G49: =IF(E49>F49,($C$12*(1+C49)*D49)/(E49-F49),0) -> 10327.657 | H49: =G49+$C$13 -> 11020.838 | I49: =H49/'Option value'!$E$10 -> 534.99214
B50: =B49+1 -> 32 | C50: =_xlfn.NORM.INV(RAND(),$F$6,$G$6) -> 0.17570964 | D50: =_xlfn.NORM.INV(RAND(),$F$7,$G$7) -> 0.064362053 | E50: =_xlfn.NORM.INV(RAND(),$F$8,$G$8) -> 0.15074593 | F50: =RAND()*($E$9-$D$9)+$D$9 -> 0.039902944 | G50: =IF(E50>F50,($C$12*(1+C50)*D50)/(E50-F50),0) -> 8466.6799 | H50: =G50+$C$13 -> 9159.8612 | I50: =H50/'Option value'!$E$10 -> 444.65346
B51: =B50+1 -> 33 | C51: =_xlfn.NORM.INV(RAND(),$F$6,$G$6) -> 0.31538872 | D51: =_xlfn.NORM.INV(RAND(),$F$7,$G$7) -> 0.066444721 | E51: =_xlfn.NORM.INV(RAND(),$F$8,$G$8) -> 0.14080159 | F51: =RAND()*($E$9-$D$9)+$D$9 -> 0.034627449 | G51: =IF(E51>F51,($C$12*(1+C51)*D51)/(E51-F51),0) -> 10209.094 | H51: =G51+$C$13 -> 10902.275 | I51: =H51/'Option value'!$E$10 -> 529.23667
B52: =B51+1 -> 34 | C52: =_xlfn.NORM.INV(RAND(),$F$6,$G$6) -> 0.25914233 | D52: =_xlfn.NORM.INV(RAND(),$F$7,$G$7) -> 0.058505555 | E52: =_xlfn.NORM.INV(RAND(),$F$8,$G$8) -> 0.14529035 | F52: =RAND()*($E$9-$D$9)+$D$9 -> 0.032785972 | G52: =IF(E52>F52,($C$12*(1+C52)*D52)/(E52-F52),0) -> 8120.7078 | H52: =G52+$C$13 -> 8813.8891 | I52: =H52/'Option value'!$E$10 -> 427.85869
